Workbook

Sheet Read me
A1: India agency account map and poaching target list
A2: Prepared for Mask360 new business. Research as of 29 Sep 2026.
A4: What is inside
A5: Target list | B5: One row per brand (908 brands), ranked by a 10 point priority score. Shows who holds the account today, what just changed and why now. 63 brands score A (9 or 10) and 177 score B (7 or 8). Yellow columns are yours to fill in.
A6: In play now | B6: Pitches, reviews, new marketing leaders and account moves from 2026, newest first. Start here for timing.
A7: Agency roster | B7: The answer to 'which agency has what': 187 agencies with their luxury and premium accounts listed first. (L) marks a luxury brand.
A8: Agency turmoil 2025-26 | B8: Mergers, sales, exits and probes that make an agency's clients poachable, each with a source and the accounts exposed.
A9: Category by group | B9: How many current relationships each holding company has in each category. The Unknown or in-house column counts brands with no credited agency.
A10: All relationships | B10: The full evidence base: 1226 brand to agency relationships, each with evidence, date, confidence and a source link. Filter by any column.
A12: How the priority score works
A13: Score = Fit + Tier + Timing | B13: Out of 10. A = 9 or 10, B = 7 or 8, C = 6 or less. The score and priority are live formulas: change Timing pts and they update (sort by Score to re-rank).
A14: Fit pts (0 to 4) | B14: How close the category is to Mask360's luxury and premium lanes: Luxury hospitality & travel 4; Jewellery & watches 4; Fashion & luxury retail 4; Real estate 4; Beauty & personal care 3; Alcobev 3; Automotive 3; Wellness, fitness & sport 3; BFSI & wealth 2; Premium F&B & QSR 2; Aviation 2; Consumer tech & D2C 1; E-commerce & quick commerce 1; FMCG 1; Telecom & media 1; Healthcare 1; Other 1; Education 0.
A15: Tier pts (0 to 3) | B15: Luxury 3, Premium 2, Mass 0. Tier is the research agents' judgement of the brand's positioning.
A16: Timing pts (0 to 3) | B16: Pitch or review live = 3. Strong triggers add 2 each: leadership change (at the brand or the incumbent agency), incumbent agency in turmoil (merger, sale, probe), open mandates (channels with no agency). Weak triggers add 1: no agency credited at all, split roster, long tenure, launch or fresh funding, renewal due. Capped at 3. 0 = no trigger found, or the brand moved agency since Mar 2026 and nothing is left open (honeymoon). Blue cells: overwrite them when you know better.
A17: Why now (triggers) | B17: Keyword flags read from the poaching signals. Treat them as a prompt to read the signal text, not as a verdict.
A18: Mask360 relationship | B18: Brands matching Mask360's current client names (per its skill files) are marked Client and ranked last. L'Oreal group brands are marked as an expansion opportunity rather than a poach. Correct this column if the client list has changed.
A20: Status and confidence
A21: Status | B21: Active = relationship confirmed and current. Won recently = new appointment in the last months. In review = pitch or review reported. Recently lost = the brand moved away (the new agency usually has its own row). Unclear = older or indirect evidence, relationship may have lapsed.
A22: Confidence | B22: High = trade press or agency site dated 2024 to 2026 stating the relationship. Medium = older, a campaign credit only, or a news feed link. Low = client logo, inference, or no agency found.
A23: Unknown or in-house | B23: Where research found no agency, the brand is still listed. These are often the easiest doors: the work is in-house or with small shops.
A25: How to use it
A26: 1. Filter | B26: Target list: filter Priority = A, then your categories. Read Current agency, Why now and Poaching signals.
A27: 2. Check | B27: Open Source 1 before any outreach. Verify anything marked Low confidence or 'unverified'.
A28: 3. Track | B28: Fill the yellow columns: Owner, Outreach status (dropdown), Next step, Notes. Example: Owner 'Kaavish', status 'Contacted', next step 'Intro via ex-colleague of new CMO'.
A29: 4. Refresh | B29: Agency rosters move monthly. Re-check the In play now sheet before each outreach sprint.
A31: Method and limits
A32: Sources | B32: Eleven parallel research streams covered WPP, Publicis, Omnicom (two streams), Dentsu, Havas, Cheil and Hakuhodo, independent creative agencies, independent digital and social agencies, luxury boutiques with PR and events, live pitches and leadership moves, and two brand-first sweeps of premium categories. Main sources were afaqs, Storyboard18, MediaNews4U, Social Samosa, Campaign Brief Asia, Adgully, Manifest, IMPACT, agency websites and award credits.
A33: Gaps | B33: The shared web search allowance ran out early, so most research came from reading trade press pages and news feeds directly. exchange4media, bestmediainfo and the SABRE site blocked direct access. Coverage is thinnest for luxury hotels, luxury fashion houses and in-house teams, where agency credits are rarely published.
A34: Checks | B34: Every row has evidence text. Rows without a working link are marked Low. A few poaching signals came from the researchers' own knowledge and are tagged 'unverified, check before outreach'.
A35: Not included | B35: Media-buying-only mandates, except where the brand is luxury or premium.

Sheet Target list
A1: Rank | B1: Brand | C1: Priority | D1: Score (of 10) | E1: Fit pts | F1: Tier pts | G1: Timing pts (edit) | H1: Category | I1: Brand tier | J1: Parent company | K1: Current agency and mandate | L1: Held by group | M1: Recently lost by | N1: Why now (triggers) | O1: Poaching signals | P1: Key evidence | Q1: Latest source | R1: Confidence | S1: Source 1 | T1: Source 2 | U1: Mask360 relationship | V1: Owner | W1: Outreach status | X1: Next step | Y1: Notes
A2: 1 | B2: De Beers Forevermark | C2: =IF(U2<>"","Client",IF(D2>=9,"A",IF(D2>=7,"B","C"))) -> A | D2: =E2+F2+G2 -> 10 | E2: 4 | F2: 3 | G2: 3 | H2: Jewellery & watches | I2: Luxury | J2: De Beers Group | K2: Grey 82.5 (Ogilvy) (Creative, since 2024); Dentsu Creative Isobar (Integrated, since 2025) | L2: Dentsu, WPP | N2: Leadership change, Incumbent turmoil, Split roster | O2: Split mandates: Forevermark creative sits with Dentsu Creative Isobar; unit now appears as Grey 82.5 (WPP consolidation).; Split mandate; 2026 De Beers India campaigns carry no agency credit; 82.5 Communications folded into Grey 82.5 in Jun 2026; team and brand transition; Luxury retail rollout in India needs ongoing social, content and PR; Dentsu India offices searched by tax authorities Sep 2026; COO South Asia retired Aug 2026 and Chief Client Officer exited Nov 2025; De Beers splits work across two networks; PR and luxury events not assigned publicly. | P2: Won integrated creative mandate after multi-agency pitch (Mumbai); launched 'This One's For Me' with Delhi flagship in Oct 2025. | Q2: 2025-04 | R2: High | S2: https://www.storyboard18.com/brand-marketing/82-5-communications-wins-creative-mandate-for-de-beers-group-44868.htm | T2: https://www.medianews4u.com/82-5-communications-secures-creative-mandate-for-de-beers/ | W2: Not started
A3: 2 | B3: Four Seasons Mumbai and Bengaluru | C3: =IF(U3<>"","Client",IF(D3>=9,"A",IF(D3>=7,"B","C"))) -> A | D3: =E3+F3+G3 -> 10 | E3: 4 | F3: 3 | G3: 3 | H3: Luxury hospitality & travel | I3: Luxury | J3: Four Seasons Hotels | K3: None credited (in-house or unknown) | L3: Unknown | N3: Open mandates, No agency credited | O3: Likely handled by global brand team plus property PR; property social and F&B content are open doors. | P3: No India agency mandate or campaign credit found in Indian trade press 2024 to 2026. | Q3: 2026-09 | R3: Low | W3: Not started
A4: 3 | B4: Hilton India | C4: =IF(U4<>"","Client",IF(D4>=9,"A",IF(D4>=7,"B","C"))) -> A | D4: =E4+F4+G4 -> 10 | E4: 4 | F4: 3 | G4: 3 | H4: Luxury hospitality & travel | I4: Luxury | J4: Hilton Worldwide | K4: McCann India (Creative); TBWA\Lintas (Creative) | L4: Omnicom | N4: Leadership change, Incumbent turmoil | O4: Hilton's global marketing leader Mark Weinstein exited in Sep 2026; India wedding and luxury brands need local content beyond the global campaign.; Merged agency still settling; leadership now Govind Pandey (CEO) and Russell Barrett | P4: McCann India created Hilton's Deepika Padukone film in the 'It Matters Where You Stay' campaign. | Q4: 2026-09 | R4: Medium | S4: https://www.afaqs.com/news/advertising/hilton-wants-indias-hustlers-to-feel-at-home-enough-to-dance-just-ask-deepika-12186053 | T4: https://www.tbwaindia.com/ | W4: Not started
A5: 4 | B5: Hyatt India | C5: =IF(U5<>"","Client",IF(D5>=9,"A",IF(D5>=7,"B","C"))) -> A | D5: =E5+F5+G5 -> 10 | E5: 4 | F5: 3 | G5: 3 | H5: Luxury hospitality & travel | I5: Luxury | J5: Hyatt Hotels Corporation | K5: TBWA\Lintas (Creative); TBWA\Lintas (ex Lintas Live) (Social, since 2024) unconfirmed; Animal (Creative, since 2024) unconfirmed | L5: Independent, Omnicom | N5: Leadership change, Incumbent turmoil, Split roster | O5: Merged agency still settling; leadership now Govind Pandey (CEO) and Russell Barrett; Hyatt created a new President India and Southwest Asia role (Vikas Chawla, Mar 2026); Lintas absorbed into TBWA after Omnicom and IPG merger.; Project-based credits suggest no single AOR; new India president may consolidate. | P5: Lintas Live, a MullenLowe Lintas division, conceptualised the 'Hyatt Celebrates You' launch of Hyatt India's official Instagram with Vaani Kapoor. | Q5: 2026-09 | R5: Medium | S5: https://www.afaqs.com/news/advertising/hyatt-india-launches-official-instagram-page-with-vaani-kapoor-8449076 | T5: https://www.afaqs.com/news/advertising/hyatt-india-launches-new-fb-campaign-to-highlight-its-culinary-legacy-7777415 | W5: Not started
A6: 5 | B6: M3M India | C6: =IF(U6<>"","Client",IF(D6>=9,"A",IF(D6>=7,"B","C"))) -> A | D6: =E6+F6+G6 -> 10 | E6: 4 | F6: 3 | G6: 3 | H6: Real estate | I6: Luxury | J6: M3M Group | K6: None credited (in-house or unknown) | L6: Unknown | N6: Leadership change, Fresh budget or launch, No agency credited | O6: New marketing head with agency background; aggressive Gurugram luxury launches and sports properties (pickleball franchise). | P6: No agency credit found; M3M appointed Nitin Singh, ex DDB Mudra, as Head of Marketing in Jan 2026. | Q6: 2026-01 | R6: Low | S6: https://www.medianews4u.com/m3m-appoints-nitin-singh-as-head-of-marketing/ | W6: Not started
A7: 6 | B7: Oberoi Realty | C7: =IF(U7<>"","Client",IF(D7>=9,"A",IF(D7>=7,"B","C"))) -> A | D7: =E7+F7+G7 -> 10 | E7: 4 | F7: 3 | G7: 3 | H7: Real estate | I7: Luxury | J7: Oberoi Realty | K7: Madison Loop (ex Madison BMB) (Integrated, since 2023) | L7: Independent | N7: Leadership change, Incumbent turmoil | O7: Incumbent about 3 years; typical review window.; Three year incumbent on a luxury realty account; Madison BMB CEO Raj Nair exited in the merger; Shift to storytelling-led brand films; Ritz-Carlton serviced residences at Three Sixty West show appetite for ultra luxury content. | P7: Madison Loop won Oberoi Realty's integrated creative, digital, social and performance mandate after a competitive pitch. | Q7: 2026-06 | R7: Medium | S7: https://www.afaqs.com/news/advertising/madison-bmb-integrates-with-madison-loop | T7: https://www.afaqs.com/news/advertising/madison-loop-wins-the-integrated-account-of-oberoi-realty | W7: Not started
A8: 7 | B8: Rivaah by Tanishq | C8: =IF(U8<>"","Client",IF(D8>=9,"A",IF(D8>=7,"B","C"))) -> A | D8: =E8+F8+G8 -> 10 | E8: 4 | F8: 3 | G8: 3 | H8: Jewellery & watches | I8: Luxury | J8: Titan Company | K8: TBWA\Lintas (Creative); TBWA\Lintas (Integrated) | L8: Omnicom | N8: Leadership change, Incumbent turmoil | O8: Long-tenured Lintas relationship now running as TBWA\Lintas after network merger; integration period.; Bridal and destination-wedding content is specialist territory; MullenLowe retired; Lintas rebadged TBWA\Lintas Jan 2026; co-CEO Prateek Bharadwaj exit reported Feb 2026 | P8: TBWA\Lintas conceptualised Rivaah by Tanishq's Sep 2026 wedding campaign under CMO Pelki Tshering. | Q8: 2026-09 | R8: Medium | S8: https://www.afaqs.com/news/advertising/rivaah-by-tanishq-brings-many-stories-to-one-wedding-12540691 | W8: Not started
A9: 8 | B9: Sobha | C9: =IF(U9<>"","Client",IF(D9>=9,"A",IF(D9>=7,"B","C"))) -> A | D9: =E9+F9+G9 -> 10 | E9: 4 | F9: 3 | G9: 3 | H9: Real estate | I9: Luxury | J9: Sobha Ltd | K9: None credited (in-house or unknown) | L9: Unknown | N9: Leadership change, Fresh budget or launch, No agency credited | O9: New brand head within the last year typically reviews agencies; Sobha's design-led luxury positioning fits a luxury boutique. | P9: No agency credit found; Ashish Bajaj joined to lead brand and communications in Oct 2025. | Q9: 2025-10 | R9: Low | S9: https://www.afaqs.com/people-spotting/ashish-bajaj-to-lead-brand-and-communications-at-sobha-limited-10563656 | W9: Not started
A10: 9 | B10: The Leela Palaces, Hotels and Resorts | C10: =IF(U10<>"","Client",IF(D10>=9,"A",IF(D10>=7,"B","C"))) -> A | D10: =E10+F10+G10 -> 10 | E10: 4 | F10: 3 | G10: 3 | H10: Luxury hospitality & travel | I10: Luxury | J10: Schloss Bangalore (Brookfield) | K10: None credited (in-house or unknown) | L10: Unknown | N10: Leadership change, Incumbent turmoil, Fresh budget or launch, No agency credited | O10: CMO churn (Shweta Jain exit May 2025, Anjali Mehra now leading marketing); record FY26 results and expansion push (Apr 2026); 40-year brand storytelling; prime luxury poach target. | P10: Leela's social campaigns (Padmanabh Singh Nov 2024, Gauravi Kumari Dec 2025) carried no agency credit; CMO Shweta Jain left in May 2025. | Q10: 2025-06 | R10: Low | S10: https://www.socialsamosa.com/industry-updates/shweta-jain-steps-down-cmo-sales-officer-the-leela-palaces-9356489 | W10: Not started
A11: 10 | B11: BMW India | C11: =IF(U11<>"","Client",IF(D11>=9,"A",IF(D11>=7,"B","C"))) -> A | D11: =E11+F11+G11 -> 9 | E11: 3 | F11: 3 | G11: 3 | H11: Automotive | I11: Luxury | J11: BMW Group | K11: Contract Advertising (VML) (Integrated, since 2026); Lodestar UM (Omnicom Media) (Media, since 2022); Interactive Avenues (Omnicom Media) (Digital); PMG India (Hakuhodo) (Experiential) | L11: Hakuhodo, Omnicom, WPP | M11: Rediffusion (Integrated) | N11: Leadership change, Incumbent turmoil, Split roster | O11: New incumbent, low near-term poachability; but social, content, experiential and dealer content can be carved out.; Account moved 2026-01 from Rediffusion; marketing director Vitesh Barar; WPP creative restructuring ongoing; Newly won in pitch; VML India creative head who oversaw Contract (Kalpesh Patankar) exited Aug 2026; Fresh pitch Jan 2026; MINI digital split out to SW Network; WPP network restructuring.; IPG Mediabrands retired into Omnicom Media post merger; creative just moved, media could follow; IPG Mediabrands folded into Omnicom Media; IA creative team integration under way; luxury auto; Experiential only; content and social separate; Brand just ran a review; signals willingness to change partners.; Account moved 2026-01 after about 4 years | P11: BMW India awarded integrated creative mandate (mainline plus digital) to VML's Contract Advertising after a competitive pitch, replacing Rediffusion. | Q11: 2026-08 | R11: High | S11: https://www.storyboard18.com/agency-news/exclusive-bmw-india-appoints-vmls-contract-advertising-india-as-creative-agency-87842.htm | T11: https://www.adgully.com/post/11327/contract-advertising-india-wins-integrated-creative-mandate-for-bmw-india | W11: Not started
A12: 11 | B12: Diageo India Reserve portfolio | C12: =IF(U12<>"","Client",IF(D12>=9,"A",IF(D12>=7,"B","C"))) -> A | D12: =E12+F12+G12 -> 9 | E12: 3 | F12: 3 | G12: 3 | H12: Alcobev | I12: Luxury | J12: Diageo India | K12: The Glitch (VML) (Integrated, since 2018) unconfirmed | L12: WPP | N12: Incumbent turmoil, Long tenure | O12: The Glitch shows no trade press activity after Apr 2024 and theglitch.in no longer resolves; likely absorbed into VML; Black & White work credited to Saatchi & Saatchi India at Storyboard18 Awards 2026 | P12: The Glitch expanded to a 360 degree mandate for Diageo India's premium, luxury and reserve brands in Feb 2020. | Q12: 2020-02 | R12: Medium | S12: https://www.medianews4u.com/the-glitch-expands-their-integrated-creative-portfolio-with-the-addition-of-diageo-indias-premium-luxury-and-reserve-brands/ | W12: Not started
A13: 12 | B13: Ducati India | C13: =IF(U13<>"","Client",IF(D13>=9,"A",IF(D13>=7,"B","C"))) -> A | D13: =E13+F13+G13 -> 9 | E13: 3 | F13: 3 | G13: 3 | H13: Automotive | I13: Luxury | J13: Ducati (Audi AG) | K13: Burson India (PR, since 2024) | L13: WPP | N13: Leadership change, Incumbent turmoil | O13: WPP hired Goldman Sachs in Apr 2026 to explore a sale of Burson; New head of marketing 2026-05 | P13: Ducati India elevated Amit Chauhan to head of marketing. | Q13: 2026-05 | R13: High | S13: https://www.medianews4u.com/ducati-india-appoints-burson-as-strategic-communications-partner/ | T13: https://www.afaqs.com/people-spotting/ducati-india-elevates-amit-chauhan-to-head-of-marketing-11805878 | W13: Not started
A14: 13 | B14: Kama Ayurveda | C14: =IF(U14<>"","Client",IF(D14>=9,"A",IF(D14>=7,"B","C"))) -> A | D14: =E14+F14+G14 -> 9 | E14: 3 | F14: 3 | G14: 3 | H14: Beauty & personal care | I14: Luxury | J14: Puig (majority) | K14: None credited (in-house or unknown) | L14: Unknown | N14: Leadership change, No agency credited | O14: Former marketing head moved to Heads Up For Tails (May 2026) | P14: Medianews4u search for Kama Ayurveda returned no agency credit. | Q14: 2026-09 | R14: Low | W14: Not started
A15: 14 | B15: Mercedes-Benz India | C15: =IF(U15<>"","Client",IF(D15>=9,"A",IF(D15>=7,"B","C"))) -> A | D15: =E15+F15+G15 -> 9 | E15: 3 | F15: 3 | G15: 3 | H15: Automotive | I15: Luxury | J15: Mercedes-Benz Group | K15: Adfactors PR (PR, since 2025); BBDO India (Integrated); PMG India (Hakuhodo) (Experiential); BBDO India (Creative); Social Beat (Cheil) (Social) unconfirmed | L15: Cheil, Hakuhodo, Independent, Omnicom | N15: Leadership change, Incumbent turmoil, Split roster | O15: New head of marketing Nandita Godbole elevated Jul 2026 (afaqs); creative, social and experiential partners not publicly mapped.; Dedicated Team X unit; luxury social, content and experiential could be carved out; BBDO India CEO Suraja Kishore exited Apr 2025; Jitender Dabas named BBDO Group CEO Feb 2026 as Mudra and Ulka folded in; Experiential only; social, content and PR are separate opportunities; New head of marketing Nandita Godbole (Jul 2026, succeeding Amrit Baid); marketing budget kept flat despite record sales; festive Dream Days campaign carried no agency credit.; New head of marketing from 2026-09 with AI and data focus; rival BMW moved creative 2026-01; New sports property 2026-07 needing content and experiential support; Social Beat was acquired by Cheil SWA Group (Nov 2025); post-acquisition integration and senior exits (AVP Dhruhi Sethi left Jan 2026). | P15: Team X BBDO India made the Sep 2025 'Dream Days' festive campaign and the Sep 2026 '140 Years. 140 Places.' India leg. | Q15: 2026-09 | R15: High | S15: https://www.adgully.com/post/611/mercedes-benz-india-awards-pr-mandate-to-adfactors-pr | T15: https://www.afaqs.com/people-spotting/mercedes-benz-india-elevates-nandita-godbole-as-head-of-marketing-12159853 | W15: Not started
A16: 15 | B16: MINI India | C16: =IF(U16<>"","Client",IF(D16>=9,"A",IF(D16>=7,"B","C"))) -> A | D16: =E16+F16+G16 -> 9 | E16: 3 | F16: 3 | G16: 3 | H16: Automotive | I16: Luxury | J16: BMW Group | K16: SW Network (Sociowash) (Digital, since 2026); VML India (Integrated) | L16: Independent, WPP | N16: Leadership change, Split roster, Long tenure | O16: Recently awarded; lifestyle content and influencer layers still open.; Appointed 2026-01 with no pitch disclosed; sister brand BMW moved creative the same month; BMW India mainline moved to Contract (WPP) in Jan 2026; MINI digital sits separately, split mandates; BMW India moved integrated communications to Contract Advertising the same week (Jan 2026), group roster in flux.; Split mandate inside BMW Group India (BMW creative with Contract); PR and experiential not assigned publicly.; VML India Group CCO Kalpesh Patankar exited Aug 2026 (to Leo Gulf) and CSO Pinaki Bhattacharya exited early 2026 after 16 years | P16: SW Network appointed digital and creative agency for MINI India covering strategy, campaigns and lifestyle content, handled from Delhi. | Q16: 2026-06 | R16: High | S16: https://www.storyboard18.com/agency-news/sw-network-wins-full-digital-mandate-for-mini-india-87868.htm | T16: https://www.afaqs.com/news/newbizwins/sw-network-wins-digital-creative-mandate-for-mini-india-11012093 | W16: Not started
A17: 16 | B17: Porsche India | C17: =IF(U17<>"","Client",IF(D17>=9,"A",IF(D17>=7,"B","C"))) -> A | D17: =E17+F17+G17 -> 9 | E17: 3 | F17: 3 | G17: 3 | H17: Automotive | I17: Luxury | J17: Porsche AG | K17: AdGlobal360 (Hakuhodo) (Digital); PMG India (Hakuhodo) (Experiential) | L17: Hakuhodo | N17: Leadership change, Split roster, Fresh budget or launch | O17: Split: PMG India handles Porsche experiential; New brand director within the last six months; Porsche globally cutting costs, so efficient local content partners appeal. | P17: AdGlobal360 won cross-channel marketing award for Porsche at e4m Automotive Marketing Awards 2026. | Q17: 2026-05 | R17: Medium | S17: https://www.hakuhodo-global.com/news/hakuhodo-india-network-secures-16-prestigious-awards-at-e4m-automotive-marketing-awards-2026.html | T17: https://www.afaqs.com/people-spotting/škoda-india-appoints-ashutosh-dixit-as-brand-director-of-porsche-india-11802850 | W17: Not started
A18: 17 | B18: Sazerac India (Paul John, Buffalo Trace) | C18: =IF(U18<>"","Client",IF(D18>=9,"A",IF(D18>=7,"B","C"))) -> A | D18: =E18+F18+G18 -> 9 | E18: 3 | F18: 3 | G18: 3 | H18: Alcobev | I18: Luxury | J18: Sazerac | K18: None credited (in-house or unknown) | L18: Unknown | N18: Leadership change, No agency credited | O18: New MD 2026-09 from Bimbo and PepsiCo | P18: Kunal Sharma joined Sazerac as MD India, overseeing Paul John, Buffalo Trace, Weller and Fireball. | Q18: 2026-09 | R18: High | S18: https://www.storyboard18.com/brand-makers/kunal-sharma-named-sazerac-india-managing-director-ws-l-110645.htm | W18: Not started
A19: 18 | B19: DLF | C19: =IF(U19<>"","Client",IF(D19>=9,"A",IF(D19>=7,"B","C"))) -> A | D19: =E19+F19+G19 -> 9 | E19: 4 | F19: 3 | G19: 2 | H19: Real estate | I19: Luxury | J19: DLF Ltd | K19: None credited (in-house or unknown) | L19: Unknown | N19: Fresh budget or launch, No agency credited | O19: Ultra luxury Gurugram launches sell on project marketing; luxury launch films and HNI content are pitchable per project; no visible incumbent. | P19: No creative or social agency credit found for DLF homes 2024 to 2026; DLF Malls' Summer Up campaign (May 2026) carried no agency credit; last public digital mandate was Envigo in 2015. | Q19: 2026-05 | R19: Low | S19: https://www.campaignindia.in/article/dlf-malls-launches-phygital-summer-up-campaign/4pvgt96ejphfhssc00m9ec3vmp | W19: Not started
A20: 19 | B20: Elan Group | C20: =IF(U20<>"","Client",IF(D20>=9,"A",IF(D20>=7,"B","C"))) -> A | D20: =E20+F20+G20 -> 9 | E20: 4 | F20: 3 | G20: 2 | H20: Real estate | I20: Luxury | J20: Elan Group | K20: None credited (in-house or unknown) | L20: Unknown | N20: Fresh budget or launch, No agency credited | O20: Big celebrity bet without visible agency; luxury Gurugram launches. | P20: No agency credit found; Elan signed Shah Rukh Khan as brand ambassador (Feb 2025) and hired an AGM Brand Marketing (Jul 2025). | Q20: 2025-02 | R20: Low | S20: https://www.afaqs.com/news/mktg/elan-group-onboards-shah-rukh-khan-as-brand-ambassador-8750776 | W20: Not started
A21: 20 | B21: Ethos Watches | C21: =IF(U21<>"","Client",IF(D21>=9,"A",IF(D21>=7,"B","C"))) -> A | D21: =E21+F21+G21 -> 9 | E21: 4 | F21: 3 | G21: 2 | H21: Jewellery & watches | I21: Luxury | J21: Ethos Ltd | K21: None credited (in-house or unknown) | L21: Unknown | N21: Fresh budget or launch, No agency credited | O21: Listed via 2024 IPO; expanding luxury watch retail; no visible agency | P21: Searched medianews4u for Ethos Watches; no agency appointment or campaign credit surfaced. | Q21: 2026-09 | R21: Low | W21: Not started
A22: 21 | B22: Experion Developers | C22: =IF(U22<>"","Client",IF(D22>=9,"A",IF(D22>=7,"B","C"))) -> A | D22: =E22+F22+G22 -> 9 | E22: 4 | F22: 3 | G22: 2 | H22: Real estate | I22: Luxury | J22: Experion Group | K22: None credited (in-house or unknown) | L22: Unknown | N22: Fresh budget or launch, No agency credited | O22: Leadership reshuffle; luxury Gurugram launches. | P22: No agency credit found; hired a VP Communications (Jan 2025) and named a deputy CEO. | Q22: 2025-01 | R22: Low | S22: https://www.afaqs.com/people-spotting/himanshu-raj-joins-juniper-green-energy-experion-developers-as-vp-communications-8598890 | W22: Not started
A23: 22 | B23: Galeries Lafayette India | C23: =IF(U23<>"","Client",IF(D23>=9,"A",IF(D23>=7,"B","C"))) -> A | D23: =E23+F23+G23 -> 9 | E23: 4 | F23: 3 | G23: 2 | H23: Fashion & luxury retail | I23: Luxury | J23: Galeries Lafayette | K23: None credited (in-house or unknown) | L23: Unknown | N23: Fresh budget or launch, No agency credited | O23: New brand marketing head 2026-08 ahead of India build out; agencies not disclosed | P23: Noopur Khandekar, ex SVP at Tilt Brand Solutions, joined as head of brand marketing for Galeries Lafayette India. | Q23: 2026-08 | R23: High | S23: https://www.afaqs.com/people-spotting/noopur-khandekar-joins-galeries-lafayette-india-as-brand-marketing-head-12391643 | W23: Not started
A24: 23 | B24: ITC Hotels | C24: =IF(U24<>"","Client",IF(D24>=9,"A",IF(D24>=7,"B","C"))) -> A | D24: =E24+F24+G24 -> 9 | E24: 4 | F24: 3 | G24: 2 | H24: Luxury hospitality & travel | I24: Luxury | J24: ITC Hotels Ltd | K24: Actimedia PR (PR, since 2021) unconfirmed | L24: Independent | N24: Incumbent turmoil | O24: New F&B marketing head 2026-08; Five year old PR relationship; ITC Hotels demerged and listed, acquiring Zuri Kumarakom and GHK (2026), new F&B marketing head (Aug 2026).; Newly independent listed company building its own brand voice; 'Responsible Luxury' platform, new acquisitions and Mementos luxury tier need premium content. | P24: ITC Hotels appointed Rajiv Singh as head of food and beverages marketing. | Q24: 2026-08 | R24: High | S24: https://www.afaqs.com/people-spotting/itc-hotels-appoints-rajiv-singh-as-head-food-beverages-marketing-12250848 | T24: https://www.exchange4media.com/pr-and-corporate-communication-news/itc-hotels-ropes-in-actimedia-as-pr-and-communications-partner-113939.html | W24: Not started
A25: 24 | B25: Krishna GVK Hotels (ex Taj GVK) | C25: =IF(U25<>"","Client",IF(D25>=9,"A",IF(D25>=7,"B","C"))) -> A | D25: =E25+F25+G25 -> 9 | E25: 4 | F25: 3 | G25: 2 | H25: Luxury hospitality & travel | I25: Luxury | J25: GVK Group | K25: None credited (in-house or unknown) | L25: Unknown | N25: Fresh budget or launch, No agency credited | O25: Full rebrand and identity launch across Hyderabad and Chennai hotels: new brand, new agency need. | P25: Taj GVK Hotels is to become Krishna GVK Hotels, exiting the Taj name (Jul 2026). | Q25: 2026-07 | R25: Low | S25: https://www.storyboard18.com/brand-marketing/taj-gvk-hotels-to-become-krishna-gvk-hotels-taj-gvk-hotels-to-become-krishna-gvk-hotels-ws-l-106223.htm | W25: Not started
A26: 25 | B26: Manish Malhotra | C26: =IF(U26<>"","Client",IF(D26>=9,"A",IF(D26>=7,"B","C"))) -> A | D26: =E26+F26+G26 -> 9 | E26: 4 | F26: 3 | G26: 2 | H26: Fashion & luxury retail | I26: Luxury | J26: Manish Malhotra (Reliance Brands stake) | K26: None credited (in-house or unknown) | L26: Unknown | N26: Fresh budget or launch, No agency credited | O26: Reliance Brands-backed expansion; in-house content | P26: No external agency credit surfaced for Manish Malhotra. | Q26: 2026-09 | R26: Low | W26: Not started
A27: 26 | B27: Reliance Brands (luxury franchise portfolio) | C27: =IF(U27<>"","Client",IF(D27>=9,"A",IF(D27>=7,"B","C"))) -> A | D27: =E27+F27+G27 -> 9 | E27: 4 | F27: 3 | G27: 2 | H27: Fashion & luxury retail | I27: Luxury | J27: Reliance Retail | K27: None credited (in-house or unknown) | L27: Unknown | N27: Fresh budget or launch, No agency credited | O27: 80+ franchise brands; local launch and PR briefs brand by brand | P27: No Reliance Brands agency appointment surfaced; international franchises typically use global brand assets. | Q27: 2026-09 | R27: Low | W27: Not started
A28: 27 | B28: The Leela Palace Jaipur | C28: =IF(U28<>"","Client",IF(D28>=9,"A",IF(D28>=7,"B","C"))) -> A | D28: =E28+F28+G28 -> 9 | E28: 4 | F28: 3 | G28: 2 | H28: Luxury hospitality & travel | I28: Luxury | J28: The Leela (Schloss Bangalore) | K28: Quirk Head (Digital) unconfirmed | L28: Independent | N28: Open mandates | O28: Property-level digital; Leela brand campaigns led by CMSO Shweta Jain with no agency credited (afaqs Nov 2024). | P28: Quirk Head website lists The Leela Palace Jaipur among its luxury hospitality clients. | Q28: 2026-09 | R28: Medium | S28: https://quirkhead.ae/ | W28: Not started
A29: 28 | B29: Tribeca Developers (Trump Towers India) | C29: =IF(U29<>"","Client",IF(D29>=9,"A",IF(D29>=7,"B","C"))) -> A | D29: =E29+F29+G29 -> 9 | E29: 4 | F29: 3 | G29: 2 | H29: Real estate | I29: Luxury | J29: Tribeca Developers | K29: None credited (in-house or unknown) | L29: Unknown | N29: Fresh budget or launch, No agency credited | O29: Ultra luxury branded residences launched city by city; launch content per project. | P29: No agency relationship found in Indian trade press for Tribeca or Trump Towers India. | Q29: 2026-09 | R29: Low | W29: Not started
A30: 29 | B30: Vianaar | C30: =IF(U30<>"","Client",IF(D30>=9,"A",IF(D30>=7,"B","C"))) -> A | D30: =E30+F30+G30 -> 9 | E30: 4 | F30: 3 | G30: 2 | H30: Real estate | I30: Luxury | J30: Vianaar | K30: PROHED (Performance, since 2026) | L30: Independent | N30: Open mandates | O30: Performance only 2026-03; brand creative and content not disclosed; Performance only; brand film, social and content for a design-led luxury developer unassigned publicly. | P30: PROHED won the performance marketing mandate for Vianaar. | Q30: 2026-03 | R30: High | S30: https://www.afaqs.com/news/newbizwins/prohed-bags-performance-marketing-mandate-for-vianaar-11220895 | W30: Not started
A31: 30 | B31: Whiteland Corporation | C31: =IF(U31<>"","Client",IF(D31>=9,"A",IF(D31>=7,"B","C"))) -> A | D31: =E31+F31+G31 -> 9 | E31: 4 | F31: 3 | G31: 2 | H31: Real estate | I31: Luxury | J31: Whiteland Corporation | K31: None credited (in-house or unknown) | L31: Unknown | N31: Fresh budget or launch, No agency credited | O31: Gurugram luxury launches with no visible agency support. | P31: No agency relationship found in Indian trade press. | Q31: 2026-09 | R31: Low | W31: Not started
A32: 31 | B32: Adani Realty | C32: =IF(U32<>"","Client",IF(D32>=9,"A",IF(D32>=7,"B","C"))) -> A | D32: =E32+F32+G32 -> 9 | E32: 4 | F32: 2 | G32: 3 | H32: Real estate | I32: Premium | J32: Adani Group | K32: 22feet Tribal Worldwide (Creative); Mirum India (VML) (Digital, since 2023) unconfirmed | L32: Omnicom, WPP | N32: Incumbent turmoil, Split roster, Fresh budget or launch | O32: Adani uses multiple agencies; Kinnect and 22feet leadership merged under Chandni Shah; unit says it will take only five new clients in 2026; Project scope; no recent credit visible; Adani Group put a Rs 500 to 600 crore media mandate up for review (Dec 2025); NCR expansion team newly built. | P32: Adani Realty and 22feet India released a Ganesh festival film on Bappa's homecoming in Sep 2026. | Q32: 2026-09 | R32: High | S32: https://campaignbriefasia.com/2026/09/23/adani-realty-and-22feet-india-celebrate-the-journey-of-bappas-homecoming/ | T32: https://www.medianews4u.com/adani-realty-collaborates-with-mirum-india-for-its-vr-offering/ | W32: Not started
A33: 32 | B33: Arvind SmartSpaces | C33: =IF(U33<>"","Client",IF(D33>=9,"A",IF(D33>=7,"B","C"))) -> A | D33: =E33+F33+G33 -> 9 | E33: 4 | F33: 2 | G33: 3 | H33: Real estate | I33: Premium | J33: Arvind Group | K33: None credited (in-house or unknown) | L33: Unknown | N33: Leadership change, No agency credited | O33: New head of marketing 2026-09 | P33: Arvind SmartSpaces appointed Ankit Dave as head of marketing. | Q33: 2026-09 | R33: High | S33: https://www.afaqs.com/people-spotting/arvind-smartspaces-appoints-ankit-dave-as-head-of-marketing-12583232 | W33: Not started
A34: 33 | B34: BIBA | C34: =IF(U34<>"","Client",IF(D34>=9,"A",IF(D34>=7,"B","C"))) -> A | D34: =E34+F34+G34 -> 9 | E34: 4 | F34: 2 | G34: 3 | H34: Fashion & luxury retail | I34: Premium | J34: Biba Apparels | K34: Famous Innovations (Creative); Dentsu Creative India (Creative, since 2022) unconfirmed | L34: Dentsu, Independent | M34: BBH India (ex Publicis India) (Creative) | N34: Leadership change, Incumbent turmoil | O34: Taproot brand retired in 2022 merger; later BIBA campaign credited to iProspect; Moved to Taproot Dentsu | P34: Biba is listed among Famous Innovations' existing clients. | Q34: 2026-04 | R34: High | S34: https://www.afaqs.com/news/advertising/famous-innovations-wins-5-major-mandates-in-h2-strengthens-geographical-expansion-11727022 | T34: https://www.medianews4u.com/taproot-dentsu-wins-creative-mandate-for-biba/ | W34: Not started
A35: 34 | B35: Brigade Group | C35: =IF(U35<>"","Client",IF(D35>=9,"A",IF(D35>=7,"B","C"))) -> A | D35: =E35+F35+G35 -> 9 | E35: 4 | F35: 2 | G35: 3 | H35: Real estate | I35: Premium | J35: Brigade Enterprises | K35: Webenza (Digital) unconfirmed; Social Beat (Cheil) (Performance) unconfirmed | L35: Cheil, Independent | N35: Leadership change, Incumbent turmoil, Split roster | O35: Brigade also appears on Social Beat's work page; split or rotating roster.; Bengaluru luxury, office and hospitality portfolio; no visible incumbent in trade press.; Social Beat was acquired by Cheil SWA Group (Nov 2025); post-acquisition integration and senior exits (AVP Dhruhi Sethi left Jan 2026). | P35: Webenza's homepage features a Brigade Group case study and logo. | Q35: 2026-09 | R35: Medium | S35: https://www.webenza.com/ | T35: https://www.socialbeat.in/work/ | W35: Not started
A36: 35 | B36: Club Mahindra (Club M) | C36: =IF(U36<>"","Client",IF(D36>=9,"A",IF(D36>=7,"B","C"))) -> A | D36: =E36+F36+G36 -> 9 | E36: 4 | F36: 2 | G36: 3 | H36: Luxury hospitality & travel | I36: Premium | J36: Mahindra Holidays & Resorts India | K36: None credited (in-house or unknown) | L36: Unknown | N36: Leadership change, Incumbent turmoil, No agency credited | O36: Rebrand plus CMO exit plus new group CEO for Real Estate and Hospitality (Aug 2026) plus adex cut 26% in FY25: classic moment for a new agency. | P36: No agency credit found; CMO Pratik Mazumder quit in Jun 2025 and the brand is rebranding to Club M with a Rs 1,000 crore leisure hospitality push. | Q36: 2025-11 | R36: Low | S36: https://www.storyboard18.com/brand-marketing/club-mahindra-to-rebrand-as-club-m-enters-leisure-hospitality-with-rs-1000-crore-investment-84498.htm | W36: Not started
A37: 36 | B37: Enamor | C37: =IF(U37<>"","Client",IF(D37>=9,"A",IF(D37>=7,"B","C"))) -> A | D37: =E37+F37+G37 -> 9 | E37: 4 | F37: 2 | G37: 3 | H37: Fashion & luxury retail | I37: Premium | J37: Gokaldas Intimatewear | K37: Tilt Brand Solutions (Integrated, since 2025); The Glitch (VML) (Integrated, since 2022) unconfirmed | L37: Independent, WPP | M37: BBH India (ex Publicis India) (Creative); Propagate India (Publicis) (Digital) | N37: Leadership change, Incumbent turmoil | O37: CBO Hari Krishnan exited Tilt in Oct 2025, servicing leadership changed; Tilt CBO Hari Krishnan exited Oct 2025; Tilt added Santoor AOR Apr 2026 (bandwidth).; The Glitch shows no trade press activity after Apr 2024 and theglitch.in no longer resolves; likely absorbed into VML; Moved to Tilt Brand Solutions; brand has changed agencies three times since 2022 | P37: Enamor appointed Tilt Brand Solutions as its brand and communications AOR. | Q37: 2025-03 | R37: High | S37: https://www.afaqs.com/news/newbizwins/enamor-appoints-tilt-brand-solutions-as-its-brand-communications-aor-8888963 | T37: https://www.medianews4u.com/enamor-names-tilt-brand-solutions-as-brand-communications-aor/ | W37: Not started
A38: 37 | B38: Ethnix by Raymond | C38: =IF(U38<>"","Client",IF(D38>=9,"A",IF(D38>=7,"B","C"))) -> A | D38: =E38+F38+G38 -> 9 | E38: 4 | F38: 2 | G38: 3 | H38: Fashion & luxury retail | I38: Premium | J38: Raymond Lifestyle Ltd | K38: Mudra (ex DDB Mudra, BBDO Group) (Creative, since 2022) unconfirmed | L38: Omnicom | N38: Incumbent turmoil, Split roster | O38: No recent credit; wedding-wear competition with Manyavar and Tasva; Premium ethnic wear sub-brand; DDB brand retired Jan 2026 and DDB Mudra split across McCann, BBDO Group (Mudra) and TBWA\Lintas; destination of this account not announced | P38: DDB Mudra Group created Ethnix by Raymond's family-themed campaign (Nov 2022). | Q38: 2022-11 | R38: Medium | S38: https://www.medianews4u.com/ethnix-by-raymond-celebrates-family-and-fashion-in-its-latest-campaign/ | T38: https://www.afaqs.com/news/advertising/ddb-mudra-wins-raymonds-integrated-aor-mandate | W38: Not started
A39: 38 | B39: Foot Locker India | C39: =IF(U39<>"","Client",IF(D39>=9,"A",IF(D39>=7,"B","C"))) -> A | D39: =E39+F39+G39 -> 9 | E39: 4 | F39: 2 | G39: 3 | H39: Fashion & luxury retail | I39: Premium | J39: Metro Brands | K39: Scribbld (Social, since 2025); SW Network (Sociowash) (Creative, since 2025); SW Network (Sociowash) (Integrated, since 2025) | L39: Independent | N39: Incumbent turmoil, Split roster | O39: Metro Brands gave Foot Locker mainline creative to SW Network two months later, possible consolidation risk; Split with SW Network, which took Foot Locker mainline creative in Nov 2025.; SW Network won Foot Locker mandates two months later; overlap or churn.; Scribbld holds Foot Locker digital and social since Sep 2025, split mandate; Scribbld had Foot Locker digital and social from Sep 2025; Metro Brands reshuffles quickly. | P39: SW Network won mainline creative duties for Foot Locker and digital creative for FILA from Metro Brands. | Q39: 2025-11 | R39: High | S39: https://www.afaqs.com/news/newbizwins/scribbld-wins-digital-and-social-media-mandate-for-foot-locker-india-10279212 | T39: https://www.medianews4u.com/scribbld-wins-digital-and-social-media-mandate-for-foot-locker-india/ | W39: Not started
A40: 39 | B40: Godrej Properties | C40: =IF(U40<>"","Client",IF(D40>=9,"A",IF(D40>=7,"B","C"))) -> A | D40: =E40+F40+G40 -> 9 | E40: 4 | F40: 2 | G40: 3 | H40: Real estate | I40: Premium | J40: Godrej Group | K40: Ogilvy India (Digital, since 2021) unconfirmed; Madison Loop (ex Madison BMB) (Integrated) unconfirmed; Gozoop (now YAAP) (Digital, since 2023) unconfirmed | L40: Independent, WPP | N40: Leadership change, Incumbent turmoil, Fresh budget or launch, Split roster | O40: No visible Ogilvy work since 2021; real estate digital scope may be open; Gozoop merged into YAAP in 2026; ORM-only scope leaves creative and social open.; Targeting Rs 40,000 crore of launches in FY26 across new cities; experiential and launch content briefs per project; MD and CEO Gaurav Pandey reappointed (Aug 2025). | P40: Gozoop Hawk bagged the digital customer service (ORM) mandate for Godrej Properties. | Q40: 2026-01 | R40: Medium | S40: https://www.medianews4u.com/godrej-properties-launches-its-first-digital-brand-campaign/ | T40: https://www.afaqs.com/news/advertising/madison-bmb-integrates-with-madison-loop | W40: Not started
A41: 40 | B41: IndiGo | C41: =IF(U41<>"","Client",IF(D41>=9,"A",IF(D41>=7,"B","C"))) -> A | D41: =E41+F41+G41 -> 9 | E41: 4 | F41: 2 | G41: 3 | H41: Luxury hospitality & travel | I41: Premium | J41: InterGlobe Aviation | K41: Nash8 (Digital) | L41: Independent | N41: Leadership change, Fresh budget or launch | O41: Co-brand work only; main brand creative unattributed.; New content and creative head 2026-09; New CEO Willie Walsh (Apr 2026), new VP Marketing and Digital Deepti Sampat (Jan 2026) and global expansion push (Jun 2026): fresh leadership, in-house leaning. | P41: IndiGo appointed Mayank Kumar as head of content and creative, marketing. | Q41: 2026-09 | R41: High | S41: https://www.afaqs.com/people-spotting/indigo-appoints-mayank-kumar-as-head-of-content-creative-marketing-12514196 | T41: https://www.campaignindia.in/article/pixel-perfect-how-nash8-turned-indigo-axis-bank-credit-card-launch-into-a-game-worth-playing/4p09sj3s31zrztgj67esjzmwdj | W41: Not started
A42: 41 | B42: K Raheja Corp | C42: =IF(U42<>"","Client",IF(D42>=9,"A",IF(D42>=7,"B","C"))) -> A | D42: =E42+F42+G42 -> 9 | E42: 4 | F42: 2 | G42: 3 | H42: Real estate | I42: Premium | J42: K Raheja Group | K42: None credited (in-house or unknown) | L42: Unknown | N42: Leadership change, No agency credited | O42: New CEO 2026-07; New CEO; group spans luxury residences, Chalet Hotels (Burson PR) and Inorbit malls. | P42: K Raheja Group appointed Vijayta Nikhil Raheja as CEO. | Q42: 2026-07 | R42: High | S42: https://www.afaqs.com/people-spotting/k-raheja-group-appoints-vijayta-nikhil-raheja-as-ceo-12208087 | W42: Not started
A43: 42 | B43: Kalpataru | C43: =IF(U43<>"","Client",IF(D43>=9,"A",IF(D43>=7,"B","C"))) -> A | D43: =E43+F43+G43 -> 9 | E43: 4 | F43: 2 | G43: 3 | H43: Real estate | I43: Premium | J43: Kalpataru Ltd | K43: Social Beat (Cheil) (Digital) | L43: Cheil | N43: Leadership change, Incumbent turmoil, Open mandates | O43: Digital-led execution; brand creative unassigned publicly.; Social Beat was acquired by Cheil SWA Group (Nov 2025); post-acquisition integration and senior exits (AVP Dhruhi Sethi left Jan 2026). | P43: Social Beat executed a programmatic DOOH campaign for Kalpataru targeting NRIs at Mumbai airport. | Q43: 2026-05 | R43: Medium | S43: https://www.afaqs.com/news/ooh/social-beat-executes-pdooh-campaign-for-kalpataru-at-mumbai-airport-11806525 | W43: Not started
A44: 43 | B44: Khazana Jewellery | C44: =IF(U44<>"","Client",IF(D44>=9,"A",IF(D44>=7,"B","C"))) -> A | D44: =E44+F44+G44 -> 9 | E44: 4 | F44: 2 | G44: 3 | H44: Jewellery & watches | I44: Premium | J44: Khazana Jewellery | K44: Social Beat (Cheil) (Digital, since 2024) | L44: Cheil | N44: Leadership change, Incumbent turmoil | O44: Social Beat was acquired by Cheil SWA Group (Nov 2025); post-acquisition integration and senior exits (AVP Dhruhi Sethi left Jan 2026). | P44: Khazana Jewellery chose Social Beat for creative campaigns, Google and Meta, and collection video content. | Q44: 2024-01 | R44: High | S44: https://www.afaqs.com/news/advertising/khazana-jewellery-chooses-social-beat-for-digital-mandate | W44: Not started
A45: 44 | B45: Limelight Lab Grown Diamonds | C45: =IF(U45<>"","Client",IF(D45>=9,"A",IF(D45>=7,"B","C"))) -> A | D45: =E45+F45+G45 -> 9 | E45: 4 | F45: 2 | G45: 3 | H45: Jewellery & watches | I45: Premium | J45: Limelight Diamonds | K45: None credited (in-house or unknown) | L45: Unknown | N45: Leadership change, Fresh budget or launch, No agency credited | O45: INR 250 Cr fundraise; new CMO Rupali Shrivastava (May 2025); Shilpa Shetty investor and ambassador | P45: Limelight announced vertical integration and an INR 250 Cr fundraise (Dec 2025); no agency named. | Q45: 2025-12 | R45: Low | S45: https://www.medianews4u.com/limelight-lab-grown-diamonds-announces-vertical-integration-inr-250-cr-fundraise-to-accelerate-growth/ | W45: Not started
A46: 45 | B46: MakeMyTrip | C46: =IF(U46<>"","Client",IF(D46>=9,"A",IF(D46>=7,"B","C"))) -> A | D46: =E46+F46+G46 -> 9 | E46: 4 | F46: 2 | G46: 3 | H46: Luxury hospitality & travel | I46: Premium | J46: MakeMyTrip Ltd | K46: Moonshot (Creative); TBWA\Lintas (Creative); Dentsu Creative Webchutney (Digital, since 2022) unconfirmed | L46: Dentsu, Independent, Omnicom | N46: Leadership change, Incumbent turmoil, Fresh budget or launch, Split roster | O46: Merged agency still settling; leadership now Govind Pandey (CEO) and Russell Barrett; Four-year-old mandate, no recent public credits found; Abhinav Narula elevated to SVP Marketing (May 2026); India IPO filing and creator programme with Meta; performance-first culture. | P46: Moonshot won an IndIAA 2025 award for MakeMyTrip work. | Q46: 2026-09 | R46: High | S46: https://www.manifest-media.in/advertising/081025/indiaa-awards-2025-moonshot-and-ogilvy-dominate-with-four-wins-each.html | T46: https://www.dentsu.com/in/en/our-news/dentsu-webchutney-wins-digital-mandate-for-make-my-trip | W46: Not started
A47: 46 | B47: Malabar Gold & Diamonds | C47: =IF(U47<>"","Client",IF(D47>=9,"A",IF(D47>=7,"B","C"))) -> A | D47: =E47+F47+G47 -> 9 | E47: 4 | F47: 2 | G47: 3 | H47: Jewellery & watches | I47: Premium | J47: Malabar Group | K47: Mudra (ex DDB Mudra, BBDO Group) (Creative) | L47: Omnicom | N47: Leadership change, Fresh budget or launch | O47: New Head of Marketing Prajith VM (Aug 2025); MS Dhoni signed Jul 2026; ZOUL, Nuwa, Nayraa launches 2026 without agency credit; India plus GCC | P47: DDB Mudra conceptualised Malabar's 'Solitaire One' campaign with Alia Bhatt (Jan 2025). | Q47: 2025-01 | R47: Medium | S47: https://www.exchange4media.com/advertising-news/malabar-gold-diamonds-campaign-with-alia-bhatt-celebrates-the-charm-of-solitaires-140391.html | W47: Not started
A48: 47 | B48: Manyavar | C48: =IF(U48<>"","Client",IF(D48>=9,"A",IF(D48>=7,"B","C"))) -> A | D48: =E48+F48+G48 -> 9 | E48: 4 | F48: 2 | G48: 3 | H48: Fashion & luxury retail | I48: Premium | J48: Vedant Fashions | K48: McCann India (Creative); Mirum India (VML) (Digital, since 2023) unconfirmed; WPP Media (Media, since 2024) unconfirmed | L48: Omnicom, WPP | N48: Leadership change, Fresh budget or launch, Split roster | O48: Work led by Prasoon Joshi, now Chairman of Omnicom Advertising India and off day-to-day; Chief Marketing and Digital Officer Anand Narang since Sep 2023; creative partner not visible; Mirum India MD and co founder Mihir Karkare stepped down Jan 2025; South India expansion | P48: McCann Worldgroup India created 'Aap Kab Ban Rahe Hain Manyavar?' groom campaign. | Q48: 2024-10 | R48: Medium | S48: https://www.medianews4u.com/manyavar-awards-digital-transformation-mandate-to-mirum-india-and-wt-commerce/ | T48: https://www.medianews4u.com/manyavar-enters-south-india-with-ram-charan-as-brands-face-in-ooh-campaign-conceptualized-by-groupm-ooh-solutions/ | W48: Not started
A49: 48 | B49: Mia by Tanishq | C49: =IF(U49<>"","Client",IF(D49>=9,"A",IF(D49>=7,"B","C"))) -> A | D49: =E49+F49+G49 -> 9 | E49: 4 | F49: 2 | G49: 3 | H49: Jewellery & watches | I49: Premium | J49: Titan Company | K49: Digital Refresh Networks (Digital, since 2021) unconfirmed; Famous Innovations (Creative) unconfirmed; Schbang (Creative) unconfirmed; Schbang (Social) unconfirmed | L49: Independent | N49: Leadership change, Fresh budget or launch, Split roster | O49: New marketing lead 2026-07; Five years old; Schbang also credits a Mia range launch, suggesting a shifting roster.; New Marketing Lead Sneha Kanukolanu joined Jul 2026; Aug 2026 Rakhi film carried no agency credit; Aneet Padda new ambassador; Digital Refresh Networks also won Mia's digital mandate (2021); roster appears project-based.; Mia hired a new marketing lead, Sneha Kanukolanu, in Jul 2026 (afaqs). | P49: Sneha Kanukolanu joined Mia by Tanishq as marketing lead. | Q49: 2026-09 | R49: High | S49: https://www.afaqs.com/people-spotting/sneha-kanukolanu-joins-mia-by-tanishq-as-marketing-lead-12158434 | T49: https://www.medianews4u.com/digital-refresh-networks-bags-the-digital-mandate-for-mia-by-tanishq-motherhood-ivf-and-ikounsellor/ | W49: Not started
A50: 49 | B50: Myntra | C50: =IF(U50<>"","Client",IF(D50>=9,"A",IF(D50>=7,"B","C"))) -> A | D50: =E50+F50+G50 -> 9 | E50: 4 | F50: 2 | G50: 3 | H50: Fashion & luxury retail | I50: Premium | J50: Myntra Designs (Flipkart) | K50: SW Network (Sociowash) (Experiential, since 2026); Braindad (Creative); Tilt Brand Solutions (Creative); McCann India (Creative); Mudra (ex DDB Mudra, BBDO Group) (Creative) unconfirmed | L50: Independent, Omnicom | N50: Pitch or review live, Leadership change, Incumbent turmoil, Split roster | O50: Myntra splits work between Tilt, Braindad and SW Network; Myntra also hands influencer programmes to SW Network's Youthbeat, split roster; Post-merger agency transition; Myntra pushing premium fashion and beauty; Myntra called a creative pitch for EORS in Apr 2026; Tilt Brand Solutions made the Mar 2026 birthday campaign; marketing leader Sunder Balasubramanian exited Sep 2026; CMO exit Sep 2026 could trigger review; CMO exit 2026-09; former CEO Nandita Sinha moved to Swiggy Instamart 2026-07; new CMO likely to review roster | P50: Tilt created Myntra's multi star campaigns including the Alia Bhatt and Ranbir Kapoor BFF film (Sep 2026). | Q50: 2026-09 | R50: High | S50: https://www.medianews4u.com/myntra-launches-high-energy-m-now-campaign-featuring-sumukhi-suresh-vihaan-samat-sakshi-shivdasani-ayesha-kanga/ | T50: https://campaignbriefasia.com/2025/06/25/ddb-mudra-india-and-myntra-unveil-m-now-campaign-spotlighting-instant-style-solutions/ | W50: Not started
A51: 50 | B51: Nykaa Fashion | C51: =IF(U51<>"","Client",IF(D51>=9,"A",IF(D51>=7,"B","C"))) -> A | D51: =E51+F51+G51 -> 9 | E51: 4 | F51: 2 | G51: 3 | H51: Fashion & luxury retail | I51: Premium | J51: FSN E-Commerce (Nykaa) | K51: None credited (in-house or unknown) | L51: Unknown | N51: Leadership change, No agency credited | O51: CEO Nihir Parikh exited Dec 2024; new faces Ishaan Khatter and Shanaya Kapoor | P51: Nykaa Fashion's campaigns and new faces (Jun 2025) are announced without agency credits. | Q51: 2025-06 | R51: Low | S51: https://www.medianews4u.com/nykaa-fashion-names-ishaan-khatter-shanaya-kapoor-as-new-faces-of-the-brand/ | W51: Not started
A52: 51 | B52: Origen Realty | C52: =IF(U52<>"","Client",IF(D52>=9,"A",IF(D52>=7,"B","C"))) -> A | D52: =E52+F52+G52 -> 9 | E52: 4 | F52: 2 | G52: 3 | H52: Real estate | I52: Premium | J52: Origen Realty | K52: None credited (in-house or unknown) | L52: Unknown | N52: Leadership change, No agency credited | O52: New CMO Poulomi Ray joined 2026-04 | P52: Origen Realty appointed Poulomi Ray as chief marketing officer. | Q52: 2026-04 | R52: High | S52: https://www.afaqs.com/people-spotting/origen-realty-appoints-poulomi-ray-as-chief-marketing-officer-11737049 | W52: Not started
A53: 52 | B53: Pothys | C53: =IF(U53<>"","Client",IF(D53>=9,"A",IF(D53>=7,"B","C"))) -> A | D53: =E53+F53+G53 -> 9 | E53: 4 | F53: 2 | G53: 3 | H53: Fashion & luxury retail | I53: Premium | J53: Pothys | K53: Social Beat (Cheil) (Content, since 2025) | L53: Cheil | N53: Leadership change, Incumbent turmoil | O53: Social Beat was acquired by Cheil SWA Group (Nov 2025); post-acquisition integration and senior exits (AVP Dhruhi Sethi left Jan 2026). | P53: Social Beat secured the SEO and content mandate for Pothys. | Q53: 2025-05 | R53: High | S53: https://www.medianews4u.com/social-beat-secures-seo-and-content-mandate-for-pothys/ | W53: Not started
A54: 53 | B54: Provident Housing (Puravankara) | C54: =IF(U54<>"","Client",IF(D54>=9,"A",IF(D54>=7,"B","C"))) -> A | D54: =E54+F54+G54 -> 9 | E54: 4 | F54: 2 | G54: 3 | H54: Real estate | I54: Premium | J54: Puravankara Ltd | K54: Ulka (BBDO Group) (Creative, since 2024) | L54: Omnicom | N54: Incumbent turmoil, Open mandates | O54: FCB now part of Omnicom post IPG merger; Puravankara flagship luxury brand appears unassigned.; Two-year incumbent now inside BBDO Group; sister premium brand Purva a separate opening | P54: FCB Ulka's Bengaluru office won the creative mandate for Provident Housing, Puravankara's mid-premium brand. | Q54: 2024-06 | R54: High | S54: https://www.socialsamosa.com/industry-updates/fcb-ulka-creative-mandate-provident-housing-4755687 | T54: https://www.medianews4u.com/fcb-ulka-bags-creative-mandate-for-provident-housing/ | W54: Not started
A55: 54 | B55: Radisson Hotel Group India | C55: =IF(U55<>"","Client",IF(D55>=9,"A",IF(D55>=7,"B","C"))) -> A | D55: =E55+F55+G55 -> 9 | E55: 4 | F55: 2 | G55: 3 | H55: Luxury hospitality & travel | I55: Premium | J55: Radisson Hotel Group | K55: None credited (in-house or unknown) | L55: Unknown | N55: Leadership change, Fresh budget or launch, Open mandates, No agency credited | O55: Targeting 160 hotels in India by 2026; new marketing lead; many openings need launch content. | P55: No agency credit found; Radisson appointed a new Director Area Marketing and Communications South Asia in Jan 2026. | Q55: 2026-05 | R55: Low | S55: https://www.storyboard18.com/brand-marketing/radisson-targets-160-hotels-19500-rooms-in-india-by-2026-amid-expansion-push-97096.htm | W55: Not started
A56: 55 | B56: Raymond | C56: =IF(U56<>"","Client",IF(D56>=9,"A",IF(D56>=7,"B","C"))) -> A | D56: =E56+F56+G56 -> 9 | E56: 4 | F56: 2 | G56: 3 | H56: Fashion & luxury retail | I56: Premium | J56: Raymond Lifestyle Ltd | K56: Omnicom (unit not named) (Creative); Mudra (ex DDB Mudra, BBDO Group) (Creative, since 2022) unconfirmed; Madison Loop (ex Madison BMB) (Integrated) unconfirmed | L56: Independent, Omnicom | N56: Incumbent turmoil, Split roster | O56: Raymond Lifestyle demerged and listed 2024; CEO Satyaki Ghosh; AOR nearly four years old (pitch cycle due); DDB brand retired Jan 2026 and DDB Mudra split across McCann, BBDO Group (Mudra) and TBWA\Lintas; destination of this account not announced | P56: Medianews4u credits Omnicom with conceptualising Raymond's 'The Complete Man' fatherhood campaign (Feb 2026). | Q56: 2026-02 | R56: Medium | S56: https://www.afaqs.com/news/advertising/ddb-mudra-wins-raymonds-integrated-aor-mandate | T56: https://www.afaqs.com/news/advertising/madison-bmb-integrates-with-madison-loop | W56: Not started
A57: 56 | B57: Raymond Lifestyle | C57: =IF(U57<>"","Client",IF(D57>=9,"A",IF(D57>=7,"B","C"))) -> A | D57: =E57+F57+G57 -> 9 | E57: 4 | F57: 2 | G57: 3 | H57: Fashion & luxury retail | I57: Premium | J57: Raymond | K57: None credited (in-house or unknown) | L57: Unknown | N57: Leadership change, No agency credited | O57: New CEO 2026-01 and new omnichannel media head 2026-09 | P57: Vineet Shah joined Raymond Lifestyle as head of omnichannel media; Satyaki Ghosh became CEO in 2026-01. | Q57: 2026-09 | R57: High | S57: https://www.afaqs.com/people-spotting/vineet-shah-joins-raymond-lifestyle-as-head-omnichannel-media-12573726 | W57: Not started
A58: 57 | B58: Tanishq | C58: =IF(U58<>"","Client",IF(D58>=9,"A",IF(D58>=7,"B","C"))) -> A | D58: =E58+F58+G58 -> 9 | E58: 4 | F58: 2 | G58: 3 | H58: Jewellery & watches | I58: Premium | J58: Titan Company (Tata Group) | K58: Grey 82.5 (Ogilvy) (Creative); TBWA\Lintas (Creative); HiveMinds (Madison) (Performance, since 2026); Dentsu Creative Webchutney (Digital, since 2021) unconfirmed; Talented (Creative) unconfirmed | L58: Dentsu, Independent, Omnicom, WPP | N58: Leadership change, Incumbent turmoil, Split roster, Long tenure, Fresh budget or launch | O58: Split mandate: Lowe Lintas makes Tanishq's main festive and diamond campaigns; Grey India merged into Grey 82.5 in Jun 2026 under 82.5 leadership; ex Grey India CCO Harsh Kapadia joined Code and Theory Jul 2026; Decades-long incumbent; heavy 2026 launch slate (gemstones, natural diamonds, gold exchange); CMO Pelki Tshering testing new formats like ChatGPT Ads; Decades-long Lintas incumbency (fatigue); MullenLowe retired; Lintas rebadged TBWA\Lintas Jan 2026; co-CEO Prateek Bharadwaj exit reported Feb 2026; Digital split from creative; experimentation budget; Digital incumbent 5 years with no recent visible credit; Five-plus year incumbent, no 2025-26 credits found; fatigue risk; Dentsu India offices searched by tax authorities Sep 2026; COO South Asia retired Aug 2026 and Chief Client Officer exited Nov 2025; Tanishq's lead brand work sits with Lowe Lintas (IndIAA 2025 Tanishq Rivaah), Talented is project based | P58: TBWA\Lintas conceptualised the Rivaah by Tanishq film 'One Wedding. Many Stories.' (Sep 2026), continuing Lintas-made Tanishq festive work such as Mriganka and Nav-Raani. | Q58: 2026-09 | R58: High | S58: https://www.afaqs.com/news/advertising/tanishq-challenges-empowerment-norms-in-womens-day-campaign-her-choice-8828061 | T58: https://www.medianews4u.com/rivaah-by-tanishq-unveils-one-wedding-many-stories-campaign-celebrating-modern-indian-weddings/ | W58: Not started
A59: 58 | B59: Tata Realty and Tata Housing | C59: =IF(U59<>"","Client",IF(D59>=9,"A",IF(D59>=7,"B","C"))) -> A | D59: =E59+F59+G59 -> 9 | E59: 4 | F59: 2 | G59: 3 | H59: Real estate | I59: Premium | J59: Tata Sons | K59: None credited (in-house or unknown) | L59: Unknown | N59: Leadership change, No agency credited | O59: Brand new CEO; CSMO Sarthak Seth; leadership change is the strongest trigger for agency review. | P59: No agency credit found; Tata Realty and Tata Housing appointed Gaurav Jain as MD and CEO in Sep 2026 after Sanjay Dutt's eight-year tenure. | Q59: 2026-09 | R59: Low | S59: https://www.medianews4u.com/tata-realty-and-tata-housing-appoint-gaurav-jain-as-managing-director-and-ceo/ | W59: Not started
A60: 59 | B60: TCNS (W, Aurelia) | C60: =IF(U60<>"","Client",IF(D60>=9,"A",IF(D60>=7,"B","C"))) -> A | D60: =E60+F60+G60 -> 9 | E60: 4 | F60: 2 | G60: 3 | H60: Fashion & luxury retail | I60: Premium | J60: Aditya Birla Fashion and Retail | K60: None credited (in-house or unknown) | L60: Unknown | N60: Incumbent turmoil, No agency credited | O60: Merged into ABFRL; womenswear brands may be re-rostered | P60: No TCNS agency credit surfaced in medianews4u fashion-mandate sweeps. | Q60: 2026-09 | R60: Low | W60: Not started
A61: 60 | B61: The House of Abhinandan Lodha | C61: =IF(U61<>"","Client",IF(D61>=9,"A",IF(D61>=7,"B","C"))) -> A | D61: =E61+F61+G61 -> 9 | E61: 4 | F61: 2 | G61: 3 | H61: Real estate | I61: Premium | J61: HoABL | K61: None credited (in-house or unknown) | L61: Unknown | N61: Leadership change, No agency credited | O61: Heavy celebrity spend (Ranbir Kapoor, Kartik Aaryan, Esha Deol for Alibaug villas); new CMO since 2025; luxury villa projects need luxury content. | P61: Ranbir Kapoor film for The Sarayu in Ayodhya (May 2026) credited no agency; CMO Saurabh Jain joined Apr 2025 from Zydus Wellness. | Q61: 2026-05 | R61: Low | S61: https://www.medianews4u.com/the-house-of-abhinandan-lodha-launches-new-campaign-for-the-sarayu-in-ayodhyaji-featuring-ranbir-kapoor/ | W61: Not started
A62: 61 | B62: Thomas Cook India and SOTC | C62: =IF(U62<>"","Client",IF(D62>=9,"A",IF(D62>=7,"B","C"))) -> A | D62: =E62+F62+G62 -> 9 | E62: 4 | F62: 2 | G62: 3 | H62: Luxury hospitality & travel | I62: Premium | J62: Thomas Cook (India) Ltd (Fairfax) | K62: None credited (in-house or unknown) | L62: Unknown | N62: Leadership change, No agency credited | O62: New MD and CEO Mahesh Iyer (Feb 2025); leaning on AI avatars and regional ambassadors, so content-led pitch could land. | P62: Kartik Aaryan forex card film (Apr 2025) and AI ambassador TACY (Dec 2025) carried no agency credit. | Q62: 2025-04 | R62: Low | S62: https://www.afaqs.com/news/advertising/thomas-cook-india-taps-kartik-aaryan-to-promote-borderless-travel-card-8920861 | W62: Not started
A63: 62 | B63: VIRGIO | C63: =IF(U63<>"","Client",IF(D63>=9,"A",IF(D63>=7,"B","C"))) -> A | D63: =E63+F63+G63 -> 9 | E63: 4 | F63: 2 | G63: 3 | H63: Fashion & luxury retail | I63: Premium | J63: VIRGIO | K63: None credited (in-house or unknown) | L63: Unknown | N63: Leadership change, No agency credited | O63: New CMO 2026-07 | P63: VIRGIO appointed Hansa Nigam as chief marketing officer. | Q63: 2026-07 | R63: High | S63: https://www.afaqs.com/people-spotting/virgio-appoints-hansa-nigam-as-chief-marketing-officer-12138383 | W63: Not started
A64: 63 | B64: World Gold Council India | C64: =IF(U64<>"","Client",IF(D64>=9,"A",IF(D64>=7,"B","C"))) -> A | D64: =E64+F64+G64 -> 9 | E64: 4 | F64: 2 | G64: 3 | H64: Jewellery & watches | I64: Premium | J64: World Gold Council | K64: BBDO India (Creative) | L64: Omnicom | N64: Leadership change, Incumbent turmoil | O64: Jewellery category fit for luxury specialists; BBDO India CEO Suraja Kishore exited Apr 2025; Jitender Dabas named BBDO Group CEO Feb 2026 as Mudra and Ulka folded in | P64: BBDO India created 'The Moment Is Gold' for WGC India in Sep 2025, repositioning gold jewellery for Gen Z across TV, OTT and social. | Q64: 2025-09 | R64: High | S64: https://campaignbriefasia.com/2025/09/24/bbdo-india-and-world-gold-council-celebrate-lifes-everyday-moments-with-gold/ | W64: Not started
A65: 64 | B65: 360 ONE Wealth | C65: =IF(U65<>"","Client",IF(D65>=9,"A",IF(D65>=7,"B","C"))) -> B | D65: =E65+F65+G65 -> 8 | E65: 2 | F65: 3 | G65: 3 | H65: BFSI & wealth | I65: Luxury | J65: 360 ONE WAM | K65: None credited (in-house or unknown) | L65: Unknown | N65: Open mandates, No agency credited | O65: UHNI wealth manager with low marketing visibility; content, events and thought-leadership are open. | P65: No agency credit found; only leadership moves surfaced (asset business CEO designate 2024, chief growth and people officer). | Q65: 2024-07 | R65: Low | S65: https://www.storyboard18.com/brand-makers/360-one-appoints-raghav-iyengar-as-ceo-designate-of-asset-business-36564.htm | W65: Not started
A66: 65 | B66: Spirit of Kashmyr (Radico Khaitan) | C66: =IF(U66<>"","Client",IF(D66>=9,"A",IF(D66>=7,"B","C"))) -> B | D66: =E66+F66+G66 -> 8 | E66: 3 | F66: 3 | G66: 2 | H66: Alcobev | I66: Luxury | J66: Radico Khaitan | K66: None credited (in-house or unknown) | L66: Unknown | N66: Fresh budget or launch, No agency credited | O66: New luxury launch; creative agency not visible | P66: Radico's integrated launch for luxury vodka Spirit of Kashmyr (Jul 2025) credits no agency. | Q66: 2025-07 | R66: Low | S66: https://www.medianews4u.com/radico-khaitan-doing-an-integrated-campaign-to-celebrate-its-debut-in-the-luxury-vodka-segment-with-the-spirit-of-kashmyr/ | W66: Not started
A67: 66 | B67: Ambuja Neotia | C67: =IF(U67<>"","Client",IF(D67>=9,"A",IF(D67>=7,"B","C"))) -> B | D67: =E67+F67+G67 -> 8 | E67: 4 | F67: 3 | G67: 1 | H67: Real estate | I67: Luxury | J67: Ambuja Neotia Group | K67: None credited (in-house or unknown) | L67: Unknown | N67: No agency credited | O67: Kolkata luxury real estate and hospitality group; regional agencies likely. | P67: No agency relationship found in Indian trade press. | Q67: 2026-09 | R67: Low | W67: Not started
A68: 67 | B68: Amrapali Jewels | C68: =IF(U68<>"","Client",IF(D68>=9,"A",IF(D68>=7,"B","C"))) -> B | D68: =E68+F68+G68 -> 8 | E68: 4 | F68: 3 | G68: 1 | H68: Jewellery & watches | I68: Luxury | J68: Amrapali | K68: None credited (in-house or unknown) | L68: Unknown | N68: No agency credited | O68: Luxury heritage label, likely in-house | P68: No agency credit surfaced in jewellery-mandate sweeps. | Q68: 2026-09 | R68: Low | W68: Not started
A69: 68 | B69: Anita Dongre (House of Anita Dongre) | C69: =IF(U69<>"","Client",IF(D69>=9,"A",IF(D69>=7,"B","C"))) -> B | D69: =E69+F69+G69 -> 8 | E69: 4 | F69: 3 | G69: 1 | H69: Fashion & luxury retail | I69: Luxury | J69: House of Anita Dongre | K69: VML India (Digital, since 2018) unconfirmed | L69: WPP | N69: Long tenure | O69: Only visible agency work is 2018; multiple labels (Grassroot, AND, Global Desi) | P69: VMLY&R India was hired for UX and creative revamp of Anita Dongre's website (Oct 2018); no later agency found. | Q69: 2018-10 | R69: Low | S69: https://www.medianews4u.com/vmlyr-india-to-work-on-user-experience-and-creative-revamp-of-anita-dongres-website/ | W69: Not started
A70: 69 | B70: Antara Senior Living | C70: =IF(U70<>"","Client",IF(D70>=9,"A",IF(D70>=7,"B","C"))) -> B | D70: =E70+F70+G70 -> 8 | E70: 4 | F70: 3 | G70: 1 | H70: Real estate | I70: Luxury | J70: Max Group | K70: Bang in the Middle (Creative, since 2024) | L70: Independent | N70: Fresh budget or launch | O70: Premium senior living is expanding to new cities; two years in. | P70: Antara Senior Care appointed Bang in the Middle as communication agency for launches of its senior residences across India. | Q70: 2024-06 | R70: High | S70: https://www.storyboard18.com/agency-news/antara-senior-living-appoints-bang-in-the-middle-as-its-creative-agency-33413.htm | W70: Not started
A71: 70 | B71: Balenciaga | C71: =IF(U71<>"","Client",IF(D71>=9,"A",IF(D71>=7,"B","C"))) -> B | D71: =E71+F71+G71 -> 8 | E71: 4 | F71: 3 | G71: 1 | H71: Fashion & luxury retail | I71: Luxury | J71: Kering | K71: Grapes Worldwide (Digital) unconfirmed | L71: Independent | N71: Fresh budget or launch | O71: Kering launched a global media review in 2026 amid Gucci slowdown (storyboard18); undated logo, verify India scope. | P71: Balenciaga appears among Grapes Worldwide client logos. | Q71: 2026-09 | R71: Medium | S71: https://www.grapesworldwide.com/ | W71: Not started
A72: 71 | B72: Conscient Infrastructure | C72: =IF(U72<>"","Client",IF(D72>=9,"A",IF(D72>=7,"B","C"))) -> B | D72: =E72+F72+G72 -> 8 | E72: 4 | F72: 3 | G72: 1 | H72: Real estate | I72: Luxury | J72: Conscient | K72: None credited (in-house or unknown) | L72: Unknown | N72: No agency credited | O72: Gurugram luxury developer with low public agency footprint. | P72: No agency relationship found in Indian trade press. | Q72: 2026-09 | R72: Low | W72: Not started
A73: 72 | B73: Good Earth | C73: =IF(U73<>"","Client",IF(D73>=9,"A",IF(D73>=7,"B","C"))) -> B | D73: =E73+F73+G73 -> 8 | E73: 4 | F73: 3 | G73: 1 | H73: Fashion & luxury retail | I73: Luxury | J73: Good Earth (Anita Lal) | K73: None credited (in-house or unknown) | L73: Unknown | N73: No agency credited | O73: Design-led luxury house, in-house content; strong boutique fit | P73: Searched medianews4u for Good Earth; no agency credit surfaced. | Q73: 2026-09 | R73: Low | W73: Not started
A74: 73 | B74: Gucci | C74: =IF(U74<>"","Client",IF(D74>=9,"A",IF(D74>=7,"B","C"))) -> B | D74: =E74+F74+G74 -> 8 | E74: 4 | F74: 3 | G74: 1 | H74: Fashion & luxury retail | I74: Luxury | J74: Kering | K74: Grapes Worldwide (Digital) unconfirmed | L74: Independent | N74: Fresh budget or launch | O74: Kering launched a global media review in 2026 amid Gucci slowdown (storyboard18); undated logo, verify India scope. | P74: Gucci appears among Grapes Worldwide client logos. | Q74: 2026-09 | R74: Medium | S74: https://www.grapesworldwide.com/ | W74: Not started
A75: 74 | B75: Hermes India | C75: =IF(U75<>"","Client",IF(D75>=9,"A",IF(D75>=7,"B","C"))) -> B | D75: =E75+F75+G75 -> 8 | E75: 4 | F75: 3 | G75: 1 | H75: Fashion & luxury retail | I75: Luxury | J75: Hermes | K75: Crosshairs Communication (PR, since 2009) | L75: Independent | N75: Long tenure | O75: Incumbent about 17 years; boutique holding a top-tier maison. | P75: Crosshairs case study says it has managed Hermes PR in India since 2009, incl. launches and international media visits. | Q75: 2026-09 | R75: Medium | S75: https://crosshairscommunication.com/case-studies/ | W75: Not started
A76: 75 | B76: Lodha (Macrotech Developers) | C76: =IF(U76<>"","Client",IF(D76>=9,"A",IF(D76>=7,"B","C"))) -> B | D76: =E76+F76+G76 -> 8 | E76: 4 | F76: 3 | G76: 1 | H76: Real estate | I76: Luxury | J76: Macrotech Developers Ltd | K76: None credited (in-house or unknown) | L76: Unknown | N76: No agency credited | O76: Refreshed brand team; ultra luxury Mumbai projects and data centre diversification (Jan 2026) need premium storytelling. | P76: No agency credit found; Lodha elevated Sneha Shenoy to AVP Brand and Marketing (May 2026) after she led corporate brand and media. | Q76: 2026-05 | R76: Low | S76: https://www.socialsamosa.com/industry-updates/lodha-sneha-shenoy-avp-brand-marketing-11871387 | W76: Not started
A77: 76 | B77: Nexus Select Citywalk | C77: =IF(U77<>"","Client",IF(D77>=9,"A",IF(D77>=7,"B","C"))) -> B | D77: =E77+F77+G77 -> 8 | E77: 4 | F77: 3 | G77: 1 | H77: Fashion & luxury retail | I77: Luxury | J77: Nexus Select Trust (Blackstone) | K77: SW Network (Sociowash) (Integrated) | L77: Independent | N77: Long tenure, Renewal due | O77: Long tenure luxury mall account, retained in 2025 so next review likely 2027; Annual renewal; five-year incumbent, fatigue risk.; Long-running incumbent; retained in 2025. | P77: SW Network retained the creative and digital mandate for Nexus Select Citywalk, Delhi. | Q77: 2025-05 | R77: High | S77: https://www.afaqs.com/news/newbizwins/sw-network-retains-creative-and-digital-mandate-for-nexus-select-citywalk-delhi-9316678 | T77: https://www.medianews4u.com/sw-network-retains-creative-and-digital-mandate-for-nexus-select-citywalk-delhi/ | W77: Not started
A78: 77 | B78: Platinum Guild International | C78: =IF(U78<>"","Client",IF(D78>=9,"A",IF(D78>=7,"B","C"))) -> B | D78: =E78+F78+G78 -> 8 | E78: 4 | F78: 3 | G78: 1 | H78: Jewellery & watches | I78: Luxury | J78: Platinum Guild International | K78: Famous Innovations (Creative) | L78: Independent | N78: Long tenure | O78: Long running relationship, possible fatigue | P78: Platinum Guild International is listed among Famous Innovations' existing clients. | Q78: 2026-04 | R78: High | S78: https://www.afaqs.com/news/advertising/famous-innovations-wins-5-major-mandates-in-h2-strengthens-geographical-expansion-11727022 | W78: Not started
A79: 78 | B79: Puravankara (luxury) | C79: =IF(U79<>"","Client",IF(D79>=9,"A",IF(D79>=7,"B","C"))) -> B | D79: =E79+F79+G79 -> 8 | E79: 4 | F79: 3 | G79: 1 | H79: Real estate | I79: Luxury | J79: Puravankara Ltd | K79: None credited (in-house or unknown) | L79: Unknown | N79: No agency credited | O79: Separate luxury brand line needs a luxury specialist. | P79: No agency credit found for Puravankara's luxury brand in 2024 to 2026 trade press. | Q79: 2026-09 | R79: Low | W79: Not started
A80: 79 | B80: Sabyasachi | C80: =IF(U80<>"","Client",IF(D80>=9,"A",IF(D80>=7,"B","C"))) -> B | D80: =E80+F80+G80 -> 8 | E80: 4 | F80: 3 | G80: 1 | H80: Fashion & luxury retail | I80: Luxury | J80: Sabyasachi Couture (ABFRL 51% stake) | K80: None credited (in-house or unknown) | L80: Unknown | N80: No agency credited | O80: Luxury house, in-house content; hard but prestigious target | P80: No external agency credit found; Sabyasachi runs communication in-house. | Q80: 2026-09 | R80: Low | W80: Not started
A81: 80 | B81: Six Senses Fort Barwara | C81: =IF(U81<>"","Client",IF(D81>=9,"A",IF(D81>=7,"B","C"))) -> B | D81: =E81+F81+G81 -> 8 | E81: 4 | F81: 3 | G81: 1 | H81: Luxury hospitality & travel | I81: Luxury | J81: IHG (Six Senses) | K81: None credited (in-house or unknown) | L81: Unknown | N81: No agency credited | O81: Destination wedding and wellness hotspot; content and PR likely property-led and pitchable. | P81: No India agency mandate found for Six Senses Fort Barwara in Indian trade press. | Q81: 2026-09 | R81: Low | W81: Not started
A82: 81 | B82: SUJÁN Luxury | C82: =IF(U82<>"","Client",IF(D82>=9,"A",IF(D82>=7,"B","C"))) -> B | D82: =E82+F82+G82 -> 8 | E82: 4 | F82: 3 | G82: 1 | H82: Luxury hospitality & travel | I82: Luxury | J82: SUJÁN | K82: None credited (in-house or unknown) | L82: Unknown | N82: No agency credited | O82: Founder-led ultra luxury brand with global audience; content and film partner is a natural fit. | P82: No agency relationship found for SUJÁN camps and palaces in Indian trade press. | Q82: 2026-09 | R82: Low | W82: Not started
A83: 82 | B83: Sunita Shekhawat | C83: =IF(U83<>"","Client",IF(D83>=9,"A",IF(D83>=7,"B","C"))) -> B | D83: =E83+F83+G83 -> 8 | E83: 4 | F83: 3 | G83: 1 | H83: Jewellery & watches | I83: Luxury | J83: Sunita Shekhawat | K83: None credited (in-house or unknown) | L83: Unknown | N83: No agency credited | O83: Luxury designer jeweller, likely in-house | P83: No agency credit surfaced in jewellery-mandate sweeps. | Q83: 2026-09 | R83: Low | W83: Not started
A84: 83 | B84: Taj Hotels (IHCL) | C84: =IF(U84<>"","Client",IF(D84>=9,"A",IF(D84>=7,"B","C"))) -> B | D84: =E84+F84+G84 -> 8 | E84: 4 | F84: 3 | G84: 1 | H84: Luxury hospitality & travel | I84: Luxury | J84: Indian Hotels Company Ltd (Tata) | K84: Rediffusion (Creative, since 2022) unconfirmed; BBH India (Creative) unconfirmed; Crosshairs Communication (PR) unconfirmed | L84: Independent, Publicis | N84: Split roster, Fresh budget or launch | O84: No public agency news since 2022; IHCL split into two verticals under Accelerate 2030 (700 hotels target) and registered a Taj sound mark in Jan 2026, so brand, content and launch briefs keep coming.; Appears project based; IHCL used Rediffusion for 'She Remains the Taj' (2022); prime luxury target; Undated client list that also carries legacy names; verify current status.; Iconic palace with global luxury audience; property content, wedding and experiential storytelling can be pitched as a specialist add-on to IHCL. | P84: Taj Lands End listed under hospitality on Crosshairs client page. | Q84: 2026-09 | R84: Medium | S84: https://www.exchange4media.com/advertising-news/rediffusion-collaborates-with-ihcl-for-launch-of-she-remains-the-taj-120348.html | T84: https://www.medianews4u.com/publicis-groupe-south-asia-appoints-paritosh-srivastava-and-snehasis-bose-to-lead-bbh-india/ | W84: Not started
A85: 84 | B85: Tata CLiQ Luxury | C85: =IF(U85<>"","Client",IF(D85>=9,"A",IF(D85>=7,"B","C"))) -> B | D85: =E85+F85+G85 -> 8 | E85: 4 | F85: 3 | G85: 1 | H85: Fashion & luxury retail | I85: Luxury | J85: Tata Digital | K85: None credited (in-house or unknown) | L85: Unknown | N85: No agency credited | O85: Frequent sale campaigns; luxury platform with no visible agency | P85: Tata CLiQ Luxury's Festive Investigation Bureau (Sep 2026) and Twinkle Khanna sale films carry no agency credit. | Q85: 2026-09 | R85: Low | S85: https://www.medianews4u.com/tata-cliq-luxury-turns-festive-shopping-into-an-investigation-with-festive-investigation-bureau/ | W85: Not started
A86: 85 | B86: The Diamond Collective (Natural Diamond Council) | C86: =IF(U86<>"","Client",IF(D86>=9,"A",IF(D86>=7,"B","C"))) -> B | D86: =E86+F86+G86 -> 8 | E86: 4 | F86: 3 | G86: 1 | H86: Jewellery & watches | I86: Luxury | J86: Natural Diamond Council | K86: None credited (in-house or unknown) | L86: Unknown | N86: No agency credited | O86: Rebrand and new strategy 2026-09 with new global campaigns; agencies not named | P86: Natural Diamond Council relaunched as The Diamond Collective under new CEO Amber Pepper, with a Diamond Desire Index launching in India. | Q86: 2026-09 | R86: High | S86: https://www.manifest-media.in/marketing/240926/natural-diamond-council-relaunches-as-the-diamond-collective-with-new.html | W86: Not started
A87: 86 | B87: The Oberoi Group (EIH) | C87: =IF(U87<>"","Client",IF(D87>=9,"A",IF(D87>=7,"B","C"))) -> B | D87: =E87+F87+G87 -> 8 | E87: 4 | F87: 3 | G87: 1 | H87: Luxury hospitality & travel | I87: Luxury | J87: EIH Ltd (Oberoi Group) | K87: None credited (in-house or unknown) | L87: Unknown | N87: No agency credited | O87: Low public agency footprint makes it hard to read but high prestige; approach via content and film craft. | P87: No current creative or social agency credit found; only an older Mirum India marketing cloud mandate surfaced for Oberoi Hotels. | Q87: 2026-09 | R87: Low | S87: https://www.agencyreporter.com/oberoi-hotels-appoints-mirum-india-for-marketing-cloud-services/ | W87: Not started
A88: 87 | B88: Tree of Life Resorts | C88: =IF(U88<>"","Client",IF(D88>=9,"A",IF(D88>=7,"B","C"))) -> B | D88: =E88+F88+G88 -> 8 | E88: 4 | F88: 3 | G88: 1 | H88: Luxury hospitality & travel | I88: Luxury | J88: Tree of Life Resorts & Spas | K88: None credited (in-house or unknown) | L88: Unknown | N88: No agency credited | O88: Small boutique chain, likely freelance or in-house social; easy entry via retainer. | P88: No agency relationship found for Tree of Life boutique resorts. | Q88: 2026-09 | R88: Low | W88: Not started
A89: 88 | B89: Adidas India | C89: =IF(U89<>"","Client",IF(D89>=9,"A",IF(D89>=7,"B","C"))) -> B | D89: =E89+F89+G89 -> 8 | E89: 3 | F89: 2 | G89: 3 | H89: Wellness, fitness & sport | I89: Premium | J89: adidas AG | K89: Famous Innovations (Creative) | L89: Independent | N89: Leadership change, Fresh budget or launch | O89: New Brand Director Atish Negi (Dec 2025); Suhana Khan face; Ranveer Singh Superstar collab (Apr 2026) | P89: Adidas is listed among Famous Innovations' existing clients. | Q89: 2026-04 | R89: High | S89: https://www.afaqs.com/news/advertising/famous-innovations-wins-5-major-mandates-in-h2-strengthens-geographical-expansion-11727022 | T89: https://www.medianews4u.com/atish-negi-appointed-brand-director-at-adidas-india/ | W89: Not started
A90: 89 | B90: Bacardi India | C90: =IF(U90<>"","Client",IF(D90>=9,"A",IF(D90>=7,"B","C"))) -> B | D90: =E90+F90+G90 -> 8 | E90: 3 | F90: 2 | G90: 3 | H90: Alcobev | I90: Premium | J90: Bacardi India | K90: Grey 82.5 (Ogilvy) (Creative, since 2024); Grey 82.5 (Ogilvy) (Integrated, since 2024); Homegrown (Content) | L90: Independent, WPP | N90: Leadership change, Incumbent turmoil, Split roster, Fresh budget or launch | O90: New Director Marketing Goodies Narayanan (Dec 2025); Mahesh Kanchan now MD India and SEA (Jul 2026); Breezer Bold launch Sep 2026; Nearly two years in; WPP now brands the unit Grey 82.5 (restructuring).; New Bacardi India marketing director Goodies Narayanan (Dec 2025) and MD Mahesh Kanchan widened to India and SEA (Jul 2026); 82.5 Communications folded into Grey 82.5 in Jun 2026; team and brand transition; Culture and experiential work split from network creative; New MD 2026-07 | P90: Bacardi appointed Mahesh Kanchan as MD for India and Southeast Asia. | Q90: 2026-07 | R90: High | S90: https://www.medianews4u.com/82-5-communications-wins-the-mandate-for-bacardi-indias-brands/ | T90: https://www.afaqs.com/news/advertising/825-communications-secures-creative-duties-for-bacardi-india-brands-8443722 | W90: Not started
A91: 90 | B91: Bella Vita | C91: =IF(U91<>"","Client",IF(D91>=9,"A",IF(D91>=7,"B","C"))) -> B | D91: =E91+F91+G91 -> 8 | E91: 3 | F91: 2 | G91: 3 | H91: Beauty & personal care | I91: Premium | J91: Bella Vita Organic | K91: None credited (in-house or unknown) | L91: Unknown | N91: Incumbent turmoil, No agency credited | O91: Fast-growing fragrance D2C; frequent marketing leadership churn | P91: Bellavita's Nov 2024 'Deo bachche lagate hai' campaign and Bigg Boss sponsorship listings name no agency. | Q91: 2024-11 | R91: Low | S91: https://www.medianews4u.com/bellavitas-campaign-deo-bachche-lagate-hai-aims-to-reposition-perfumes-as-a-luxurious-upgrade-to-deodorants/ | W91: Not started
A92: 91 | B92: Blenders Pride | C92: =IF(U92<>"","Client",IF(D92>=9,"A",IF(D92>=7,"B","C"))) -> B | D92: =E92+F92+G92 -> 8 | E92: 3 | F92: 2 | G92: 3 | H92: Alcobev | I92: Premium | J92: Pernod Ricard India | K92: None credited (in-house or unknown) | L92: Unknown | N92: Leadership change, No agency credited | O92: New CMO; Fashion Tour IP with FDCI suits luxury content partner | P92: Blenders Pride Fashion Tour campaign (Dec 2025) credits no agency. | Q92: 2025-12 | R92: Low | S92: https://www.medianews4u.com/blenders-pride-fashion-tour-powered-by-fdci-sets-fashions-next-move-with-new-campaign/ | W92: Not started
A93: 92 | B93: Corona | C93: =IF(U93<>"","Client",IF(D93>=9,"A",IF(D93>=7,"B","C"))) -> B | D93: =E93+F93+G93 -> 8 | E93: 3 | F93: 2 | G93: 3 | H93: Alcobev | I93: Premium | J93: AB InBev India | K93: Publicis Digital Experience (ex Digitas) (Digital) unconfirmed | L93: Publicis | N93: Leadership change, Incumbent turmoil | O93: Digitas CEO Unny Radhakrishnan exited Sep 2025 and Digitas was merged into PDX Jan 2026 | P93: Digitas India created Corona's sunset view rating system for luxury hotels (Apr 2024). | Q93: 2024-04 | R93: Medium | S93: https://www.medianews4u.com/coronas-launches-a-campaign-around-sunset-views/ | W93: Not started
A94: 93 | B94: Dewar's | C94: =IF(U94<>"","Client",IF(D94>=9,"A",IF(D94>=7,"B","C"))) -> B | D94: =E94+F94+G94 -> 8 | E94: 3 | F94: 2 | G94: 3 | H94: Alcobev | I94: Premium | J94: Bacardi India | K94: BBDO India (Creative, since 2020) unconfirmed | L94: Omnicom | N94: Leadership change, Incumbent turmoil | O94: Six-year-old mandate with no recent credits; BBDO India CEO Suraja Kishore exited Apr 2025; Jitender Dabas named BBDO Group CEO Feb 2026 as Mudra and Ulka folded in | P94: Bacardi appointed BBDO India to handle strategy and creative for Dewar's in Jul 2020. | Q94: 2020-07 | R94: Medium | S94: https://news.google.com/rss/search?q=%22BBDO+India%22+mandate&hl=en-IN&gl=IN&ceid=IN:en | W94: Not started
A95: 94 | B95: Eicher Motors | C95: =IF(U95<>"","Client",IF(D95>=9,"A",IF(D95>=7,"B","C"))) -> B | D95: =E95+F95+G95 -> 8 | E95: 3 | F95: 2 | G95: 3 | H95: Automotive | I95: Premium | J95: Eicher Motors | K95: TBWA\Lintas (Creative) unconfirmed | L95: Omnicom | N95: Leadership change, Incumbent turmoil | O95: Account lead exited Apr 2025; TBWA India merged into TBWA\Lintas Jan 2026; co-lead Prateek Bharadwaj reported exiting Feb 2026 | P95: afaqs says exiting TBWA\India executive director Ranjeev Vij handled Eicher Motors among his key clients. | Q95: 2025-04 | R95: Medium | S95: https://www.afaqs.com/people-spotting/ranjeev-vij-moves-on-from-tbwaindia-9009481 | W95: Not started
A96: 95 | B96: Gillette | C96: =IF(U96<>"","Client",IF(D96>=9,"A",IF(D96>=7,"B","C"))) -> B | D96: =E96+F96+G96 -> 8 | E96: 3 | F96: 2 | G96: 3 | H96: Beauty & personal care | I96: Premium | J96: Procter & Gamble India | K96: BBDO India (Creative) | L96: Omnicom | N96: Leadership change, Incumbent turmoil | O96: BBDO India CEO Suraja Kishore exited Apr 2025; Jitender Dabas named BBDO Group CEO Feb 2026 as Mudra and Ulka folded in | P96: Social Samosa lists Gillette among BBDO India's key brands (Dec 2025). | Q96: 2025-12 | R96: Medium | S96: https://www.socialsamosa.com/samosa-snippets/bbdo-tbwa-mccann-bring-omnicom-reshaped-empire-10841609 | W96: Not started
A97: 96 | B97: Honasa emerging brands (The Derma Co, Aqualogica, Dr. Sheth's, BBlunt) | C97: =IF(U97<>"","Client",IF(D97>=9,"A",IF(D97>=7,"B","C"))) -> B | D97: =E97+F97+G97 -> 8 | E97: 3 | F97: 2 | G97: 3 | H97: Beauty & personal care | I97: Premium | J97: Honasa Consumer | K97: None credited (in-house or unknown) | L97: Unknown | N97: Leadership change, Incumbent turmoil, Fresh budget or launch, No agency credited | O97: New leadership for emerging brands; category expansion | P97: Honasa named a new Business Head for emerging brands (May 2026); no agency named. | Q97: 2026-05 | R97: Low | S97: https://www.medianews4u.com/honasa-consumer-names-saahil-nayar-as-business-head-senior-vice-president-to-lead-emerging-brands/ | W97: Not started
A98: 97 | B98: Jawa Motorcycles | C98: =IF(U98<>"","Client",IF(D98>=9,"A",IF(D98>=7,"B","C"))) -> B | D98: =E98+F98+G98 -> 8 | E98: 3 | F98: 2 | G98: 3 | H98: Automotive | I98: Premium | J98: Classic Legends | K98: TBWA\Lintas (Creative, since 2024) | L98: Omnicom | N98: Leadership change, Incumbent turmoil | O98: Heritage premium bikes (Yezdi, BSA siblings); MullenLowe retired; Lintas rebadged TBWA\Lintas Jan 2026; co-CEO Prateek Bharadwaj exit reported Feb 2026 | P98: Classic Legends appointed Lowe Lintas as creative AOR for Jawa. | Q98: 2024-02 | R98: High | S98: https://www.medianews4u.com/lowe-lintas-wins-jawa-motorcycles-creative-mandate/ | W98: Not started
A99: 98 | B99: JSW MG Motor India | C99: =IF(U99<>"","Client",IF(D99>=9,"A",IF(D99>=7,"B","C"))) -> B | D99: =E99+F99+G99 -> 8 | E99: 3 | F99: 2 | G99: 3 | H99: Automotive | I99: Premium | J99: JSW MG Motor India | K99: Grey 82.5 (Ogilvy) (Creative, since 2024) unconfirmed; Cheil X (Creative) unconfirmed; Punctuate Productions (Content) unconfirmed; Value 360 Communications (PR) unconfirmed | L99: Cheil, Independent, WPP | N99: Leadership change, Incumbent turmoil, Split roster | O99: Split mandate with Cheil X; new MD Anurag Mehrotra from Feb 2025; 82.5 Communications folded into Grey 82.5 in Jun 2026; team and brand transition; New chairman 2026-08; JSW also in talks for Volkswagen India; JSW to become largest shareholder (May 2026) and Parth Jindal named chairman (Aug 2026): ownership shift likely triggers agency realignment; MG Select luxury line needs premium creative.; Cheil X CEO Jitender Dabas left for BBDO India in 2026; no 2025-26 MG credit found; Fragmented roster across festive and EV work.; Undated client mention; mandate scope not stated. | P99: JSW MG Motor India appointed Parth Jindal as chairman. | Q99: 2026-09 | R99: High | S99: https://www.medianews4u.com/82-5-communications-india-secures-the-creative-mandate-for-jsw-mg-motor-india/ | T99: https://www.afaqs.com/people-spotting/jsw-mg-motor-india-appoints-parth-jindal-as-chairman-12458026 | W99: Not started
A100: 99 | B100: Juicy Chemistry | C100: =IF(U100<>"","Client",IF(D100>=9,"A",IF(D100>=7,"B","C"))) -> B | D100: =E100+F100+G100 -> 8 | E100: 3 | F100: 2 | G100: 3 | H100: Beauty & personal care | I100: Premium | J100: Juicy Chemistry | K100: Social Beat (Cheil) (Digital, since 2024) unconfirmed | L100: Cheil | N100: Leadership change, Incumbent turmoil | O100: Social Beat was acquired by Cheil SWA Group (Nov 2025); post-acquisition integration and senior exits (AVP Dhruhi Sethi left Jan 2026). | P100: Social Beat secured the digital mandate for organic skincare brand Juicy Chemistry. | Q100: 2024-04 | R100: High | S100: https://www.afaqs.com/news/digital/social-beat-secures-digital-mandate-for-juicy-chemistry | W100: Not started
...

Sheet In play now
A1: Date | B1: Brand | C1: Category | D1: Brand tier | E1: What is happening | F1: Agency involved | G1: Agency status | H1: Mandate | I1: Evidence | J1: Source | K1: Confidence
A2: 2026-09 | B2: DeVANS (Godfather, Six Fields, GianChand) | C2: Alcobev | D2: Luxury | E2: Appointed 2026-09 with no pitch disclosed; PR, film and experiential not assigned in sources | F2: INNOCEAN India | G2: Won recently | H2: Digital | I2: INNOCEAN India won digital strategy, creative direction and social for GianChand Single Malt across India and international markets. | J2: https://www.afaqs.com/news/newbizwins/innocean-india-wins-digital-and-social-mandate-for-gianchand-single-malt-12539501 | K2: High
A3: 2026-09 | B3: Sazerac India (Paul John, Buffalo Trace) | C3: Alcobev | D3: Luxury | E3: New MD 2026-09 from Bimbo and PepsiCo | F3: Unknown or in-house | G3: Unclear | H3: Integrated | I3: Kunal Sharma joined Sazerac as MD India, overseeing Paul John, Buffalo Trace, Weller and Fireball. | J3: https://www.storyboard18.com/brand-makers/kunal-sharma-named-sazerac-india-managing-director-ws-l-110645.htm | K3: High
A4: 2026-09 | B4: The Diamond Collective (Natural Diamond Council) | C4: Jewellery & watches | D4: Luxury | E4: Rebrand and new strategy 2026-09 with new global campaigns; agencies not named | F4: Unknown or in-house | G4: Unclear | H4: Integrated | I4: Natural Diamond Council relaunched as The Diamond Collective under new CEO Amber Pepper, with a Diamond Desire Index launching in India. | J4: https://www.manifest-media.in/marketing/240926/natural-diamond-council-relaunches-as-the-diamond-collective-with-new.html | K4: High
A5: 2026-09 | B5: VinFast India | C5: Automotive | D5: Premium | E5: PR appointed 2026-09; sister company GSM ran a creative and media pitch 2026-01 | F5: Boomerang Collaborations | G5: Won recently | H5: PR | I5: Campaign India reports VinFast India awarded its communications mandate to Boomerang Collaborations with Velocity Fintrust. | J5: https://www.campaignindia.in/article/pitch-update-coca-cola-mastercard-vinfast-sleepwell-and-more/42wq85ph1ex6qsf9ngpgb9ahxk | K5: High
A6: 2026-09 | B6: 4700BC | C6: Premium F&B & QSR | D6: Premium | E6: Rebrand underway 2026-09; launch campaign and social likely to follow | F6: Pollinate Labs | G6: Won recently | H6: Creative | I6: Pollinate Labs won the rebranding mandate for gourmet popcorn brand 4700BC. | J6: https://www.afaqs.com/news/newbizwins/pollinate-labs-wins-the-rebranding-mandate-for-4700bc-12506207 | K6: High
A7: 2026-09 | B7: Air India | C7: Aviation | D7: Premium | E7: Leadership reset 2026-09 (new CEO-designate, comms head exit); media moved 2026-06; creative incumbent not verified | F7: Unknown or in-house | G7: Unclear | H7: Creative | I7: Air India's global communications head Partha Ghosh exited after CEO Campbell Wilson's exit; CEO-designate Tewolde Gebremariam is charting the next phase. | J7: https://www.afaqs.com/people-spotting/partha-ghosh-exits-air-india-after-three-and-a-half-years-12558443 | K7: Medium
A8: 2026-09 | B8: Arvind Limited | C8: Fashion & luxury retail | D8: Premium | E8: New comms head 2026-09 | F8: Unknown or in-house | G8: Unclear | H8: PR | I8: Arvind appointed Swagat Lakku as head of corporate communications. | J8: https://www.afaqs.com/corporate-communications-and-pr/arvind-appoints-swagat-lakku-as-head-of-corporate-communications-12588593 | K8: High
A9: 2026-09 | B9: Arvind SmartSpaces | C9: Real estate | D9: Premium | E9: New head of marketing 2026-09 | F9: Unknown or in-house | G9: Unclear | H9: Integrated | I9: Arvind SmartSpaces appointed Ankit Dave as head of marketing. | J9: https://www.afaqs.com/people-spotting/arvind-smartspaces-appoints-ankit-dave-as-head-of-marketing-12583232 | K9: High
A10: 2026-09 | B10: CMF by Nothing | C10: Consumer tech & D2C | D10: Premium | E10: Brand spin-off 2026-09; Nothing's India marketing lead left for DailyObjects 2026-09 | F10: Unknown or in-house | G10: Unclear | H10: Integrated | I10: Nothing spun off CMF in India as a separate brand, per Storyboard18. | J10: https://www.storyboard18.com/brand-makers/nothing-ceo-india-needs-engineering-not-just-manufacturing-ws-l-111110.htm | K10: Medium
A11: 2026-09 | B11: DailyObjects | C11: Consumer tech & D2C | D11: Premium | E11: New Global CMO Zeenah Vilcassim joined 2026-09 from Nothing | F11: Unknown or in-house | G11: Unclear | H11: Integrated | I11: DailyObjects appointed Zeenah Vilcassim, who led marketing for Nothing in India, as Global CMO. | J11: https://www.afaqs.com/people-spotting/dailyobjects-appoints-zeenah-vilcassim-as-global-chief-marketing-officer-12570725 | K11: High
A12: 2026-09 | B12: IndiGo | C12: Aviation | D12: Premium | E12: New content and creative head 2026-09 | F12: Unknown or in-house | G12: Unclear | H12: Integrated | I12: IndiGo appointed Mayank Kumar as head of content and creative, marketing. | J12: https://www.afaqs.com/people-spotting/indigo-appoints-mayank-kumar-as-head-of-content-creative-marketing-12514196 | K12: High
... A126: 2024-12 | B126: Kotak Mahindra Bank | C126: BFSI & wealth | D126: Premium | E126: Review signal plus leadership change in marketing (Jul 2026). | F126: Wavemaker (WPP Media) | G126: In review | H126: Media | I126: Kotak Mahindra Group's Rs 100 to 150 crore media account, held by Wavemaker, was reported as evaluating partners in 2024. | J126: https://www.storyboard18.com/advertising/biz-breaks-major-account-moves-and-pitches-of-2024-51970.htm | K126: Medium

Sheet Agency roster
A1: Agency (current name) | B1: Group | C1: Type | D1: Relationships found | E1: Luxury accounts | F1: Premium accounts | G1: Luxury and premium accounts held | H1: Other accounts held | I1: Recently lost | J1: Also reported as
A2: Ogilvy India | B2: WPP | C2: Network creative | D2: =COUNTIF('All relationships'!$A$2:$A$1227,A2) -> 42 | E2: =COUNTIFS('All relationships'!$A$2:$A$1227,A2,'All relationships'!$H$2:$H$1227,"Luxury",'All relationships'!$K$2:$K$1227,"<>Recently lost") -> 2 | F2: =COUNTIFS('All relationships'!$A$2:$A$1227,A2,'All relationships'!$H$2:$H$1227,"Premium",'All relationships'!$K$2:$K$1227,"<>Recently lost") -> 12 | G2: Aqua Plumbings (Plumber Bathware, Aquini) (L), Asian Paints Emporio (L), Adani Airports, Allen Solly, Asian Paints, Asian Paints Beautiful Homes, Brooke Bond Taj Mahal, Cadbury Dairy Milk Silk, Godrej Properties, Indriya (Aditya Birla Jewellery), Lakme, Rustomjee, Titan Raga | H2: Amazon India, Bajaj Pulsar, Cadbury 5 Star, Cadbury Celebrations, Cadbury Dairy Milk, CEAT Tyres, Charged by Thums Up, Coca-Cola India, Coke Zero, DP World, Eveready Ultima, Fevicol and Fevikwik, Google India, Jio-bp, JSW Steel, Mother Dairy, PhonePe Mutual Funds, POND'S, Powerade, Revital H, Santoor, Sunfeast YiPPee!, Tata Motors Commercial Vehicles, Tata Play, Titan Eye+, Vi (Vodafone Idea) | I2: Vistara | J2: Ogilvy (Beauty & Luxury, Ogilvy West), Ogilvy India (Bengaluru), Ogilvy India (Ogilvy Delhi), Ogilvy India (Ogilvy East), Ogilvy India (Ogilvy South), Ogilvy South
A3: VML India | B3: WPP | C3: Network creative | D3: =COUNTIF('All relationships'!$A$2:$A$1227,A3) -> 21 | E3: =COUNTIFS('All relationships'!$A$2:$A$1227,A3,'All relationships'!$H$2:$H$1227,"Luxury",'All relationships'!$K$2:$K$1227,"<>Recently lost") -> 2 | F3: =COUNTIFS('All relationships'!$A$2:$A$1227,A3,'All relationships'!$H$2:$H$1227,"Premium",'All relationships'!$K$2:$K$1227,"<>Recently lost") -> 7 | G3: Anita Dongre (House of Anita Dongre) (L), MINI India (L), CenturyPly, CERA Sanitaryware, Cult.Sport, Kalapuri, Saint-Gobain India (Glass), Skoda Auto India, vivo India | H3: Apollo Tyres, Boost, Coca-Cola India, Durex, Kingfisher, KitKat, Sprite, Star Cement, Sugar Free, Thums Up, Tirupati Edible Oils | I3: Limca | J3: Studio X (VML), VML India (ex Wunderman Thompson), VMLY&R India (now VML), Wunderman Thompson India (now VML), Wunderman Thompson South Asia (now VML)
A4: Grey 82.5 (Ogilvy) | B4: WPP | C4: Network creative | D4: =COUNTIF('All relationships'!$A$2:$A$1227,A4) -> 18 | E4: =COUNTIFS('All relationships'!$A$2:$A$1227,A4,'All relationships'!$H$2:$H$1227,"Luxury",'All relationships'!$K$2:$K$1227,"<>Recently lost") -> 1 | F4: =COUNTIFS('All relationships'!$A$2:$A$1227,A4,'All relationships'!$H$2:$H$1227,"Premium",'All relationships'!$K$2:$K$1227,"<>Recently lost") -> 11 | G4: De Beers Forevermark (L), Bacardi India, Havells, Himalayan Natural Mineral Water, Indian Craft Brewery, JSW MG Motor India, Kajaria Ceramics, Kalapuri, MMTC-PAMP, Tanishq, Tata Coffee Grand Cold Coffee | H4: Axis Bank, Bandhan Mutual Fund, Imperial Blue, Luminous, Mother's Recipe, Vadilal | J4: 82.5 Communications, 82.5 Communications (Mumbai), 82.5 Communications (now Grey 82.5), AutumnGrey (Grey India), Grey 82.5, Grey 82.5 (ex Grey India / AutumnGrey), Grey 82.5 (formerly 82.5 Communications), Grey India (now Grey 82.5), Grey India and AutumnGrey
A5: Contract Advertising (VML) | B5: WPP | C5: Network creative | D5: =COUNTIF('All relationships'!$A$2:$A$1227,A5) -> 7 | E5: =COUNTIFS('All relationships'!$A$2:$A$1227,A5,'All relationships'!$H$2:$H$1227,"Luxury",'All relationships'!$K$2:$K$1227,"<>Recently lost") -> 1 | F5: =COUNTIFS('All relationships'!$A$2:$A$1227,A5,'All relationships'!$H$2:$H$1227,"Premium",'All relationships'!$K$2:$K$1227,"<>Recently lost") -> 4 | G5: BMW India (L), HSBC India, KISNA, L&T Realty, Shoppers Stop | H5: Haldiram's, Softovac | J5: Contract Advertising, Contract Advertising India (VML)
A6: Wavemaker (WPP Media) | B6: WPP | C6: Media | D6: =COUNTIF('All relationships'!$A$2:$A$1227,A6) -> 7 | E6: =COUNTIFS('All relationships'!$A$2:$A$1227,A6,'All relationships'!$H$2:$H$1227,"Luxury",'All relationships'!$K$2:$K$1227,"<>Recently lost") -> 0 | F6: =COUNTIFS('All relationships'!$A$2:$A$1227,A6,'All relationships'!$H$2:$H$1227,"Premium",'All relationships'!$K$2:$K$1227,"<>Recently lost") -> 4 | G6: Kotak Mahindra Bank, Pernod Ricard India, Red Bull India, Tata Consumer Products (portfolio) | H6: Wipro Consumer Care | I6: L'Oreal India, Netflix India | J6: Wavemaker, Wavemaker India (WPP Media)
A7: Burson India | B7: WPP | C7: PR | D7: =COUNTIF('All relationships'!$A$2:$A$1227,A7) -> 6 | E7: =COUNTIFS('All relationships'!$A$2:$A$1227,A7,'All relationships'!$H$2:$H$1227,"Luxury",'All relationships'!$K$2:$K$1227,"<>Recently lost") -> 2 | F7: =COUNTIFS('All relationships'!$A$2:$A$1227,A7,'All relationships'!$H$2:$H$1227,"Premium",'All relationships'!$K$2:$K$1227,"<>Recently lost") -> 3 | G7: Chalet Hotels (Athiva) (L), Ducati India (L), Birla Opus Paints, Honda Cars India, Mirae Asset Sharekhan | H7: Eastman Auto & Power | J7: Burson, Burson Group India
A8: Mirum India (VML) | B8: WPP | C8: Network digital | D8: =COUNTIF('All relationships'!$A$2:$A$1227,A8) -> 4 | E8: =COUNTIFS('All relationships'!$A$2:$A$1227,A8,'All relationships'!$H$2:$H$1227,"Luxury",'All relationships'!$K$2:$K$1227,"<>Recently lost") -> 0 | F8: =COUNTIFS('All relationships'!$A$2:$A$1227,A8,'All relationships'!$H$2:$H$1227,"Premium",'All relationships'!$K$2:$K$1227,"<>Recently lost") -> 2 | G8: Adani Realty, Manyavar | H8: AMFI (Mutual Funds Sahi Hai), ibis (Accor India) | J8: Mirum India (with WT Commerce)
A9: The Glitch (VML) | B9: WPP | C9: Network digital | D9: =COUNTIF('All relationships'!$A$2:$A$1227,A9) -> 4 | E9: =COUNTIFS('All relationships'!$A$2:$A$1227,A9,'All relationships'!$H$2:$H$1227,"Luxury",'All relationships'!$K$2:$K$1227,"<>Recently lost") -> 1 | F9: =COUNTIFS('All relationships'!$A$2:$A$1227,A9,'All relationships'!$H$2:$H$1227,"Premium",'All relationships'!$K$2:$K$1227,"<>Recently lost") -> 3 | G9: Diageo India Reserve portfolio (L), Diageo India (portfolio), Dove, Enamor | J9: The Glitch
A10: WPP Media | B10: WPP | C10: Media | D10: =COUNTIF('All relationships'!$A$2:$A$1227,A10) -> 3 | E10: =COUNTIFS('All relationships'!$A$2:$A$1227,A10,'All relationships'!$H$2:$H$1227,"Luxury",'All relationships'!$K$2:$K$1227,"<>Recently lost") -> 0 | F10: =COUNTIFS('All relationships'!$A$2:$A$1227,A10,'All relationships'!$H$2:$H$1227,"Premium",'All relationships'!$K$2:$K$1227,"<>Recently lost") -> 2 | G10: DAAWAT, Manyavar | I10: Flipkart | J10: EssenceMediacom, GroupM OOH Solutions (now WPP Media)
A11: Hogarth India | B11: WPP | C11: Network digital | D11: =COUNTIF('All relationships'!$A$2:$A$1227,A11) -> 1 | E11: =COUNTIFS('All relationships'!$A$2:$A$1227,A11,'All relationships'!$H$2:$H$1227,"Luxury",'All relationships'!$K$2:$K$1227,"<>Recently lost") -> 0 | F11: =COUNTIFS('All relationships'!$A$2:$A$1227,A11,'All relationships'!$H$2:$H$1227,"Premium",'All relationships'!$K$2:$K$1227,"<>Recently lost") -> 0 | H11: Federal Bank | J11: Hogarth India (WPP Production)
A12: Landor India | B12: WPP | C12: Network creative | D12: =COUNTIF('All relationships'!$A$2:$A$1227,A12) -> 1 | E12: =COUNTIFS('All relationships'!$A$2:$A$1227,A12,'All relationships'!$H$2:$H$1227,"Luxury",'All relationships'!$K$2:$K$1227,"<>Recently lost") -> 1 | F12: =COUNTIFS('All relationships'!$A$2:$A$1227,A12,'All relationships'!$H$2:$H$1227,"Premium",'All relationships'!$K$2:$K$1227,"<>Recently lost") -> 0 | G12: Dharana at Shillim (L)
A13: WPP (unit not named) | B13: WPP | C13: Network creative | D13: =COUNTIF('All relationships'!$A$2:$A$1227,A13) -> 1 | E13: =COUNTIFS('All relationships'!$A$2:$A$1227,A13,'All relationships'!$H$2:$H$1227,"Luxury",'All relationships'!$K$2:$K$1227,"<>Recently lost") -> 1 | F13: =COUNTIFS('All relationships'!$A$2:$A$1227,A13,'All relationships'!$H$2:$H$1227,"Premium",'All relationships'!$K$2:$K$1227,"<>Recently lost") -> 0 | G13: Jaguar Land Rover India (L) | J13: WPP
A14: Leo India | B14: Publicis | C14: Network creative | D14: =COUNTIF('All relationships'!$A$2:$A$1227,A14) -> 30 | E14: =COUNTIFS('All relationships'!$A$2:$A$1227,A14,'All relationships'!$H$2:$H$1227,"Luxury",'All relationships'!$K$2:$K$1227,"<>Recently lost") -> 0 | F14: =COUNTIFS('All relationships'!$A$2:$A$1227,A14,'All relationships'!$H$2:$H$1227,"Premium",'All relationships'!$K$2:$K$1227,"<>Recently lost") -> 13 | G14: Birla Opus Paints, California Almonds, HCL Group, HDFC Life, IKEA India, IndusInd Bank, Lee (India), Lenovo India, LinkedIn India, Puma India, Schneider Electric (home electricals), Sebamed, Visa | H14: ACKO, Amazon India, Bandhan Bank, BGMI (Krafton India), Cleartrip, Flipkart, Gatorade, JioMart, Lay's, Meta (India), PepsiCo India Foods & Beverages (digital), redBus, Spotify India, Sting Energy, Whisper, Zupee | I14: McDonald's India (West & South) | J14: Leo India (ex Leo Burnett Orchard)
A15: BBH India | B15: Publicis | C15: Network creative | D15: =COUNTIF('All relationships'!$A$2:$A$1227,A15) -> 14 | E15: =COUNTIFS('All relationships'!$A$2:$A$1227,A15,'All relationships'!$H$2:$H$1227,"Luxury",'All relationships'!$K$2:$K$1227,"<>Recently lost") -> 1 | F15: =COUNTIFS('All relationships'!$A$2:$A$1227,A15,'All relationships'!$H$2:$H$1227,"Premium",'All relationships'!$K$2:$K$1227,"<>Recently lost") -> 5 | G15: Taj Hotels (IHCL) (L), CaratLane, DP World, Oaksmith, Skoda Auto India | H15: CYBX, Garnier Men, HDFC Ergo, JAPFA, Microtek, Nestle Milkmaid, UniScholars, upGrad
A16: Saatchi & Saatchi India | B16: Publicis | C16: Network creative | D16: =COUNTIF('All relationships'!$A$2:$A$1227,A16) -> 14 | E16: =COUNTIFS('All relationships'!$A$2:$A$1227,A16,'All relationships'!$H$2:$H$1227,"Luxury",'All relationships'!$K$2:$K$1227,"<>Recently lost") -> 1 | F16: =COUNTIFS('All relationships'!$A$2:$A$1227,A16,'All relationships'!$H$2:$H$1227,"Premium",'All relationships'!$K$2:$K$1227,"<>Recently lost") -> 4 | G16: Audi India (L), Arvind Limited, Dunkin' India, FedEx India, Lauritz Knudsen | H16: Captain Steel, Flite, Floron, Grupo Bimbo (Bimbo Bakeries India), Hero MotoCorp, McDowell's (House of McDowell's Soda), Renault India (Kiger) | I16: Audi India, JioMart
A17: Publicis Digital Experience (ex Digitas) | B17: Publicis | C17: Network digital | D17: =COUNTIF('All relationships'!$A$2:$A$1227,A17) -> 9 | E17: =COUNTIFS('All relationships'!$A$2:$A$1227,A17,'All relationships'!$H$2:$H$1227,"Luxury",'All relationships'!$K$2:$K$1227,"<>Recently lost") -> 0 | F17: =COUNTIFS('All relationships'!$A$2:$A$1227,A17,'All relationships'!$H$2:$H$1227,"Premium",'All relationships'!$K$2:$K$1227,"<>Recently lost") -> 5 | G17: Corona, Duolingo, EquBot, Figaro and Bertolli olive oils, Matter | H17: boAt, Okaya, Renault India (Kiger) | I17: Duolingo | J17: Digitas India (now Publicis Digital Experience)
A18: BBH India (ex Publicis India) | B18: Publicis | C18: Network creative | D18: =COUNTIF('All relationships'!$A$2:$A$1227,A18) -> 8 | E18: =COUNTIFS('All relationships'!$A$2:$A$1227,A18,'All relationships'!$H$2:$H$1227,"Luxury",'All relationships'!$K$2:$K$1227,"<>Recently lost") -> 0 | F18: =COUNTIFS('All relationships'!$A$2:$A$1227,A18,'All relationships'!$H$2:$H$1227,"Premium",'All relationships'!$K$2:$K$1227,"<>Recently lost") -> 1 | G18: HDFC Mutual Fund | H18: Navratna, Nerolac Paints, Pramerica Life Insurance, ZEE TV, ZEE5 | I18: BIBA, Enamor | J18: Publicis India (merged into BBH India, Jan 2026)
A19: Propagate India (Publicis) | B19: Publicis | C19: Network digital | D19: =COUNTIF('All relationships'!$A$2:$A$1227,A19) -> 6 | E19: =COUNTIFS('All relationships'!$A$2:$A$1227,A19,'All relationships'!$H$2:$H$1227,"Luxury",'All relationships'!$K$2:$K$1227,"<>Recently lost") -> 0 | F19: =COUNTIFS('All relationships'!$A$2:$A$1227,A19,'All relationships'!$H$2:$H$1227,"Premium",'All relationships'!$K$2:$K$1227,"<>Recently lost") -> 1 | G19: Dunkin' India | H19: CremTreat, CYBX, Jio-bp, UPES | I19: Enamor | J19: Propagate India (ex Saatchi & Saatchi Propagate)
A20: Publicis Beehive | B20: Publicis | C20: Network creative | D20: =COUNTIF('All relationships'!$A$2:$A$1227,A20) -> 2 | E20: =COUNTIFS('All relationships'!$A$2:$A$1227,A20,'All relationships'!$H$2:$H$1227,"Luxury",'All relationships'!$K$2:$K$1227,"<>Recently lost") -> 0 | F20: =COUNTIFS('All relationships'!$A$2:$A$1227,A20,'All relationships'!$H$2:$H$1227,"Premium",'All relationships'!$K$2:$K$1227,"<>Recently lost") -> 0 | H20: Balaji Wafers, Storia
A21: Publicis Media | B21: Publicis | C21: Media | D21: =COUNTIF('All relationships'!$A$2:$A$1227,A21) -> 2 | E21: =COUNTIFS('All relationships'!$A$2:$A$1227,A21,'All relationships'!$H$2:$H$1227,"Luxury",'All relationships'!$K$2:$K$1227,"<>Recently lost") -> 0 | F21: =COUNTIFS('All relationships'!$A$2:$A$1227,A21,'All relationships'!$H$2:$H$1227,"Premium",'All relationships'!$K$2:$K$1227,"<>Recently lost") -> 1 | G21: L'Oreal India | H21: Flipkart | J21: Starcom
A22: BBH Singapore | B22: Publicis | C22: Network creative | D22: =COUNTIF('All relationships'!$A$2:$A$1227,A22) -> 1 | E22: =COUNTIFS('All relationships'!$A$2:$A$1227,A22,'All relationships'!$H$2:$H$1227,"Luxury",'All relationships'!$K$2:$K$1227,"<>Recently lost") -> 1 | F22: =COUNTIFS('All relationships'!$A$2:$A$1227,A22,'All relationships'!$H$2:$H$1227,"Premium",'All relationships'!$K$2:$K$1227,"<>Recently lost") -> 0 | G22: Marriott Bonvoy (India) (L)
A23: MSL India | B23: Publicis | C23: PR | D23: =COUNTIF('All relationships'!$A$2:$A$1227,A23) -> 1 | E23: =COUNTIFS('All relationships'!$A$2:$A$1227,A23,'All relationships'!$H$2:$H$1227,"Luxury",'All relationships'!$K$2:$K$1227,"<>Recently lost") -> 0 | F23: =COUNTIFS('All relationships'!$A$2:$A$1227,A23,'All relationships'!$H$2:$H$1227,"Premium",'All relationships'!$K$2:$K$1227,"<>Recently lost") -> 0 | H23: Quess Corp
A24: Team Spirit (Publicis) | B24: Publicis | C24: Network creative | D24: =COUNTIF('All relationships'!$A$2:$A$1227,A24) -> 1 | E24: =COUNTIFS('All relationships'!$A$2:$A$1227,A24,'All relationships'!$H$2:$H$1227,"Luxury",'All relationships'!$K$2:$K$1227,"<>Recently lost") -> 0 | F24: =COUNTIFS('All relationships'!$A$2:$A$1227,A24,'All relationships'!$H$2:$H$1227,"Premium",'All relationships'!$K$2:$K$1227,"<>Recently lost") -> 0 | H24: McDowell's (House of McDowell's Soda) | J24: Publicis Groupe India (Team Spirit)
A25: TBWA\Lintas | B25: Omnicom | C25: Network creative | D25: =COUNTIF('All relationships'!$A$2:$A$1227,A25) -> 64 | E25: =COUNTIFS('All relationships'!$A$2:$A$1227,A25,'All relationships'!$H$2:$H$1227,"Luxury",'All relationships'!$K$2:$K$1227,"<>Recently lost") -> 2 | F25: =COUNTIFS('All relationships'!$A$2:$A$1227,A25,'All relationships'!$H$2:$H$1227,"Premium",'All relationships'!$K$2:$K$1227,"<>Recently lost") -> 27 | G25: Hyatt India (L), Rivaah by Tanishq (L), Axis Bank, Dosti Realty, Eicher Motors, Etihad Airways, FabIndia, Google Gemini, Havells, Hershey's, Hilton India, Hindware Italian Collection, IndusInd Bank, Jawa Motorcycles, JioBlackRock, Magnum, Manipal Hospitals, Mirae Asset, Philips, Reliance Foundation, Standard Chartered India, Tanishq, True Elements, Tuborg, TVS Apache, TVS Ronin, Urban Ladder | H25: Air India Express, ALKEM, Amaron, Britannia, Cipla, Cofsils, Complan, Dixcy Scott, Dollar Missy and Dollar Rainguard, Eureka Forbes, Flipkart Health+, Future Generali, General Insurance Council, Google Pay, JSW Paints, Kamiliant, LEAD School, Lifebuoy, Lifestyle, MakeMyTrip, Naukri.com, Nissan Magnite, Real Fizzin', Saffola, Steadfast, Surf Excel, Tata AIG General Insurance, Tata Tea (Premium, Gold), TVS Motor, Vasmol, Vim, Yousta | I25: Bajaj Almond Drops, Bandhan Bank, Mumbai Indians | J25: Lowe Lintas (now TBWA\Lintas), Mullen Lintas (folded into TBWA\Lintas), TBWA India, TBWA\Lintas (ex Lowe Lintas), TBWA\Lintas (formerly Lowe Lintas)
A26: Mudra (ex DDB Mudra, BBDO Group) | B26: Omnicom | C26: Network creative | D26: =COUNTIF('All relationships'!$A$2:$A$1227,A26) -> 35 | E26: =COUNTIFS('All relationships'!$A$2:$A$1227,A26,'All relationships'!$H$2:$H$1227,"Luxury",'All relationships'!$K$2:$K$1227,"<>Recently lost") -> 0 | F26: =COUNTIFS('All relationships'!$A$2:$A$1227,A26,'All relationships'!$H$2:$H$1227,"Premium",'All relationships'!$K$2:$K$1227,"<>Recently lost") -> 13 | G26: Adani Group (corporate), Ethnix by Raymond, Infosys, Instagram, Malabar Gold & Diamonds, Meta AI, Myntra, Narayana Health, Netflix India, Philips, Raymond, Royal Challenge, Spotify India | H26: ACKO, Bewakoof, Bharat Connect (Bharat BillPay), BirlaNu, Boomer, Dhara, Dharavi Redevelopment (DRPPL), Dream11, Gulf Oil Lubricants India, Indeed, McDowell's No.1, Meesho, RuPay, TTK Prestige | I26: BGMI (Krafton India), Birla Opus Paints, Flipkart, McDonald's India (North & East), McDonald's India (West & South), Stayfree, Steadfast, Volkswagen | J26: DDB Mudra
A27: McCann India | B27: Omnicom | C27: Network creative | D27: =COUNTIF('All relationships'!$A$2:$A$1227,A27) -> 29 | E27: =COUNTIFS('All relationships'!$A$2:$A$1227,A27,'All relationships'!$H$2:$H$1227,"Luxury",'All relationships'!$K$2:$K$1227,"<>Recently lost") -> 1 | F27: =COUNTIFS('All relationships'!$A$2:$A$1227,A27,'All relationships'!$H$2:$H$1227,"Premium",'All relationships'!$K$2:$K$1227,"<>Recently lost") -> 11 | G27: Hilton India (L), Air India, Asian Paints, Birla Estates, Buckaroo, CERA Sanitaryware, Johnson's Baby, Mahindra electric SUVs (BE 6, XEV 9e), Manyavar, Myntra, Salesforce | H27: 3M Consumer Business, Bajaj Electricals (fans, coolers), Britannia Good Day, Campa Cola, Coca-Cola India, Dettol, ESAF Small Finance Bank, Flipkart, Hero Destini, Maggi, McDonald's India (West & South), Nescafe, Paytm, Smart Bazaar, YES BANK | I27: Complan, Stayfree | J27: McCann Worldgroup India
A28: 22feet Tribal Worldwide | B28: Omnicom | C28: Network digital | D28: =COUNTIF('All relationships'!$A$2:$A$1227,A28) -> 21 | E28: =COUNTIFS('All relationships'!$A$2:$A$1227,A28,'All relationships'!$H$2:$H$1227,"Luxury",'All relationships'!$K$2:$K$1227,"<>Recently lost") -> 0 | F28: =COUNTIFS('All relationships'!$A$2:$A$1227,A28,'All relationships'!$H$2:$H$1227,"Premium",'All relationships'!$K$2:$K$1227,"<>Recently lost") -> 15 | G28: Adani Realty, Agoda, AJIO, Galaxy, Godrej Interio, HomeLane, Jack Daniel's, Keenai Wealth, Kohinoor rice, Lumina CloudInfra, Royal Canin India, Volkswagen, Whiskas | H28: BGMI (Krafton India), Doublemint, Flipkart, Pedigree, Porter, Snickers | J28: 22feet Tribal, 22Feet Tribal Worldwide, DDB Tribal India
A29: BBDO India | B29: Omnicom | C29: Network creative | D29: =COUNTIF('All relationships'!$A$2:$A$1227,A29) -> 18 | E29: =COUNTIFS('All relationships'!$A$2:$A$1227,A29,'All relationships'!$H$2:$H$1227,"Luxury",'All relationships'!$K$2:$K$1227,"<>Recently lost") -> 2 | F29: =COUNTIFS('All relationships'!$A$2:$A$1227,A29,'All relationships'!$H$2:$H$1227,"Premium",'All relationships'!$K$2:$K$1227,"<>Recently lost") -> 8 | G29: Mercedes-Benz India (L), DAAWAT, Dewar's, Gillette, McDonald's India (North & East), Tata Ultra Marathon, WhatsApp, Whiskas, World Gold Council India | H29: Ariel, Birla Opus Paints, Candid, Cargill edible oils, Indian Newspaper Society (INS), Milkbasket, Whisper | I29: Jack Daniel's | J29: BBDO India (team X)
A30: McCann India (ex FCB India) | B30: Omnicom | C30: Network creative | D30: =COUNTIF('All relationships'!$A$2:$A$1227,A30) -> 13 | E30: =COUNTIFS('All relationships'!$A$2:$A$1227,A30,'All relationships'!$H$2:$H$1227,"Luxury",'All relationships'!$K$2:$K$1227,"<>Recently lost") -> 0 | F30: =COUNTIFS('All relationships'!$A$2:$A$1227,A30,'All relationships'!$H$2:$H$1227,"Premium",'All relationships'!$K$2:$K$1227,"<>Recently lost") -> 5 | G30: Android, Centrum, DBS Bank India, Philips Home Appliances, Tasty Bite | H30: Bata, Dulcoflex, Hero Xtreme, Swaraj Tractors, Torrent Electricals, Uber India, vivo India, Wagh Bakri | J30: FCB India (retired 2026, absorbed into McCann India), FCB Interface (retired 2026, FCB India unit)
A31: Kinnect | B31: Omnicom | C31: Network digital | D31: =COUNTIF('All relationships'!$A$2:$A$1227,A31) -> 11 | E31: =COUNTIFS('All relationships'!$A$2:$A$1227,A31,'All relationships'!$H$2:$H$1227,"Luxury",'All relationships'!$K$2:$K$1227,"<>Recently lost") -> 0 | F31: =COUNTIFS('All relationships'!$A$2:$A$1227,A31,'All relationships'!$H$2:$H$1227,"Premium",'All relationships'!$K$2:$K$1227,"<>Recently lost") -> 5 | G31: HDFC Bank, Intel India, Lenovo India, Mumbai Indians, Titan SKINN | H31: Blue Star, Burger King India, Flipkart, Prega News, State Bank of India, TVS Raider | J31: FCB Kinnect, Kinnect (ex FCB Kinnect)
A32: Ulka (BBDO Group) | B32: Omnicom | C32: Network creative | D32: =COUNTIF('All relationships'!$A$2:$A$1227,A32) -> 10 | E32: =COUNTIFS('All relationships'!$A$2:$A$1227,A32,'All relationships'!$H$2:$H$1227,"Luxury",'All relationships'!$K$2:$K$1227,"<>Recently lost") -> 0 | F32: =COUNTIFS('All relationships'!$A$2:$A$1227,A32,'All relationships'!$H$2:$H$1227,"Premium",'All relationships'!$K$2:$K$1227,"<>Recently lost") -> 5 | G32: Bhima Jewellers, Kansai Nerolac, Provident Housing (Puravankara), Shoppers Stop, Sunfeast Dark Fantasy | H32: Bajaj Almond Drops, ITC Candyman, Navbharat Times, Sensodent | I32: Santoor | J32: FCB Ulka, Ulka, Ulka (ex FCB Ulka, now in BBDO Group India)
A33: TBWA\Lintas (ex Lintas Live) | B33: Omnicom | C33: PR | D33: =COUNTIF('All relationships'!$A$2:$A$1227,A33) -> 9 | E33: =COUNTIFS('All relationships'!$A$2:$A$1227,A33,'All relationships'!$H$2:$H$1227,"Luxury",'All relationships'!$K$2:$K$1227,"<>Recently lost") -> 1 | F33: =COUNTIFS('All relationships'!$A$2:$A$1227,A33,'All relationships'!$H$2:$H$1227,"Premium",'All relationships'!$K$2:$K$1227,"<>Recently lost") -> 5 | G33: Hyatt India (L), Classic Legends (Jawa, Yezdi, BSA), Prestige Group, SOCIAL (Impresario), Turespana (Spain Tourism), Visit Victoria | H33: Officer's Choice, Saridon and Supradyn, Tata AIG General Insurance | J33: Lintas Live (folded into TBWA\Lintas), Lintas Live (now under Omnicom), Lintas Live (TBWA\Lintas)
A34: FCB Neo (absorbed into McCann) | B34: Omnicom | C34: Network creative | D34: =COUNTIF('All relationships'!$A$2:$A$1227,A34) -> 6 | E34: =COUNTIFS('All relationships'!$A$2:$A$1227,A34,'All relationships'!$H$2:$H$1227,"Luxury",'All relationships'!$K$2:$K$1227,"<>Recently lost") -> 0 | F34: =COUNTIFS('All relationships'!$A$2:$A$1227,A34,'All relationships'!$H$2:$H$1227,"Premium",'All relationships'!$K$2:$K$1227,"<>Recently lost") -> 3 | G34: Berger Paints (Silk Glamor), Mahindra Thar ROXX, Royal Stag | H34: Horlicks, KFC India, Royal Stag | J34: FCB Neo, FCB Neo (retired 2026, FCB India unit)
A35: Interactive Avenues (Omnicom Media) | B35: Omnicom | C35: Network digital | D35: =COUNTIF('All relationships'!$A$2:$A$1227,A35) -> 6 | E35: =COUNTIFS('All relationships'!$A$2:$A$1227,A35,'All relationships'!$H$2:$H$1227,"Luxury",'All relationships'!$K$2:$K$1227,"<>Recently lost") -> 1 | F35: =COUNTIFS('All relationships'!$A$2:$A$1227,A35,'All relationships'!$H$2:$H$1227,"Premium",'All relationships'!$K$2:$K$1227,"<>Recently lost") -> 2 | G35: BMW India (L), Indian Racing League and FIA F4 India, Twinings | H35: Apsara Zesta, Home Centre, Super League Kerala | J35: Interactive Avenues (now Omnicom Media)
A36: OMD India | B36: Omnicom | C36: Media | D36: =COUNTIF('All relationships'!$A$2:$A$1227,A36) -> 4 | E36: =COUNTIFS('All relationships'!$A$2:$A$1227,A36,'All relationships'!$H$2:$H$1227,"Luxury",'All relationships'!$K$2:$K$1227,"<>Recently lost") -> 0 | F36: =COUNTIFS('All relationships'!$A$2:$A$1227,A36,'All relationships'!$H$2:$H$1227,"Premium",'All relationships'!$K$2:$K$1227,"<>Recently lost") -> 3 | G36: Bira 91, HDFC Life, SUGAR Cosmetics | H36: Ventura Securities
A37: Initiative (Omnicom Media) | B37: Omnicom | C37: Media | D37: =COUNTIF('All relationships'!$A$2:$A$1227,A37) -> 3 | E37: =COUNTIFS('All relationships'!$A$2:$A$1227,A37,'All relationships'!$H$2:$H$1227,"Luxury",'All relationships'!$K$2:$K$1227,"<>Recently lost") -> 1 | F37: =COUNTIFS('All relationships'!$A$2:$A$1227,A37,'All relationships'!$H$2:$H$1227,"Premium",'All relationships'!$K$2:$K$1227,"<>Recently lost") -> 1 | G37: Volvo Cars India (L), Ather Energy | I37: Air India | J37: Initiative (IPG Mediabrands)
A38: Ketchum Sampark | B38: Omnicom | C38: PR | D38: =COUNTIF('All relationships'!$A$2:$A$1227,A38) -> 3 | E38: =COUNTIFS('All relationships'!$A$2:$A$1227,A38,'All relationships'!$H$2:$H$1227,"Luxury",'All relationships'!$K$2:$K$1227,"<>Recently lost") -> 0 | F38: =COUNTIFS('All relationships'!$A$2:$A$1227,A38,'All relationships'!$H$2:$H$1227,"Premium",'All relationships'!$K$2:$K$1227,"<>Recently lost") -> 1 | G38: World Trade Centers Association (WTCA) | H38: Aadhar Housing Finance, Usha International
A39: Lodestar UM (Omnicom Media) | B39: Omnicom | C39: Media | D39: =COUNTIF('All relationships'!$A$2:$A$1227,A39) -> 3 | E39: =COUNTIFS('All relationships'!$A$2:$A$1227,A39,'All relationships'!$H$2:$H$1227,"Luxury",'All relationships'!$K$2:$K$1227,"<>Recently lost") -> 1 | F39: =COUNTIFS('All relationships'!$A$2:$A$1227,A39,'All relationships'!$H$2:$H$1227,"Premium",'All relationships'!$K$2:$K$1227,"<>Recently lost") -> 0 | G39: BMW India (L) | H39: AMFI (Mutual Funds Sahi Hai) | I39: Samsung India | J39: Lodestar UM, Lodestar UM (now Omnicom Media)
A40: Omnicom Media India | B40: Omnicom | C40: Media | D40: =COUNTIF('All relationships'!$A$2:$A$1227,A40) -> 3 | E40: =COUNTIFS('All relationships'!$A$2:$A$1227,A40,'All relationships'!$H$2:$H$1227,"Luxury",'All relationships'!$K$2:$K$1227,"<>Recently lost") -> 0 | F40: =COUNTIFS('All relationships'!$A$2:$A$1227,A40,'All relationships'!$H$2:$H$1227,"Premium",'All relationships'!$K$2:$K$1227,"<>Recently lost") -> 2 | G40: Netflix India, Tata Motors Passenger Vehicles (incl. Tata.ev) | H40: State Bank of India | J40: Omnicom Media, Omnicom Media Group (Lodestar UM, OMD) with Dentsu and Madison
A41: Bernbach (Omnicom, VW unit) | B41: Omnicom | C41: Network creative | D41: =COUNTIF('All relationships'!$A$2:$A$1227,A41) -> 2 | E41: =COUNTIFS('All relationships'!$A$2:$A$1227,A41,'All relationships'!$H$2:$H$1227,"Luxury",'All relationships'!$K$2:$K$1227,"<>Recently lost") -> 0 | F41: =COUNTIFS('All relationships'!$A$2:$A$1227,A41,'All relationships'!$H$2:$H$1227,"Premium",'All relationships'!$K$2:$K$1227,"<>Recently lost") -> 2 | G41: Volkswagen | J41: Bernbach (Omnicom Advertising), Bernbach (Omnicom, ex DDB)
A42: Weber Shandwick India | B42: Omnicom | C42: PR | D42: =COUNTIF('All relationships'!$A$2:$A$1227,A42) -> 2 | E42: =COUNTIFS('All relationships'!$A$2:$A$1227,A42,'All relationships'!$H$2:$H$1227,"Luxury",'All relationships'!$K$2:$K$1227,"<>Recently lost") -> 0 | F42: =COUNTIFS('All relationships'!$A$2:$A$1227,A42,'All relationships'!$H$2:$H$1227,"Premium",'All relationships'!$K$2:$K$1227,"<>Recently lost") -> 1 | G42: IDP Education | H42: Livpure
A43: Omnicom (unit not named) | B43: Omnicom | C43: Network creative | D43: =COUNTIF('All relationships'!$A$2:$A$1227,A43) -> 1 | E43: =COUNTIFS('All relationships'!$A$2:$A$1227,A43,'All relationships'!$H$2:$H$1227,"Luxury",'All relationships'!$K$2:$K$1227,"<>Recently lost") -> 0 | F43: =COUNTIFS('All relationships'!$A$2:$A$1227,A43,'All relationships'!$H$2:$H$1227,"Premium",'All relationships'!$K$2:$K$1227,"<>Recently lost") -> 1 | G43: Raymond | J43: Omnicom (agency unit not named)
A44: TBWA\Media Arts Lab India | B44: Omnicom | C44: Network creative | D44: =COUNTIF('All relationships'!$A$2:$A$1227,A44) -> 1 | E44: =COUNTIFS('All relationships'!$A$2:$A$1227,A44,'All relationships'!$H$2:$H$1227,"Luxury",'All relationships'!$K$2:$K$1227,"<>Recently lost") -> 0 | F44: =COUNTIFS('All relationships'!$A$2:$A$1227,A44,'All relationships'!$H$2:$H$1227,"Premium",'All relationships'!$K$2:$K$1227,"<>Recently lost") -> 1 | G44: Apple
A45: Dentsu Creative India | B45: Dentsu | C45: Network creative | D45: =COUNTIF('All relationships'!$A$2:$A$1227,A45) -> 20 | E45: =COUNTIFS('All relationships'!$A$2:$A$1227,A45,'All relationships'!$H$2:$H$1227,"Luxury",'All relationships'!$K$2:$K$1227,"<>Recently lost") -> 1 | F45: =COUNTIFS('All relationships'!$A$2:$A$1227,A45,'All relationships'!$H$2:$H$1227,"Premium",'All relationships'!$K$2:$K$1227,"<>Recently lost") -> 8 | G45: Johnnie Walker (L), Aditya Birla Capital, Air India, BIBA, Honda Cars India, Tasva, Tata Group IPL (Tata Motors, Air India Express and others), Triumph Motorcycles India, VLCC | H45: Bajaj Finserv insurance (Bajaj Life, Bajaj General), CarDekho, Gulf Oil Lubricants India, HELL Energy Drink, Lotte India, Motorola India, Popeyes India, Sony Entertainment Television, SAB, MAX, MAX 2, TTK Healthcare brands, TVS Motor, TVS NTORQ | J45: Dentsu, dentsu India, Dentsu India, Taproot Dentsu, Taproot Dentsu (folded into Dentsu Creative), WATConsult (folded into Dentsu Creative)
A46: Dentsu Creative Webchutney | B46: Dentsu | C46: Network creative | D46: =COUNTIF('All relationships'!$A$2:$A$1227,A46) -> 16 | E46: =COUNTIFS('All relationships'!$A$2:$A$1227,A46,'All relationships'!$H$2:$H$1227,"Luxury",'All relationships'!$K$2:$K$1227,"<>Recently lost") -> 1 | F46: =COUNTIFS('All relationships'!$A$2:$A$1227,A46,'All relationships'!$H$2:$H$1227,"Premium",'All relationships'!$K$2:$K$1227,"<>Recently lost") -> 7 | G46: KLUDI India (L), Bhima Jewellers, Canon India, DSP Mutual Fund, Godrej Professional, Greenlam Laminates, RAK Ceramics India, Tanishq | H46: Catch (Spices, Pink Rock Salt), Freedom and Be-Rite edible oils, iQOO, Madhur Sugar, MakeMyTrip, NESCAFE Sunrise, New Holland, Papa Johns India | J46: Dentsu Webchutney
A47: Dentsu Creative Isobar | B47: Dentsu | C47: Network digital | D47: =COUNTIF('All relationships'!$A$2:$A$1227,A47) -> 8 | E47: =COUNTIFS('All relationships'!$A$2:$A$1227,A47,'All relationships'!$H$2:$H$1227,"Luxury",'All relationships'!$K$2:$K$1227,"<>Recently lost") -> 1 | F47: =COUNTIFS('All relationships'!$A$2:$A$1227,A47,'All relationships'!$H$2:$H$1227,"Premium",'All relationships'!$K$2:$K$1227,"<>Recently lost") -> 3 | G47: De Beers Forevermark (L), Blackberrys, Canon India, Intel India | H47: Bandhan Bank, BGMI (Krafton India), HELL Energy Drink, Swiggy Instamart
A48: Dentsu Creative PR (ex Perfect Relations) | B48: Dentsu | C48: PR | D48: =COUNTIF('All relationships'!$A$2:$A$1227,A48) -> 2 | E48: =COUNTIFS('All relationships'!$A$2:$A$1227,A48,'All relationships'!$H$2:$H$1227,"Luxury",'All relationships'!$K$2:$K$1227,"<>Recently lost") -> 0 | F48: =COUNTIFS('All relationships'!$A$2:$A$1227,A48,'All relationships'!$H$2:$H$1227,"Premium",'All relationships'!$K$2:$K$1227,"<>Recently lost") -> 0 | H48: HELL Energy Drink, Papa Johns India | J48: Dentsu Creative PR
A49: Dentsu Sports & Entertainment | B49: Dentsu | C49: Experiential | D49: =COUNTIF('All relationships'!$A$2:$A$1227,A49) -> 1 | E49: =COUNTIFS('All relationships'!$A$2:$A$1227,A49,'All relationships'!$H$2:$H$1227,"Luxury",'All relationships'!$K$2:$K$1227,"<>Recently lost") -> 0 | F49: =COUNTIFS('All relationships'!$A$2:$A$1227,A49,'All relationships'!$H$2:$H$1227,"Premium",'All relationships'!$K$2:$K$1227,"<>Recently lost") -> 0 | H49: Air India Express
A50: Havas Creative India | B50: Havas | C50: Network creative | D50: =COUNTIF('All relationships'!$A$2:$A$1227,A50) -> 15 | E50: =COUNTIFS('All relationships'!$A$2:$A$1227,A50,'All relationships'!$H$2:$H$1227,"Luxury",'All relationships'!$K$2:$K$1227,"<>Recently lost") -> 0 | F50: =COUNTIFS('All relationships'!$A$2:$A$1227,A50,'All relationships'!$H$2:$H$1227,"Premium",'All relationships'!$K$2:$K$1227,"<>Recently lost") -> 1 | G50: JBL | H50: Bingo!, Burger King India, Chinese Wok, Eastman Auto & Power, Harpic, Mamaearth, Moov, Mortein, Muthoot FinCorp, The Times of India, UTI Mutual Fund, Vanish, Veet | J50: Havas Worldwide India
A51: PR Pundit Havas Red | B51: Havas | C51: PR | D51: =COUNTIF('All relationships'!$A$2:$A$1227,A51) -> 4 | E51: =COUNTIFS('All relationships'!$A$2:$A$1227,A51,'All relationships'!$H$2:$H$1227,"Luxury",'All relationships'!$K$2:$K$1227,"<>Recently lost") -> 1 | F51: =COUNTIFS('All relationships'!$A$2:$A$1227,A51,'All relationships'!$H$2:$H$1227,"Premium",'All relationships'!$K$2:$K$1227,"<>Recently lost") -> 3 | G51: hansgrohe and AXOR (L), Bioderma India, JBCN Group of Schools, ORRA
A52: Havas Media India | B52: Havas | C52: Media | D52: =COUNTIF('All relationships'!$A$2:$A$1227,A52) -> 3 | E52: =COUNTIFS('All relationships'!$A$2:$A$1227,A52,'All relationships'!$H$2:$H$1227,"Luxury",'All relationships'!$K$2:$K$1227,"<>Recently lost") -> 0 | F52: =COUNTIFS('All relationships'!$A$2:$A$1227,A52,'All relationships'!$H$2:$H$1227,"Premium",'All relationships'!$K$2:$K$1227,"<>Recently lost") -> 1 | G52: Joyalukkas | H52: Aakash Educational Services, Policybazaar | J52: Havas Media, Havas Media Network India
A53: Arena Media India (Havas) | B53: Havas | C53: Media | D53: =COUNTIF('All relationships'!$A$2:$A$1227,A53) -> 1 | E53: =COUNTIFS('All relationships'!$A$2:$A$1227,A53,'All relationships'!$H$2:$H$1227,"Luxury",'All relationships'!$K$2:$K$1227,"<>Recently lost") -> 0 | F53: =COUNTIFS('All relationships'!$A$2:$A$1227,A53,'All relationships'!$H$2:$H$1227,"Premium",'All relationships'!$K$2:$K$1227,"<>Recently lost") -> 1 | G53: Ashiana Housing
A54: Social Beat (Cheil) | B54: Cheil | C54: Network digital | D54: =COUNTIF('All relationships'!$A$2:$A$1227,A54) -> 8 | E54: =COUNTIFS('All relationships'!$A$2:$A$1227,A54,'All relationships'!$H$2:$H$1227,"Luxury",'All relationships'!$K$2:$K$1227,"<>Recently lost") -> 1 | F54: =COUNTIFS('All relationships'!$A$2:$A$1227,A54,'All relationships'!$H$2:$H$1227,"Premium",'All relationships'!$K$2:$K$1227,"<>Recently lost") -> 6 | G54: Mercedes-Benz India (L), Brigade Group, Cialfo, Juicy Chemistry, Kalpataru, Khazana Jewellery, Pothys | H54: Fortune | J54: Social Beat
A55: Cheil X | B55: Cheil | C55: Network creative | D55: =COUNTIF('All relationships'!$A$2:$A$1227,A55) -> 4 | E55: =COUNTIFS('All relationships'!$A$2:$A$1227,A55,'All relationships'!$H$2:$H$1227,"Luxury",'All relationships'!$K$2:$K$1227,"<>Recently lost") -> 0 | F55: =COUNTIFS('All relationships'!$A$2:$A$1227,A55,'All relationships'!$H$2:$H$1227,"Premium",'All relationships'!$K$2:$K$1227,"<>Recently lost") -> 2 | G55: JSW MG Motor India, PNB MetLife | H55: Hero MotoCorp, Luminous | J55: Cheil X India
A56: Experience Commerce (Cheil) | B56: Cheil | C56: Network digital | D56: =COUNTIF('All relationships'!$A$2:$A$1227,A56) -> 4 | E56: =COUNTIFS('All relationships'!$A$2:$A$1227,A56,'All relationships'!$H$2:$H$1227,"Luxury",'All relationships'!$K$2:$K$1227,"<>Recently lost") -> 0 | F56: =COUNTIFS('All relationships'!$A$2:$A$1227,A56,'All relationships'!$H$2:$H$1227,"Premium",'All relationships'!$K$2:$K$1227,"<>Recently lost") -> 2 | G56: ICONIQA Hotels & Resorts, MRF Tyres | H56: Eveready, Parle Candy Culture (Melody, Kismi, Londonderry) | J56: Experience Commerce (Cheil SWA)
A57: Cheil India | B57: Cheil | C57: Network creative | D57: =COUNTIF('All relationships'!$A$2:$A$1227,A57) -> 2 | E57: =COUNTIFS('All relationships'!$A$2:$A$1227,A57,'All relationships'!$H$2:$H$1227,"Luxury",'All relationships'!$K$2:$K$1227,"<>Recently lost") -> 0 | F57: =COUNTIFS('All relationships'!$A$2:$A$1227,A57,'All relationships'!$H$2:$H$1227,"Premium",'All relationships'!$K$2:$K$1227,"<>Recently lost") -> 2 | G57: Samsung India
A58: AdGlobal360 (Hakuhodo) | B58: Hakuhodo | C58: Independent digital/social | D58: =COUNTIF('All relationships'!$A$2:$A$1227,A58) -> 6 | E58: =COUNTIFS('All relationships'!$A$2:$A$1227,A58,'All relationships'!$H$2:$H$1227,"Luxury",'All relationships'!$K$2:$K$1227,"<>Recently lost") -> 4 | F58: =COUNTIFS('All relationships'!$A$2:$A$1227,A58,'All relationships'!$H$2:$H$1227,"Premium",'All relationships'!$K$2:$K$1227,"<>Recently lost") -> 0 | G58: Jaisalmer Gin (L), Porsche India (L), Radico Khaitan (L), Rampur Indian Single Malt (L) | H58: Magic Moments, TVS NTORQ | J58: AdGlobal360
A59: Hakuhodo India | B59: Hakuhodo | C59: Network creative | D59: =COUNTIF('All relationships'!$A$2:$A$1227,A59) -> 5 | E59: =COUNTIFS('All relationships'!$A$2:$A$1227,A59,'All relationships'!$H$2:$H$1227,"Luxury",'All relationships'!$K$2:$K$1227,"<>Recently lost") -> 0 | F59: =COUNTIFS('All relationships'!$A$2:$A$1227,A59,'All relationships'!$H$2:$H$1227,"Premium",'All relationships'!$K$2:$K$1227,"<>Recently lost") -> 1 | G59: Morpheus Brandy and premium launches | H59: Dizester, Jindal Stainless, Maruti Suzuki (Baleno, Service, Super Carry), Suzuki Motorcycle India | J59: Hakuhodo.Sync, Hakuhodo.Wyng
A60: PMG India (Hakuhodo) | B60: Hakuhodo | C60: Experiential | D60: =COUNTIF('All relationships'!$A$2:$A$1227,A60) -> 4 | E60: =COUNTIFS('All relationships'!$A$2:$A$1227,A60,'All relationships'!$H$2:$H$1227,"Luxury",'All relationships'!$K$2:$K$1227,"<>Recently lost") -> 3 | F60: =COUNTIFS('All relationships'!$A$2:$A$1227,A60,'All relationships'!$H$2:$H$1227,"Premium",'All relationships'!$K$2:$K$1227,"<>Recently lost") -> 1 | G60: BMW India (L), Mercedes-Benz India (L), Porsche India (L), Toyota Kirloskar Motor
A61: Schbang | B61: Independent | C61: Independent creative | D61: =COUNTIF('All relationships'!$A$2:$A$1227,A61) -> 26 | E61: =COUNTIFS('All relationships'!$A$2:$A$1227,A61,'All relationships'!$H$2:$H$1227,"Luxury",'All relationships'!$K$2:$K$1227,"<>Recently lost") -> 1 | F61: =COUNTIFS('All relationships'!$A$2:$A$1227,A61,'All relationships'!$H$2:$H$1227,"Premium",'All relationships'!$K$2:$K$1227,"<>Recently lost") -> 15 | G61: Indriya (Aditya Birla Jewellery) (L), Castrol India, HDFC Life, IDFC FIRST Bank, Kotak811, L'Oreal India, Louis Philippe, Mia by Tanishq, Skybags, Specta Quartz Surfaces, Tata Capital, Tata Communications, The Laughing Cow | H61: Amazon India, Britannia, Dabur, IIFL Home Finance, Jio, McCain India, Mentos and Centerfruit, Pidilite (Fevicol), ShareChat and Moj, Voltas
A62: Crosshairs Communication | B62: Independent | C62: Luxury boutique | D62: =COUNTIF('All relationships'!$A$2:$A$1227,A62) -> 20 | E62: =COUNTIFS('All relationships'!$A$2:$A$1227,A62,'All relationships'!$H$2:$H$1227,"Luxury",'All relationships'!$K$2:$K$1227,"<>Recently lost") -> 15 | F62: =COUNTIFS('All relationships'!$A$2:$A$1227,A62,'All relationships'!$H$2:$H$1227,"Premium",'All relationships'!$K$2:$K$1227,"<>Recently lost") -> 5 | G62: Big Boy Toyz (L), Fairmont Jaipur (L), Harry Winston (L), Hazoorilal (L), Hermes India (L), Khurana Jewellery House (L), Kiehl's India (L), L'Occitane India (L), Le Royal Monceau Raffles Paris (L), OBEETEE (L), Raffles Udaipur (L), Raghavendra Rathore Jodhpur (L), Taj Hotels (IHCL) (L), Tarun Tahiliani (L), Thomas Goode & Co. (L), Accor India (Raffles, Fairmont, Sofitel), Aspri Spirits, Luxmi Tea, Moroccanoil, ORRA
A63: SW Network (Sociowash) | B63: Independent | C63: Independent digital/social | D63: =COUNTIF('All relationships'!$A$2:$A$1227,A63) -> 18 | E63: =COUNTIFS('All relationships'!$A$2:$A$1227,A63,'All relationships'!$H$2:$H$1227,"Luxury",'All relationships'!$K$2:$K$1227,"<>Recently lost") -> 2 | F63: =COUNTIFS('All relationships'!$A$2:$A$1227,A63,'All relationships'!$H$2:$H$1227,"Premium",'All relationships'!$K$2:$K$1227,"<>Recently lost") -> 12 | G63: MINI India (L), Nexus Select Citywalk (L), AGEasy, Anytime Fitness India, FILA India, Foot Locker India, Fujifilm India (instax, X Series), Garden Vareli, Motorola Razr 60, Nykaa, Titan licensed watches (Kenneth Cole, Tommy Hilfiger) | H63: inDrive, Lava Mobiles, Livpure, Myntra | J63: Sociowash, SW Network, SW Network (Youthbeat)
A64: Grapes Worldwide | B64: Independent | C64: Independent digital/social | D64: =COUNTIF('All relationships'!$A$2:$A$1227,A64) -> 17 | E64: =COUNTIFS('All relationships'!$A$2:$A$1227,A64,'All relationships'!$H$2:$H$1227,"Luxury",'All relationships'!$K$2:$K$1227,"<>Recently lost") -> 8 | F64: =COUNTIFS('All relationships'!$A$2:$A$1227,A64,'All relationships'!$H$2:$H$1227,"Premium",'All relationships'!$K$2:$K$1227,"<>Recently lost") -> 6 | G64: Balenciaga (L), Burberry (L), Cartier (L), Estee Lauder India (Estee Lauder, MAC, Clinique) (L), Gucci (L), Louis Vuitton (L), Piramal Realty (L), Tiffany & Co. (L), Absolut, Campari, Harley-Davidson, Jameson, LivWell, Samsonite | H64: Bikano, MamyPoko Pants, Vibhor Oils
A65: The Womb | B65: Independent | C65: Independent creative | D65: =COUNTIF('All relationships'!$A$2:$A$1227,A65) -> 17 | E65: =COUNTIFS('All relationships'!$A$2:$A$1227,A65,'All relationships'!$H$2:$H$1227,"Luxury",'All relationships'!$K$2:$K$1227,"<>Recently lost") -> 0 | F65: =COUNTIFS('All relationships'!$A$2:$A$1227,A65,'All relationships'!$H$2:$H$1227,"Premium",'All relationships'!$K$2:$K$1227,"<>Recently lost") -> 5 | G65: Asus, Bosch, Siemens and Gaggenau (BSH), Mahindra Lifespaces, Mahindra Thar ROXX, Sebamed | H65: Britannia, Danone, Dinshaw's, Gullak, Nilkamal, Piramal Finance, Rasna, Symphony, upGrad, Vini Cosmetics (Fogg), Wonder Cement
A66: Hashtag Orange | B66: Independent | C66: Independent digital/social | D66: =COUNTIF('All relationships'!$A$2:$A$1227,A66) -> 15 | E66: =COUNTIFS('All relationships'!$A$2:$A$1227,A66,'All relationships'!$H$2:$H$1227,"Luxury",'All relationships'!$K$2:$K$1227,"<>Recently lost") -> 1 | F66: =COUNTIFS('All relationships'!$A$2:$A$1227,A66,'All relationships'!$H$2:$H$1227,"Premium",'All relationships'!$K$2:$K$1227,"<>Recently lost") -> 8 | G66: Forest Essentials (L), Aparna Venster and Okotech, Dr. Reddy's, Monte Carlo, Mufti, Nestle Health Science, ROCA India, SafeTree, The Man Company | H66: Escorts Kubota MU Series, Frankfinn Institute, Krazy Kebab Co, Swiss Beauty, Taco Bell India, Zuno General Insurance
A67: Talented | B67: Independent | C67: Independent creative | D67: =COUNTIF('All relationships'!$A$2:$A$1227,A67) -> 14 | E67: =COUNTIFS('All relationships'!$A$2:$A$1227,A67,'All relationships'!$H$2:$H$1227,"Luxury",'All relationships'!$K$2:$K$1227,"<>Recently lost") -> 1 | F67: =COUNTIFS('All relationships'!$A$2:$A$1227,A67,'All relationships'!$H$2:$H$1227,"Premium",'All relationships'!$K$2:$K$1227,"<>Recently lost") -> 4 | G67: Forest Essentials (L), HomeLane, Tanishq, The Hindu, Urban Company | H67: Britannia, Cars24, Cleartrip, Duolingo, Flipkart, Pantaloons, Rimzim Jeera, Star Health Insurance, Swiggy
A68: Tonic Worldwide | B68: Independent | C68: Independent digital/social | D68: =COUNTIF('All relationships'!$A$2:$A$1227,A68) -> 14 | E68: =COUNTIFS('All relationships'!$A$2:$A$1227,A68,'All relationships'!$H$2:$H$1227,"Luxury",'All relationships'!$K$2:$K$1227,"<>Recently lost") -> 1 | F68: =COUNTIFS('All relationships'!$A$2:$A$1227,A68,'All relationships'!$H$2:$H$1227,"Premium",'All relationships'!$K$2:$K$1227,"<>Recently lost") -> 6 | G68: Monarch Legacy Edition (L), Motilal Oswal Financial Services, PCPL (Pranav Constructions), Seven Islands Whisky, Tata Housing, Triumph | H68: airpay money, Bingo!, Fiesta Condoms, Kurlon, MuscleBlaze, NICMAR, Parachute Advansed
A69: Famous Innovations | B69: Independent | C69: Independent creative | D69: =COUNTIF('All relationships'!$A$2:$A$1227,A69) -> 13 | E69: =COUNTIFS('All relationships'!$A$2:$A$1227,A69,'All relationships'!$H$2:$H$1227,"Luxury",'All relationships'!$K$2:$K$1227,"<>Recently lost") -> 2 | F69: =COUNTIFS('All relationships'!$A$2:$A$1227,A69,'All relationships'!$H$2:$H$1227,"Premium",'All relationships'!$K$2:$K$1227,"<>Recently lost") -> 5 | G69: Platinum Guild International (L), Taneira (L), Adidas India, BIBA, Mia by Tanishq, Sebamed, World Pickleball League | H69: Airtel, B Natural, Haier India, Kamiliant, Nilkamal Sleep, OPPO India
A70: Moonshot | B70: Independent | C70: Independent creative | D70: =COUNTIF('All relationships'!$A$2:$A$1227,A70) -> 13 | E70: =COUNTIFS('All relationships'!$A$2:$A$1227,A70,'All relationships'!$H$2:$H$1227,"Luxury",'All relationships'!$K$2:$K$1227,"<>Recently lost") -> 0 | F70: =COUNTIFS('All relationships'!$A$2:$A$1227,A70,'All relationships'!$H$2:$H$1227,"Premium",'All relationships'!$K$2:$K$1227,"<>Recently lost") -> 2 | G70: CRED, Mokobara | H70: Bold Care, Campus Activewear, Dr Agarwal's Eye Hospital, Gabit, Lenskart, MakeMyTrip, OYO, Shaadi.com, Subway India, Swiggy Instamart, Wild Stone
A71: Enormous Brands | B71: Independent | C71: Independent creative | D71: =COUNTIF('All relationships'!$A$2:$A$1227,A71) -> 12 | E71: =COUNTIFS('All relationships'!$A$2:$A$1227,A71,'All relationships'!$H$2:$H$1227,"Luxury",'All relationships'!$K$2:$K$1227,"<>Recently lost") -> 0 | F71: =COUNTIFS('All relationships'!$A$2:$A$1227,A71,'All relationships'!$H$2:$H$1227,"Premium",'All relationships'!$K$2:$K$1227,"<>Recently lost") -> 5 | G71: Bombay Shaving Company, Duroflex and Sleepyhead, Jaquar Lighting, Nua | H71: Dish TV, Hero FinCorp, Lahori Zeera, Navneet, Ralco Tyres, Reliance Consumer Products, Veeba | J71: Enormous
A72: SoCheers | B72: Independent | C72: Independent digital/social | D72: =COUNTIF('All relationships'!$A$2:$A$1227,A72) -> 11 | E72: =COUNTIFS('All relationships'!$A$2:$A$1227,A72,'All relationships'!$H$2:$H$1227,"Luxury",'All relationships'!$K$2:$K$1227,"<>Recently lost") -> 2 | F72: =COUNTIFS('All relationships'!$A$2:$A$1227,A72,'All relationships'!$H$2:$H$1227,"Premium",'All relationships'!$K$2:$K$1227,"<>Recently lost") -> 7 | G72: Chandon (L), Glenmorangie (L), Asus, Broadway, Carlton, IndusInd General Insurance, Superdry Sport, The Belgian Waffle Co. | I72: Audi India, Godrej Interio
A73: Rediffusion | B73: Independent | C73: Independent creative | D73: =COUNTIF('All relationships'!$A$2:$A$1227,A73) -> 10 | E73: =COUNTIFS('All relationships'!$A$2:$A$1227,A73,'All relationships'!$H$2:$H$1227,"Luxury",'All relationships'!$K$2:$K$1227,"<>Recently lost") -> 1 | F73: =COUNTIFS('All relationships'!$A$2:$A$1227,A73,'All relationships'!$H$2:$H$1227,"Premium",'All relationships'!$K$2:$K$1227,"<>Recently lost") -> 2 | G73: Taj Hotels (IHCL) (L), Liebherr Refrigerators, Nippon India Mutual Fund | H73: Glucon-D, Keya Foods, Londonderry, Prabhuji Pure Food, Protinex, Tata Power | I73: BMW India
A74: White Rivers Media | B74: Independent | C74: Independent digital/social | D74: =COUNTIF('All relationships'!$A$2:$A$1227,A74) -> 10 | E74: =COUNTIFS('All relationships'!$A$2:$A$1227,A74,'All relationships'!$H$2:$H$1227,"Luxury",'All relationships'!$K$2:$K$1227,"<>Recently lost") -> 1 | F74: =COUNTIFS('All relationships'!$A$2:$A$1227,A74,'All relationships'!$H$2:$H$1227,"Premium",'All relationships'!$K$2:$K$1227,"<>Recently lost") -> 4 | G74: Piramal Realty (L), Reliance Jewels, The Times of India | H74: boAt, Pulse Candy, SMFG India Credit, Swiggy Dineout
A75: BC Web Wise | B75: Independent | C75: Independent digital/social | D75: =COUNTIF('All relationships'!$A$2:$A$1227,A75) -> 9 | E75: =COUNTIFS('All relationships'!$A$2:$A$1227,A75,'All relationships'!$H$2:$H$1227,"Luxury",'All relationships'!$K$2:$K$1227,"<>Recently lost") -> 0 | F75: =COUNTIFS('All relationships'!$A$2:$A$1227,A75,'All relationships'!$H$2:$H$1227,"Premium",'All relationships'!$K$2:$K$1227,"<>Recently lost") -> 3 | G75: Birla Estates, HDOR (Hundred Days of Running), Tira | H75: Gatsby, LIC Housing Finance, mPokket, MsChief, Tiger Balm, Zuno General Insurance
A76: Social Panga | B76: Independent | C76: Independent digital/social | D76: =COUNTIF('All relationships'!$A$2:$A$1227,A76) -> 9 | E76: =COUNTIFS('All relationships'!$A$2:$A$1227,A76,'All relationships'!$H$2:$H$1227,"Luxury",'All relationships'!$K$2:$K$1227,"<>Recently lost") -> 0 | F76: =COUNTIFS('All relationships'!$A$2:$A$1227,A76,'All relationships'!$H$2:$H$1227,"Premium",'All relationships'!$K$2:$K$1227,"<>Recently lost") -> 5 | G76: AMD India (Ryzen AI), DeVANS (Godfather, Six Fields, GianChand), Tata AIG General Insurance, Van Heusen Innerwear | H76: Amazon Now, Miniklub, Neo by Nippon Paint | I76: Balaji Wafers
A77: Team Pumpkin | B77: Independent | C77: Independent digital/social | D77: =COUNTIF('All relationships'!$A$2:$A$1227,A77) -> 8 | E77: =COUNTIFS('All relationships'!$A$2:$A$1227,A77,'All relationships'!$H$2:$H$1227,"Luxury",'All relationships'!$K$2:$K$1227,"<>Recently lost") -> 0 | F77: =COUNTIFS('All relationships'!$A$2:$A$1227,A77,'All relationships'!$H$2:$H$1227,"Premium",'All relationships'!$K$2:$K$1227,"<>Recently lost") -> 6 | G77: AlphaTheta (Pioneer DJ), Kickers, Koche, Kotak Securities, Plum, Royaloak | H77: Lavie, The Souled Store
A78: Creativeland Asia | B78: Independent | C78: Independent creative | D78: =COUNTIF('All relationships'!$A$2:$A$1227,A78) -> 7 | E78: =COUNTIFS('All relationships'!$A$2:$A$1227,A78,'All relationships'!$H$2:$H$1227,"Luxury",'All relationships'!$K$2:$K$1227,"<>Recently lost") -> 0 | F78: =COUNTIFS('All relationships'!$A$2:$A$1227,A78,'All relationships'!$H$2:$H$1227,"Premium",'All relationships'!$K$2:$K$1227,"<>Recently lost") -> 5 | G78: Del Monte India, Hero Vida, Kotak Mahindra Bank, Uniqlo India | H78: Pizza Hut India, realme
A79: Lyxel&Flamingo | B79: Independent | C79: Independent digital/social | D79: =COUNTIF('All relationships'!$A$2:$A$1227,A79) -> 7 | E79: =COUNTIFS('All relationships'!$A$2:$A$1227,A79,'All relationships'!$H$2:$H$1227,"Luxury",'All relationships'!$K$2:$K$1227,"<>Recently lost") -> 1 | F79: =COUNTIFS('All relationships'!$A$2:$A$1227,A79,'All relationships'!$H$2:$H$1227,"Premium",'All relationships'!$K$2:$K$1227,"<>Recently lost") -> 4 | G79: Omega (L), Converse India, Kimirica, O3+, United Colors of Benetton | H79: Big Bowl, Kurlon
A80: One Hand Clap | B80: Independent | C80: Independent creative | D80: =COUNTIF('All relationships'!$A$2:$A$1227,A80) -> 7 | E80: =COUNTIFS('All relationships'!$A$2:$A$1227,A80,'All relationships'!$H$2:$H$1227,"Luxury",'All relationships'!$K$2:$K$1227,"<>Recently lost") -> 0 | F80: =COUNTIFS('All relationships'!$A$2:$A$1227,A80,'All relationships'!$H$2:$H$1227,"Premium",'All relationships'!$K$2:$K$1227,"<>Recently lost") -> 5 | G80: Bajaj Chetak, Bumble India, Netflix India, Prime Video, Underneat | H80: EMotorad, Swiggy Instamart
A81: Liqvd Asia | B81: Independent | C81: Independent digital/social | D81: =COUNTIF('All relationships'!$A$2:$A$1227,A81) -> 6 | E81: =COUNTIFS('All relationships'!$A$2:$A$1227,A81,'All relationships'!$H$2:$H$1227,"Luxury",'All relationships'!$K$2:$K$1227,"<>Recently lost") -> 0 | F81: =COUNTIFS('All relationships'!$A$2:$A$1227,A81,'All relationships'!$H$2:$H$1227,"Premium",'All relationships'!$K$2:$K$1227,"<>Recently lost") -> 4 | G81: Narayana Health, Woodland, Wozoyo | H81: Kasturi Foods, Origami
A82: Tilt Brand Solutions | B82: Independent | C82: Independent creative | D82: =COUNTIF('All relationships'!$A$2:$A$1227,A82) -> 6 | E82: =COUNTIFS('All relationships'!$A$2:$A$1227,A82,'All relationships'!$H$2:$H$1227,"Luxury",'All relationships'!$K$2:$K$1227,"<>Recently lost") -> 0 | F82: =COUNTIFS('All relationships'!$A$2:$A$1227,A82,'All relationships'!$H$2:$H$1227,"Premium",'All relationships'!$K$2:$K$1227,"<>Recently lost") -> 3 | G82: Ather Energy, Enamor, Myntra | H82: Bajaj Auto, Dream11, Santoor
A83: Makani Creatives | B83: Independent | C83: Independent creative | D83: =COUNTIF('All relationships'!$A$2:$A$1227,A83) -> 5 | E83: =COUNTIFS('All relationships'!$A$2:$A$1227,A83,'All relationships'!$H$2:$H$1227,"Luxury",'All relationships'!$K$2:$K$1227,"<>Recently lost") -> 0 | F83: =COUNTIFS('All relationships'!$A$2:$A$1227,A83,'All relationships'!$H$2:$H$1227,"Premium",'All relationships'!$K$2:$K$1227,"<>Recently lost") -> 3 | G83: Florsheim India, IRUS Eyewear, Shoppers Stop | H83: American Tourister, Stimulus and Eeken
A84: Verve Media | B84: Independent | C84: Independent digital/social | D84: =COUNTIF('All relationships'!$A$2:$A$1227,A84) -> 5 | E84: =COUNTIFS('All relationships'!$A$2:$A$1227,A84,'All relationships'!$H$2:$H$1227,"Luxury",'All relationships'!$K$2:$K$1227,"<>Recently lost") -> 0 | F84: =COUNTIFS('All relationships'!$A$2:$A$1227,A84,'All relationships'!$H$2:$H$1227,"Premium",'All relationships'!$K$2:$K$1227,"<>Recently lost") -> 2 | G84: Maple India, Vedas Fund | H84: Rasoi Raga, Shriram General Insurance, Snitch
A85: Bang in the Middle | B85: Independent | C85: Independent creative | D85: =COUNTIF('All relationships'!$A$2:$A$1227,A85) -> 4 | E85: =COUNTIFS('All relationships'!$A$2:$A$1227,A85,'All relationships'!$H$2:$H$1227,"Luxury",'All relationships'!$K$2:$K$1227,"<>Recently lost") -> 1 | F85: =COUNTIFS('All relationships'!$A$2:$A$1227,A85,'All relationships'!$H$2:$H$1227,"Premium",'All relationships'!$K$2:$K$1227,"<>Recently lost") -> 1 | G85: Antara Senior Living (L), Groupe SEB India (Tefal, Maharaja Whiteline) | H85: Mother's Recipe | I85: Medanta
A86: Confiance Communications | B86: Independent | C86: PR | D86: =COUNTIF('All relationships'!$A$2:$A$1227,A86) -> 4 | E86: =COUNTIFS('All relationships'!$A$2:$A$1227,A86,'All relationships'!$H$2:$H$1227,"Luxury",'All relationships'!$K$2:$K$1227,"<>Recently lost") -> 1 | F86: =COUNTIFS('All relationships'!$A$2:$A$1227,A86,'All relationships'!$H$2:$H$1227,"Premium",'All relationships'!$K$2:$K$1227,"<>Recently lost") -> 3 | G86: Raga Svara (L), Libertario Coffee India, The Pant Project, Turkiye Tourism
A87: Curativity | B87: Independent | C87: Independent creative | D87: =COUNTIF('All relationships'!$A$2:$A$1227,A87) -> 4 | E87: =COUNTIFS('All relationships'!$A$2:$A$1227,A87,'All relationships'!$H$2:$H$1227,"Luxury",'All relationships'!$K$2:$K$1227,"<>Recently lost") -> 0 | F87: =COUNTIFS('All relationships'!$A$2:$A$1227,A87,'All relationships'!$H$2:$H$1227,"Premium",'All relationships'!$K$2:$K$1227,"<>Recently lost") -> 1 | G87: Axis Bank | H87: Gulf Oil Lubricants India, Too Yumm!, Urbn
A88: Digital Refresh Networks | B88: Independent | C88: Independent digital/social | D88: =COUNTIF('All relationships'!$A$2:$A$1227,A88) -> 4 | E88: =COUNTIFS('All relationships'!$A$2:$A$1227,A88,'All relationships'!$H$2:$H$1227,"Luxury",'All relationships'!$K$2:$K$1227,"<>Recently lost") -> 0 | F88: =COUNTIFS('All relationships'!$A$2:$A$1227,A88,'All relationships'!$H$2:$H$1227,"Premium",'All relationships'!$K$2:$K$1227,"<>Recently lost") -> 1 | G88: Mia by Tanishq | H88: Hari:Bol, LIC, Nissin Geki Korean Noodles
A89: Madison Media | B89: Independent | C89: Media | D89: =COUNTIF('All relationships'!$A$2:$A$1227,A89) -> 4 | E89: =COUNTIFS('All relationships'!$A$2:$A$1227,A89,'All relationships'!$H$2:$H$1227,"Luxury",'All relationships'!$K$2:$K$1227,"<>Recently lost") -> 0 | F89: =COUNTIFS('All relationships'!$A$2:$A$1227,A89,'All relationships'!$H$2:$H$1227,"Premium",'All relationships'!$K$2:$K$1227,"<>Recently lost") -> 2 | G89: Pilgrim, Tata Starbucks | H89: Jindal Stainless | I89: TVS Motor | J89: Madison Media Alpha, Madison World, MOMS (Madison Outdoor Media Solutions)
A90: Quirk Head | B90: Independent | C90: Luxury boutique | D90: =COUNTIF('All relationships'!$A$2:$A$1227,A90) -> 4 | E90: =COUNTIFS('All relationships'!$A$2:$A$1227,A90,'All relationships'!$H$2:$H$1227,"Luxury",'All relationships'!$K$2:$K$1227,"<>Recently lost") -> 3 | F90: =COUNTIFS('All relationships'!$A$2:$A$1227,A90,'All relationships'!$H$2:$H$1227,"Premium",'All relationships'!$K$2:$K$1227,"<>Recently lost") -> 1 | G90: The Leela Palace Jaipur (L), The Westin Gurgaon (L), The Westin Sohna Resort (L), Marriott Udaipur and Jim Corbett
A91: Scribbld | B91: Independent | C91: Independent digital/social | D91: =COUNTIF('All relationships'!$A$2:$A$1227,A91) -> 4 | E91: =COUNTIFS('All relationships'!$A$2:$A$1227,A91,'All relationships'!$H$2:$H$1227,"Luxury",'All relationships'!$K$2:$K$1227,"<>Recently lost") -> 0 | F91: =COUNTIFS('All relationships'!$A$2:$A$1227,A91,'All relationships'!$H$2:$H$1227,"Premium",'All relationships'!$K$2:$K$1227,"<>Recently lost") -> 4 | G91: Brushers Co, Foot Locker India, Suzette, Terrapy
A92: Sideways | B92: Independent | C92: Independent creative | D92: =COUNTIF('All relationships'!$A$2:$A$1227,A92) -> 4 | E92: =COUNTIFS('All relationships'!$A$2:$A$1227,A92,'All relationships'!$H$2:$H$1227,"Luxury",'All relationships'!$K$2:$K$1227,"<>Recently lost") -> 0 | F92: =COUNTIFS('All relationships'!$A$2:$A$1227,A92,'All relationships'!$H$2:$H$1227,"Premium",'All relationships'!$K$2:$K$1227,"<>Recently lost") -> 2 | G92: Happilo, Licious | H92: Aakash Educational Services, Haisha Paints
A93: The Minimalist | B93: Independent | C93: Independent digital/social | D93: =COUNTIF('All relationships'!$A$2:$A$1227,A93) -> 4 | E93: =COUNTIFS('All relationships'!$A$2:$A$1227,A93,'All relationships'!$H$2:$H$1227,"Luxury",'All relationships'!$K$2:$K$1227,"<>Recently lost") -> 0 | F93: =COUNTIFS('All relationships'!$A$2:$A$1227,A93,'All relationships'!$H$2:$H$1227,"Premium",'All relationships'!$K$2:$K$1227,"<>Recently lost") -> 2 | G93: AFC Furniture Solutions, Schwarzkopf India | H93: Eveready, TyresNmore
A94: Webenza | B94: Independent | C94: Independent digital/social | D94: =COUNTIF('All relationships'!$A$2:$A$1227,A94) -> 4 | E94: =COUNTIFS('All relationships'!$A$2:$A$1227,A94,'All relationships'!$H$2:$H$1227,"Luxury",'All relationships'!$K$2:$K$1227,"<>Recently lost") -> 0 | F94: =COUNTIFS('All relationships'!$A$2:$A$1227,A94,'All relationships'!$H$2:$H$1227,"Premium",'All relationships'!$K$2:$K$1227,"<>Recently lost") -> 3 | G94: Brigade Group, Prestige Group, Sterling Holidays | H94: Joy Personal Care
A95: Actimedia PR | B95: Independent | C95: PR | D95: =COUNTIF('All relationships'!$A$2:$A$1227,A95) -> 3 | E95: =COUNTIFS('All relationships'!$A$2:$A$1227,A95,'All relationships'!$H$2:$H$1227,"Luxury",'All relationships'!$K$2:$K$1227,"<>Recently lost") -> 1 | F95: =COUNTIFS('All relationships'!$A$2:$A$1227,A95,'All relationships'!$H$2:$H$1227,"Premium",'All relationships'!$K$2:$K$1227,"<>Recently lost") -> 2 | G95: ITC Hotels (L), Air Canada, Senco Gold & Diamonds | J95: ActiMedia, Actimedia PR & Digital
A96: AdLift (Liqvd Asia) | B96: Independent | C96: Independent digital/social | D96: =COUNTIF('All relationships'!$A$2:$A$1227,A96) -> 3 | E96: =COUNTIFS('All relationships'!$A$2:$A$1227,A96,'All relationships'!$H$2:$H$1227,"Luxury",'All relationships'!$K$2:$K$1227,"<>Recently lost") -> 0 | F96: =COUNTIFS('All relationships'!$A$2:$A$1227,A96,'All relationships'!$H$2:$H$1227,"Premium",'All relationships'!$K$2:$K$1227,"<>Recently lost") -> 3 | G96: Casagrand, Indriya (Aditya Birla Jewellery) | J96: AdLift
A97: Braindad | B97: Independent | C97: Independent creative | D97: =COUNTIF('All relationships'!$A$2:$A$1227,A97) -> 3 | E97: =COUNTIFS('All relationships'!$A$2:$A$1227,A97,'All relationships'!$H$2:$H$1227,"Luxury",'All relationships'!$K$2:$K$1227,"<>Recently lost") -> 0 | F97: =COUNTIFS('All relationships'!$A$2:$A$1227,A97,'All relationships'!$H$2:$H$1227,"Premium",'All relationships'!$K$2:$K$1227,"<>Recently lost") -> 2 | G97: Myntra, TRESemme | H97: super.money
A98: Creativefuel | B98: Independent | C98: Independent digital/social | D98: =COUNTIF('All relationships'!$A$2:$A$1227,A98) -> 3 | E98: =COUNTIFS('All relationships'!$A$2:$A$1227,A98,'All relationships'!$H$2:$H$1227,"Luxury",'All relationships'!$K$2:$K$1227,"<>Recently lost") -> 0 | F98: =COUNTIFS('All relationships'!$A$2:$A$1227,A98,'All relationships'!$H$2:$H$1227,"Premium",'All relationships'!$K$2:$K$1227,"<>Recently lost") -> 0 | H98: Balaji Wafers, JioHotstar, Priyagold
A99: Glad U Came | B99: Independent | C99: PR | D99: =COUNTIF('All relationships'!$A$2:$A$1227,A99) -> 3 | E99: =COUNTIFS('All relationships'!$A$2:$A$1227,A99,'All relationships'!$H$2:$H$1227,"Luxury",'All relationships'!$K$2:$K$1227,"<>Recently lost") -> 1 | F99: =COUNTIFS('All relationships'!$A$2:$A$1227,A99,'All relationships'!$H$2:$H$1227,"Premium",'All relationships'!$K$2:$K$1227,"<>Recently lost") -> 2 | G99: World Luxury Chamber of Commerce (L), Eze Perfumes, Park Avenue
A100: Gozoop (now YAAP) | B100: Independent | C100: Independent digital/social | D100: =COUNTIF('All relationships'!$A$2:$A$1227,A100) -> 3 | E100: =COUNTIFS('All relationships'!$A$2:$A$1227,A100,'All relationships'!$H$2:$H$1227,"Luxury",'All relationships'!$K$2:$K$1227,"<>Recently lost") -> 0 | F100: =COUNTIFS('All relationships'!$A$2:$A$1227,A100,'All relationships'!$H$2:$H$1227,"Premium",'All relationships'!$K$2:$K$1227,"<>Recently lost") -> 3 | G100: CookieMan India, Godrej Properties, Tata Tele Business Services | J100: Gozoop Creative, Gozoop Hawk
...

Sheet Agency turmoil 2025-26
A1: Group | B1: Agency | C1: What changed | D1: When | E1: Why it opens doors | F1: Accounts exposed (from this map, luxury and premium first) | G1: Source
A2: Omnicom | B2: DDB Mudra (brand retired) | C2: Omnicom closed its IPG deal and retired the DDB, FCB and MullenLowe brands. India now runs as Omnicom Advertising India under Prasoon Joshi (chairman) and Aditya Kanthy (president). | D2: Dec 2025 to Jan 2026 | E2: Clients were redistributed across McCann, BBDO Group and TBWA\Lintas. Several legacy DDB accounts still show no confirmed new home. | F2: Adani Group (corporate), Ethnix by Raymond, Infosys, Instagram, Malabar Gold & Diamonds, Meta AI, Myntra, Narayana Health, Netflix India, Philips, Raymond, Royal Challenge, Spotify India, ACKO, plus 13 more | G2: afaqs: Aditya Kanthy and Prasoon Joshi to steer Omnicom's India reboot
A3: Omnicom | B3: BBDO Group India (BBDO, Ulka, Mudra) | C3: Mudra and Ulka (ex FCB Ulka) moved under BBDO Group India. Jitender Dabas became group CEO in Feb 2026. | D3: Dec 2025 to Feb 2026 | E3: Repeated leadership change at BBDO, which holds Mercedes-Benz India and World Gold Council. | F3: Mercedes-Benz India (L), Bhima Jewellers, DAAWAT, Dewar's, Gillette, Kansai Nerolac, McDonald's India (North & East), Provident Housing (Puravankara), Shoppers Stop, Sunfeast Dark Fantasy, Tata Ultra Marathon, WhatsApp, Whiskas, World Gold Council India, plus 11 more | G3: Storyboard18: Ulka, Mudra find new home in BBDO after Omnicom IPG merger
A4: Omnicom | B4: TBWA\Lintas (ex MullenLowe Lintas and TBWA India) | C4: MullenLowe Lintas and TBWA India merged into TBWA\Lintas from 1 Jan 2026. Co-CEO Prateek Bharadwaj was reported to be exiting in Feb 2026. | D4: Jan to Feb 2026 | E4: Decades-old Lintas accounts (Tanishq, Axis Bank) now sit in a newly merged agency with changing leadership. | F4: Hyatt India (L), Rivaah by Tanishq (L), Axis Bank, Classic Legends (Jawa, Yezdi, BSA), Dosti Realty, Eicher Motors, Etihad Airways, FabIndia, Google Gemini, Havells, Hershey's, Hilton India, Hindware Italian Collection, IndusInd Bank, plus 52 more | G4: Storyboard18 (via Google News): Prateek Bharadwaj to exit TBWA\Lintas?
A5: Omnicom | B5: McCann India (absorbed FCB India) | C5: FCB India was folded into McCann India under CEO Dheeraj Sinha, with ex DDB CCO Rahul Mathew running creative. | D5: Dec 2025 to 2026 | E5: Competing clients now share one roof (for example KFC and Burger King inside Omnicom). Former FCB accounts show no 2026 work. | F5: Hilton India (L), Air India, Android, Asian Paints, Berger Paints (Silk Glamor), Birla Estates, Buckaroo, Centrum, CERA Sanitaryware, DBS Bank India, Johnson's Baby, Mahindra electric SUVs (BE 6, XEV 9e), Mahindra Thar ROXX, Manyavar, plus 30 more | G5: afaqs: CEO Dheeraj Sinha on leading McCann in the post-merger era
A6: WPP | B6: WPP Creative India (Ogilvy, VML, AKQA, Grey, Landor, Burson, Design Bridge) | C6: WPP put its India creative agencies under one unit, WPP Creative India, with Hephzibah Pathak as CEO. | D6: Apr 2026 | E6: Integration year: teams, leaders and account structures are shifting across all WPP creative clients. | F6: All WPP creative clients (see rows below) | G6: afaqs (via Google News): Ogilvy chair Hephzibah Pathak appointed CEO of WPP Creative India
A7: WPP | B7: Grey 82.5 (Ogilvy group) | C7: Grey India and 82.5 Communications were merged into Grey 82.5 under Ogilvy. Grey's CCO left in Jul 2026. | D7: Jun to Jul 2026 | E7: Former Grey and 82.5 clients are mid-transition. | F7: De Beers Forevermark (L), Bacardi India, Havells, Himalayan Natural Mineral Water, Indian Craft Brewery, JSW MG Motor India, Kajaria Ceramics, Kalapuri, MMTC-PAMP, Tanishq, Tata Coffee Grand Cold Coffee, Axis Bank, Bandhan Mutual Fund, Imperial Blue, plus 3 more | G7: afaqs: Ogilvy Group integrates Grey and 82.5 Communications to form Grey 82.5
A8: WPP | B8: VML India (incl. Contract, Mirum, The Glitch) | C8: Group CCO Kalpesh Patankar left VML India in Aug 2026 and joined Publicis in Sep 2026. The CSO also left earlier in 2026. | D8: Aug to Sep 2026 | E8: Creative leadership gap on auto and tech accounts. | F8: Anita Dongre (House of Anita Dongre) (L), BMW India (L), Diageo India Reserve portfolio (L), MINI India (L), Adani Realty, CenturyPly, CERA Sanitaryware, Cult.Sport, Diageo India (portfolio), Dove, Enamor, HSBC India, Kalapuri, KISNA, plus 21 more | G8: bestmediainfo (via Google News): Kalpesh Patankar exits VML India
A9: WPP | B9: Burson India | C9: WPP hired Goldman Sachs to explore a sale of Burson. | D9: Apr 2026 | E9: PR clients face a possible change of owner. | F9: Chalet Hotels (Athiva) (L), Ducati India (L), Birla Opus Paints, Honda Cars India, Mirae Asset Sharekhan, Eastman Auto & Power | G9: bestmediainfo (via Google News): WPP explores Burson sale
A10: WPP | B10: Ogilvy India | C10: Piyush Pandey, the face of Ogilvy India, died in Oct 2025. | D10: Oct 2025 | E10: Long-tenure accounts enter a new era. Luxury sub-brands (Emporio, Indriya, Raga) are run inside mass-market teams. | F10: Aqua Plumbings (Plumber Bathware, Aquini) (L), Asian Paints Emporio (L), Adani Airports, Allen Solly, Asian Paints, Asian Paints Beautiful Homes, Brooke Bond Taj Mahal, Cadbury Dairy Milk Silk, Godrej Properties, Indriya (Aditya Birla Jewellery), Lakme, Rustomjee, Titan Raga, Amazon India, plus 25 more | G10: afaqs: Industry in mourning over Piyush Pandey's demise
A11: Publicis | B11: BBH India (absorbed Publicis India) | C11: Publicis Groupe folded Publicis India into BBH India. | D11: Jan 2026 | E11: Former Publicis India clients changed teams after the MD who fronted them left in 2025. | F11: Taj Hotels (IHCL) (L), CaratLane, DP World, HDFC Mutual Fund, Oaksmith, Skoda Auto India, CYBX, Garnier Men, HDFC Ergo, JAPFA, Microtek, Navratna, Nerolac Paints, Nestle Milkmaid, plus 5 more | G11: Storyboard18 (via Google News): Publicis folds Publicis India into BBH
A12: Publicis | B12: Publicis Digital Experience (Digitas, Razorfish, Indigo Consulting) | C12: Digitas, Razorfish and Indigo Consulting were combined into PDX under CEO Amaresh Godbole. | D12: Jan 2026 | E12: Digital and social clients were re-teamed. | F12: Corona, Duolingo, EquBot, Figaro and Bertolli olive oils, Matter, boAt, Okaya, Renault India (Kiger) | G12: Storyboard18 (via Google News): Publicis brings PDX to India
... A23: Independent | B23: Big Bang Social (Collective Artists Network) | C23: Layoffs at the creator platform, which its owner is also looking to sell. | D23: Feb to Apr 2026 | E23: Influencer and creator mandates at risk. | F23: None mapped | G23: Storyboard18 (via Google News): Layoffs at Collective Artists Network hit Big Bang Social

Sheet Category by group
A1: Current relationships by category and agency group (excludes Recently lost). Unknown means no agency credited: often in-house, often an open door.
A3: Category | B3: WPP | C3: Publicis | D3: Omnicom | E3: Dentsu | F3: Havas | G3: Cheil | H3: Hakuhodo | I3: Independent | J3: Other | K3: Unknown or in-house | L3: Total
A4: Luxury hospitality & travel | B4: =COUNTIFS('All relationships'!$G$2:$G$1227,$A4,'All relationships'!$B$2:$B$1227,"WPP",'All relationships'!$K$2:$K$1227,"<>Recently lost") -> 3 | C4: =COUNTIFS('All relationships'!$G$2:$G$1227,$A4,'All relationships'!$B$2:$B$1227,"Publicis",'All relationships'!$K$2:$K$1227,"<>Recently lost") -> 2 | D4: =COUNTIFS('All relationships'!$G$2:$G$1227,$A4,'All relationships'!$B$2:$B$1227,"Omnicom",'All relationships'!$K$2:$K$1227,"<>Recently lost") -> 9 | E4: =COUNTIFS('All relationships'!$G$2:$G$1227,$A4,'All relationships'!$B$2:$B$1227,"Dentsu",'All relationships'!$K$2:$K$1227,"<>Recently lost") -> 4 | F4: =COUNTIFS('All relationships'!$G$2:$G$1227,$A4,'All relationships'!$B$2:$B$1227,"Havas",'All relationships'!$K$2:$K$1227,"<>Recently lost") -> 0 | G4: =COUNTIFS('All relationships'!$G$2:$G$1227,$A4,'All relationships'!$B$2:$B$1227,"Cheil",'All relationships'!$K$2:$K$1227,"<>Recently lost") -> 1 | H4: =COUNTIFS('All relationships'!$G$2:$G$1227,$A4,'All relationships'!$B$2:$B$1227,"Hakuhodo",'All relationships'!$K$2:$K$1227,"<>Recently lost") -> 0 | I4: =COUNTIFS('All relationships'!$G$2:$G$1227,$A4,'All relationships'!$B$2:$B$1227,"Independent",'All relationships'!$K$2:$K$1227,"<>Recently lost") -> 24 | J4: =COUNTIFS('All relationships'!$G$2:$G$1227,$A4,'All relationships'!$B$2:$B$1227,"Other",'All relationships'!$K$2:$K$1227,"<>Recently lost") -> 0 | K4: =COUNTIFS('All relationships'!$G$2:$G$1227,$A4,'All relationships'!$B$2:$B$1227,"Unknown",'All relationships'!$K$2:$K$1227,"<>Recently lost") -> 19 | L4: =SUM(B4:K4) -> 62
A5: Jewellery & watches | B5: =COUNTIFS('All relationships'!$G$2:$G$1227,$A5,'All relationships'!$B$2:$B$1227,"WPP",'All relationships'!$K$2:$K$1227,"<>Recently lost") -> 7 | C5: =COUNTIFS('All relationships'!$G$2:$G$1227,$A5,'All relationships'!$B$2:$B$1227,"Publicis",'All relationships'!$K$2:$K$1227,"<>Recently lost") -> 1 | D5: =COUNTIFS('All relationships'!$G$2:$G$1227,$A5,'All relationships'!$B$2:$B$1227,"Omnicom",'All relationships'!$K$2:$K$1227,"<>Recently lost") -> 6 | E5: =COUNTIFS('All relationships'!$G$2:$G$1227,$A5,'All relationships'!$B$2:$B$1227,"Dentsu",'All relationships'!$K$2:$K$1227,"<>Recently lost") -> 3 | F5: =COUNTIFS('All relationships'!$G$2:$G$1227,$A5,'All relationships'!$B$2:$B$1227,"Havas",'All relationships'!$K$2:$K$1227,"<>Recently lost") -> 2 | G5: =COUNTIFS('All relationships'!$G$2:$G$1227,$A5,'All relationships'!$B$2:$B$1227,"Cheil",'All relationships'!$K$2:$K$1227,"<>Recently lost") -> 1 | H5: =COUNTIFS('All relationships'!$G$2:$G$1227,$A5,'All relationships'!$B$2:$B$1227,"Hakuhodo",'All relationships'!$K$2:$K$1227,"<>Recently lost") -> 0 | I5: =COUNTIFS('All relationships'!$G$2:$G$1227,$A5,'All relationships'!$B$2:$B$1227,"Independent",'All relationships'!$K$2:$K$1227,"<>Recently lost") -> 32 | J5: =COUNTIFS('All relationships'!$G$2:$G$1227,$A5,'All relationships'!$B$2:$B$1227,"Other",'All relationships'!$K$2:$K$1227,"<>Recently lost") -> 1 | K5: =COUNTIFS('All relationships'!$G$2:$G$1227,$A5,'All relationships'!$B$2:$B$1227,"Unknown",'All relationships'!$K$2:$K$1227,"<>Recently lost") -> 24 | L5: =SUM(B5:K5) -> 77
A6: Fashion & luxury retail | B6: =COUNTIFS('All relationships'!$G$2:$G$1227,$A6,'All relationships'!$B$2:$B$1227,"WPP",'All relationships'!$K$2:$K$1227,"<>Recently lost") -> 8 | C6: =COUNTIFS('All relationships'!$G$2:$G$1227,$A6,'All relationships'!$B$2:$B$1227,"Publicis",'All relationships'!$K$2:$K$1227,"<>Recently lost") -> 3 | D6: =COUNTIFS('All relationships'!$G$2:$G$1227,$A6,'All relationships'!$B$2:$B$1227,"Omnicom",'All relationships'!$K$2:$K$1227,"<>Recently lost") -> 18 | E6: =COUNTIFS('All relationships'!$G$2:$G$1227,$A6,'All relationships'!$B$2:$B$1227,"Dentsu",'All relationships'!$K$2:$K$1227,"<>Recently lost") -> 3 | F6: =COUNTIFS('All relationships'!$G$2:$G$1227,$A6,'All relationships'!$B$2:$B$1227,"Havas",'All relationships'!$K$2:$K$1227,"<>Recently lost") -> 0 | G6: =COUNTIFS('All relationships'!$G$2:$G$1227,$A6,'All relationships'!$B$2:$B$1227,"Cheil",'All relationships'!$K$2:$K$1227,"<>Recently lost") -> 1 | H6: =COUNTIFS('All relationships'!$G$2:$G$1227,$A6,'All relationships'!$B$2:$B$1227,"Hakuhodo",'All relationships'!$K$2:$K$1227,"<>Recently lost") -> 0 | I6: =COUNTIFS('All relationships'!$G$2:$G$1227,$A6,'All relationships'!$B$2:$B$1227,"Independent",'All relationships'!$K$2:$K$1227,"<>Recently lost") -> 71 | J6: =COUNTIFS('All relationships'!$G$2:$G$1227,$A6,'All relationships'!$B$2:$B$1227,"Other",'All relationships'!$K$2:$K$1227,"<>Recently lost") -> 0 | K6: =COUNTIFS('All relationships'!$G$2:$G$1227,$A6,'All relationships'!$B$2:$B$1227,"Unknown",'All relationships'!$K$2:$K$1227,"<>Recently lost") -> 22 | L6: =SUM(B6:K6) -> 126
A7: Real estate | B7: =COUNTIFS('All relationships'!$G$2:$G$1227,$A7,'All relationships'!$B$2:$B$1227,"WPP",'All relationships'!$K$2:$K$1227,"<>Recently lost") -> 4 | C7: =COUNTIFS('All relationships'!$G$2:$G$1227,$A7,'All relationships'!$B$2:$B$1227,"Publicis",'All relationships'!$K$2:$K$1227,"<>Recently lost") -> 0 | D7: =COUNTIFS('All relationships'!$G$2:$G$1227,$A7,'All relationships'!$B$2:$B$1227,"Omnicom",'All relationships'!$K$2:$K$1227,"<>Recently lost") -> 7 | E7: =COUNTIFS('All relationships'!$G$2:$G$1227,$A7,'All relationships'!$B$2:$B$1227,"Dentsu",'All relationships'!$K$2:$K$1227,"<>Recently lost") -> 0 | F7: =COUNTIFS('All relationships'!$G$2:$G$1227,$A7,'All relationships'!$B$2:$B$1227,"Havas",'All relationships'!$K$2:$K$1227,"<>Recently lost") -> 1 | G7: =COUNTIFS('All relationships'!$G$2:$G$1227,$A7,'All relationships'!$B$2:$B$1227,"Cheil",'All relationships'!$K$2:$K$1227,"<>Recently lost") -> 2 | H7: =COUNTIFS('All relationships'!$G$2:$G$1227,$A7,'All relationships'!$B$2:$B$1227,"Hakuhodo",'All relationships'!$K$2:$K$1227,"<>Recently lost") -> 0 | I7: =COUNTIFS('All relationships'!$G$2:$G$1227,$A7,'All relationships'!$B$2:$B$1227,"Independent",'All relationships'!$K$2:$K$1227,"<>Recently lost") -> 21 | J7: =COUNTIFS('All relationships'!$G$2:$G$1227,$A7,'All relationships'!$B$2:$B$1227,"Other",'All relationships'!$K$2:$K$1227,"<>Recently lost") -> 0 | K7: =COUNTIFS('All relationships'!$G$2:$G$1227,$A7,'All relationships'!$B$2:$B$1227,"Unknown",'All relationships'!$K$2:$K$1227,"<>Recently lost") -> 30 | L7: =SUM(B7:K7) -> 65
A8: Beauty & personal care | B8: =COUNTIFS('All relationships'!$G$2:$G$1227,$A8,'All relationships'!$B$2:$B$1227,"WPP",'All relationships'!$K$2:$K$1227,"<>Recently lost") -> 4 | C8: =COUNTIFS('All relationships'!$G$2:$G$1227,$A8,'All relationships'!$B$2:$B$1227,"Publicis",'All relationships'!$K$2:$K$1227,"<>Recently lost") -> 4 | D8: =COUNTIFS('All relationships'!$G$2:$G$1227,$A8,'All relationships'!$B$2:$B$1227,"Omnicom",'All relationships'!$K$2:$K$1227,"<>Recently lost") -> 8 | E8: =COUNTIFS('All relationships'!$G$2:$G$1227,$A8,'All relationships'!$B$2:$B$1227,"Dentsu",'All relationships'!$K$2:$K$1227,"<>Recently lost") -> 2 | F8: =COUNTIFS('All relationships'!$G$2:$G$1227,$A8,'All relationships'!$B$2:$B$1227,"Havas",'All relationships'!$K$2:$K$1227,"<>Recently lost") -> 4 | G8: =COUNTIFS('All relationships'!$G$2:$G$1227,$A8,'All relationships'!$B$2:$B$1227,"Cheil",'All relationships'!$K$2:$K$1227,"<>Recently lost") -> 1 | H8: =COUNTIFS('All relationships'!$G$2:$G$1227,$A8,'All relationships'!$B$2:$B$1227,"Hakuhodo",'All relationships'!$K$2:$K$1227,"<>Recently lost") -> 0 | I8: =COUNTIFS('All relationships'!$G$2:$G$1227,$A8,'All relationships'!$B$2:$B$1227,"Independent",'All relationships'!$K$2:$K$1227,"<>Recently lost") -> 43 | J8: =COUNTIFS('All relationships'!$G$2:$G$1227,$A8,'All relationships'!$B$2:$B$1227,"Other",'All relationships'!$K$2:$K$1227,"<>Recently lost") -> 0 | K8: =COUNTIFS('All relationships'!$G$2:$G$1227,$A8,'All relationships'!$B$2:$B$1227,"Unknown",'All relationships'!$K$2:$K$1227,"<>Recently lost") -> 18 | L8: =SUM(B8:K8) -> 84
A9: Alcobev | B9: =COUNTIFS('All relationships'!$G$2:$G$1227,$A9,'All relationships'!$B$2:$B$1227,"WPP",'All relationships'!$K$2:$K$1227,"<>Recently lost") -> 8 | C9: =COUNTIFS('All relationships'!$G$2:$G$1227,$A9,'All relationships'!$B$2:$B$1227,"Publicis",'All relationships'!$K$2:$K$1227,"<>Recently lost") -> 4 | D9: =COUNTIFS('All relationships'!$G$2:$G$1227,$A9,'All relationships'!$B$2:$B$1227,"Omnicom",'All relationships'!$K$2:$K$1227,"<>Recently lost") -> 9 | E9: =COUNTIFS('All relationships'!$G$2:$G$1227,$A9,'All relationships'!$B$2:$B$1227,"Dentsu",'All relationships'!$K$2:$K$1227,"<>Recently lost") -> 1 | F9: =COUNTIFS('All relationships'!$G$2:$G$1227,$A9,'All relationships'!$B$2:$B$1227,"Havas",'All relationships'!$K$2:$K$1227,"<>Recently lost") -> 0 | G9: =COUNTIFS('All relationships'!$G$2:$G$1227,$A9,'All relationships'!$B$2:$B$1227,"Cheil",'All relationships'!$K$2:$K$1227,"<>Recently lost") -> 0 | H9: =COUNTIFS('All relationships'!$G$2:$G$1227,$A9,'All relationships'!$B$2:$B$1227,"Hakuhodo",'All relationships'!$K$2:$K$1227,"<>Recently lost") -> 5 | I9: =COUNTIFS('All relationships'!$G$2:$G$1227,$A9,'All relationships'!$B$2:$B$1227,"Independent",'All relationships'!$K$2:$K$1227,"<>Recently lost") -> 20 | J9: =COUNTIFS('All relationships'!$G$2:$G$1227,$A9,'All relationships'!$B$2:$B$1227,"Other",'All relationships'!$K$2:$K$1227,"<>Recently lost") -> 2 | K9: =COUNTIFS('All relationships'!$G$2:$G$1227,$A9,'All relationships'!$B$2:$B$1227,"Unknown",'All relationships'!$K$2:$K$1227,"<>Recently lost") -> 18 | L9: =SUM(B9:K9) -> 67
A10: Automotive | B10: =COUNTIFS('All relationships'!$G$2:$G$1227,$A10,'All relationships'!$B$2:$B$1227,"WPP",'All relationships'!$K$2:$K$1227,"<>Recently lost") -> 12 | C10: =COUNTIFS('All relationships'!$G$2:$G$1227,$A10,'All relationships'!$B$2:$B$1227,"Publicis",'All relationships'!$K$2:$K$1227,"<>Recently lost") -> 8 | D10: =COUNTIFS('All relationships'!$G$2:$G$1227,$A10,'All relationships'!$B$2:$B$1227,"Omnicom",'All relationships'!$K$2:$K$1227,"<>Recently lost") -> 25 | E10: =COUNTIFS('All relationships'!$G$2:$G$1227,$A10,'All relationships'!$B$2:$B$1227,"Dentsu",'All relationships'!$K$2:$K$1227,"<>Recently lost") -> 7 | F10: =COUNTIFS('All relationships'!$G$2:$G$1227,$A10,'All relationships'!$B$2:$B$1227,"Havas",'All relationships'!$K$2:$K$1227,"<>Recently lost") -> 1 | G10: =COUNTIFS('All relationships'!$G$2:$G$1227,$A10,'All relationships'!$B$2:$B$1227,"Cheil",'All relationships'!$K$2:$K$1227,"<>Recently lost") -> 4 | H10: =COUNTIFS('All relationships'!$G$2:$G$1227,$A10,'All relationships'!$B$2:$B$1227,"Hakuhodo",'All relationships'!$K$2:$K$1227,"<>Recently lost") -> 8 | I10: =COUNTIFS('All relationships'!$G$2:$G$1227,$A10,'All relationships'!$B$2:$B$1227,"Independent",'All relationships'!$K$2:$K$1227,"<>Recently lost") -> 25 | J10: =COUNTIFS('All relationships'!$G$2:$G$1227,$A10,'All relationships'!$B$2:$B$1227,"Other",'All relationships'!$K$2:$K$1227,"<>Recently lost") -> 2 | K10: =COUNTIFS('All relationships'!$G$2:$G$1227,$A10,'All relationships'!$B$2:$B$1227,"Unknown",'All relationships'!$K$2:$K$1227,"<>Recently lost") -> 15 | L10: =SUM(B10:K10) -> 107
A11: Wellness, fitness & sport | B11: =COUNTIFS('All relationships'!$G$2:$G$1227,$A11,'All relationships'!$B$2:$B$1227,"WPP",'All relationships'!$K$2:$K$1227,"<>Recently lost") -> 1 | C11: =COUNTIFS('All relationships'!$G$2:$G$1227,$A11,'All relationships'!$B$2:$B$1227,"Publicis",'All relationships'!$K$2:$K$1227,"<>Recently lost") -> 2 | D11: =COUNTIFS('All relationships'!$G$2:$G$1227,$A11,'All relationships'!$B$2:$B$1227,"Omnicom",'All relationships'!$K$2:$K$1227,"<>Recently lost") -> 5 | E11: =COUNTIFS('All relationships'!$G$2:$G$1227,$A11,'All relationships'!$B$2:$B$1227,"Dentsu",'All relationships'!$K$2:$K$1227,"<>Recently lost") -> 0 | F11: =COUNTIFS('All relationships'!$G$2:$G$1227,$A11,'All relationships'!$B$2:$B$1227,"Havas",'All relationships'!$K$2:$K$1227,"<>Recently lost") -> 0 | G11: =COUNTIFS('All relationships'!$G$2:$G$1227,$A11,'All relationships'!$B$2:$B$1227,"Cheil",'All relationships'!$K$2:$K$1227,"<>Recently lost") -> 0 | H11: =COUNTIFS('All relationships'!$G$2:$G$1227,$A11,'All relationships'!$B$2:$B$1227,"Hakuhodo",'All relationships'!$K$2:$K$1227,"<>Recently lost") -> 0 | I11: =COUNTIFS('All relationships'!$G$2:$G$1227,$A11,'All relationships'!$B$2:$B$1227,"Independent",'All relationships'!$K$2:$K$1227,"<>Recently lost") -> 9 | J11: =COUNTIFS('All relationships'!$G$2:$G$1227,$A11,'All relationships'!$B$2:$B$1227,"Other",'All relationships'!$K$2:$K$1227,"<>Recently lost") -> 0 | K11: =COUNTIFS('All relationships'!$G$2:$G$1227,$A11,'All relationships'!$B$2:$B$1227,"Unknown",'All relationships'!$K$2:$K$1227,"<>Recently lost") -> 10 | L11: =SUM(B11:K11) -> 27
A12: BFSI & wealth | B12: =COUNTIFS('All relationships'!$G$2:$G$1227,$A12,'All relationships'!$B$2:$B$1227,"WPP",'All relationships'!$K$2:$K$1227,"<>Recently lost") -> 8 | C12: =COUNTIFS('All relationships'!$G$2:$G$1227,$A12,'All relationships'!$B$2:$B$1227,"Publicis",'All relationships'!$K$2:$K$1227,"<>Recently lost") -> 9 | D12: =COUNTIFS('All relationships'!$G$2:$G$1227,$A12,'All relationships'!$B$2:$B$1227,"Omnicom",'All relationships'!$K$2:$K$1227,"<>Recently lost") -> 26 | E12: =COUNTIFS('All relationships'!$G$2:$G$1227,$A12,'All relationships'!$B$2:$B$1227,"Dentsu",'All relationships'!$K$2:$K$1227,"<>Recently lost") -> 4 | F12: =COUNTIFS('All relationships'!$G$2:$G$1227,$A12,'All relationships'!$B$2:$B$1227,"Havas",'All relationships'!$K$2:$K$1227,"<>Recently lost") -> 3 | G12: =COUNTIFS('All relationships'!$G$2:$G$1227,$A12,'All relationships'!$B$2:$B$1227,"Cheil",'All relationships'!$K$2:$K$1227,"<>Recently lost") -> 1 | H12: =COUNTIFS('All relationships'!$G$2:$G$1227,$A12,'All relationships'!$B$2:$B$1227,"Hakuhodo",'All relationships'!$K$2:$K$1227,"<>Recently lost") -> 0 | I12: =COUNTIFS('All relationships'!$G$2:$G$1227,$A12,'All relationships'!$B$2:$B$1227,"Independent",'All relationships'!$K$2:$K$1227,"<>Recently lost") -> 40 | J12: =COUNTIFS('All relationships'!$G$2:$G$1227,$A12,'All relationships'!$B$2:$B$1227,"Other",'All relationships'!$K$2:$K$1227,"<>Recently lost") -> 1 | K12: =COUNTIFS('All relationships'!$G$2:$G$1227,$A12,'All relationships'!$B$2:$B$1227,"Unknown",'All relationships'!$K$2:$K$1227,"<>Recently lost") -> 25 | L12: =SUM(B12:K12) -> 117
A13: Premium F&B & QSR | B13: =COUNTIFS('All relationships'!$G$2:$G$1227,$A13,'All relationships'!$B$2:$B$1227,"WPP",'All relationships'!$K$2:$K$1227,"<>Recently lost") -> 1 | C13: =COUNTIFS('All relationships'!$G$2:$G$1227,$A13,'All relationships'!$B$2:$B$1227,"Publicis",'All relationships'!$K$2:$K$1227,"<>Recently lost") -> 4 | D13: =COUNTIFS('All relationships'!$G$2:$G$1227,$A13,'All relationships'!$B$2:$B$1227,"Omnicom",'All relationships'!$K$2:$K$1227,"<>Recently lost") -> 10 | E13: =COUNTIFS('All relationships'!$G$2:$G$1227,$A13,'All relationships'!$B$2:$B$1227,"Dentsu",'All relationships'!$K$2:$K$1227,"<>Recently lost") -> 3 | F13: =COUNTIFS('All relationships'!$G$2:$G$1227,$A13,'All relationships'!$B$2:$B$1227,"Havas",'All relationships'!$K$2:$K$1227,"<>Recently lost") -> 2 | G13: =COUNTIFS('All relationships'!$G$2:$G$1227,$A13,'All relationships'!$B$2:$B$1227,"Cheil",'All relationships'!$K$2:$K$1227,"<>Recently lost") -> 0 | H13: =COUNTIFS('All relationships'!$G$2:$G$1227,$A13,'All relationships'!$B$2:$B$1227,"Hakuhodo",'All relationships'!$K$2:$K$1227,"<>Recently lost") -> 0 | I13: =COUNTIFS('All relationships'!$G$2:$G$1227,$A13,'All relationships'!$B$2:$B$1227,"Independent",'All relationships'!$K$2:$K$1227,"<>Recently lost") -> 20 | J13: =COUNTIFS('All relationships'!$G$2:$G$1227,$A13,'All relationships'!$B$2:$B$1227,"Other",'All relationships'!$K$2:$K$1227,"<>Recently lost") -> 0 | K13: =COUNTIFS('All relationships'!$G$2:$G$1227,$A13,'All relationships'!$B$2:$B$1227,"Unknown",'All relationships'!$K$2:$K$1227,"<>Recently lost") -> 8 | L13: =SUM(B13:K13) -> 48
A14: Aviation | B14: =COUNTIFS('All relationships'!$G$2:$G$1227,$A14,'All relationships'!$B$2:$B$1227,"WPP",'All relationships'!$K$2:$K$1227,"<>Recently lost") -> 1 | C14: =COUNTIFS('All relationships'!$G$2:$G$1227,$A14,'All relationships'!$B$2:$B$1227,"Publicis",'All relationships'!$K$2:$K$1227,"<>Recently lost") -> 0 | D14: =COUNTIFS('All relationships'!$G$2:$G$1227,$A14,'All relationships'!$B$2:$B$1227,"Omnicom",'All relationships'!$K$2:$K$1227,"<>Recently lost") -> 3 | E14: =COUNTIFS('All relationships'!$G$2:$G$1227,$A14,'All relationships'!$B$2:$B$1227,"Dentsu",'All relationships'!$K$2:$K$1227,"<>Recently lost") -> 0 | F14: =COUNTIFS('All relationships'!$G$2:$G$1227,$A14,'All relationships'!$B$2:$B$1227,"Havas",'All relationships'!$K$2:$K$1227,"<>Recently lost") -> 0 | G14: =COUNTIFS('All relationships'!$G$2:$G$1227,$A14,'All relationships'!$B$2:$B$1227,"Cheil",'All relationships'!$K$2:$K$1227,"<>Recently lost") -> 0 | H14: =COUNTIFS('All relationships'!$G$2:$G$1227,$A14,'All relationships'!$B$2:$B$1227,"Hakuhodo",'All relationships'!$K$2:$K$1227,"<>Recently lost") -> 0 | I14: =COUNTIFS('All relationships'!$G$2:$G$1227,$A14,'All relationships'!$B$2:$B$1227,"Independent",'All relationships'!$K$2:$K$1227,"<>Recently lost") -> 1 | J14: =COUNTIFS('All relationships'!$G$2:$G$1227,$A14,'All relationships'!$B$2:$B$1227,"Other",'All relationships'!$K$2:$K$1227,"<>Recently lost") -> 0 | K14: =COUNTIFS('All relationships'!$G$2:$G$1227,$A14,'All relationships'!$B$2:$B$1227,"Unknown",'All relationships'!$K$2:$K$1227,"<>Recently lost") -> 3 | L14: =SUM(B14:K14) -> 8
A15: Consumer tech & D2C | B15: =COUNTIFS('All relationships'!$G$2:$G$1227,$A15,'All relationships'!$B$2:$B$1227,"WPP",'All relationships'!$K$2:$K$1227,"<>Recently lost") -> 2 | C15: =COUNTIFS('All relationships'!$G$2:$G$1227,$A15,'All relationships'!$B$2:$B$1227,"Publicis",'All relationships'!$K$2:$K$1227,"<>Recently lost") -> 9 | D15: =COUNTIFS('All relationships'!$G$2:$G$1227,$A15,'All relationships'!$B$2:$B$1227,"Omnicom",'All relationships'!$K$2:$K$1227,"<>Recently lost") -> 14 | E15: =COUNTIFS('All relationships'!$G$2:$G$1227,$A15,'All relationships'!$B$2:$B$1227,"Dentsu",'All relationships'!$K$2:$K$1227,"<>Recently lost") -> 6 | F15: =COUNTIFS('All relationships'!$G$2:$G$1227,$A15,'All relationships'!$B$2:$B$1227,"Havas",'All relationships'!$K$2:$K$1227,"<>Recently lost") -> 1 | G15: =COUNTIFS('All relationships'!$G$2:$G$1227,$A15,'All relationships'!$B$2:$B$1227,"Cheil",'All relationships'!$K$2:$K$1227,"<>Recently lost") -> 2 | H15: =COUNTIFS('All relationships'!$G$2:$G$1227,$A15,'All relationships'!$B$2:$B$1227,"Hakuhodo",'All relationships'!$K$2:$K$1227,"<>Recently lost") -> 0 | I15: =COUNTIFS('All relationships'!$G$2:$G$1227,$A15,'All relationships'!$B$2:$B$1227,"Independent",'All relationships'!$K$2:$K$1227,"<>Recently lost") -> 35 | J15: =COUNTIFS('All relationships'!$G$2:$G$1227,$A15,'All relationships'!$B$2:$B$1227,"Other",'All relationships'!$K$2:$K$1227,"<>Recently lost") -> 0 | K15: =COUNTIFS('All relationships'!$G$2:$G$1227,$A15,'All relationships'!$B$2:$B$1227,"Unknown",'All relationships'!$K$2:$K$1227,"<>Recently lost") -> 10 | L15: =SUM(B15:K15) -> 79
... A21: Education | B21: =COUNTIFS('All relationships'!$G$2:$G$1227,$A21,'All relationships'!$B$2:$B$1227,"WPP",'All relationships'!$K$2:$K$1227,"<>Recently lost") -> 0 | C21: =COUNTIFS('All relationships'!$G$2:$G$1227,$A21,'All relationships'!$B$2:$B$1227,"Publicis",'All relationships'!$K$2:$K$1227,"<>Recently lost") -> 4 | D21: =COUNTIFS('All relationships'!$G$2:$G$1227,$A21,'All relationships'!$B$2:$B$1227,"Omnicom",'All relationships'!$K$2:$K$1227,"<>Recently lost") -> 2 | E21: =COUNTIFS('All relationships'!$G$2:$G$1227,$A21,'All relationships'!$B$2:$B$1227,"Dentsu",'All relationships'!$K$2:$K$1227,"<>Recently lost") -> 0 | F21: =COUNTIFS('All relationships'!$G$2:$G$1227,$A21,'All relationships'!$B$2:$B$1227,"Havas",'All relationships'!$K$2:$K$1227,"<>Recently lost") -> 2 | G21: =COUNTIFS('All relationships'!$G$2:$G$1227,$A21,'All relationships'!$B$2:$B$1227,"Cheil",'All relationships'!$K$2:$K$1227,"<>Recently lost") -> 1 | H21: =COUNTIFS('All relationships'!$G$2:$G$1227,$A21,'All relationships'!$B$2:$B$1227,"Hakuhodo",'All relationships'!$K$2:$K$1227,"<>Recently lost") -> 0 | I21: =COUNTIFS('All relationships'!$G$2:$G$1227,$A21,'All relationships'!$B$2:$B$1227,"Independent",'All relationships'!$K$2:$K$1227,"<>Recently lost") -> 7 | J21: =COUNTIFS('All relationships'!$G$2:$G$1227,$A21,'All relationships'!$B$2:$B$1227,"Other",'All relationships'!$K$2:$K$1227,"<>Recently lost") -> 0 | K21: =COUNTIFS('All relationships'!$G$2:$G$1227,$A21,'All relationships'!$B$2:$B$1227,"Unknown",'All relationships'!$K$2:$K$1227,"<>Recently lost") -> 0 | L21: =SUM(B21:K21) -> 16
A22: Total | B22: =SUM(B4:B21) -> 110 | C22: =SUM(C4:C21) -> 81 | D22: =SUM(D4:D21) -> 227 | E22: =SUM(E4:E21) -> 47 | F22: =SUM(F4:F21) -> 23 | G22: =SUM(G4:G21) -> 18 | H22: =SUM(H4:H21) -> 15 | I22: =SUM(I4:I21) -> 448 | ... L22: =SUM(L4:L21) -> 1188

Sheet All relationships
A1: Agency (current name) | B1: Agency group | C1: Agency type | D1: Brand | E1: Brand as reported | F1: Parent company | G1: Category | H1: Brand tier | I1: Mandate | J1: Since | K1: Status | L1: Evidence | M1: Poaching signals | N1: Source | O1: Source date | P1: Confidence | Q1: Agency as reported | R1: Research stream
A2: Burson India | B2: WPP | C2: PR | D2: Chalet Hotels (Athiva) | E2: Chalet Hotels (JW Marriott Mumbai Sahar, Westin, Athiva) | F2: Chalet Hotels Ltd (K Raheja) | G2: Luxury hospitality & travel | H2: Luxury | I2: PR | J2: 2026-06 | K2: Won recently | L2: Burson won Chalet Hotels' reputation mandate covering corporate narrative, ESG and its Athiva Hotels & Resorts brand. | M2: PR only; new Athiva brand launch needs social, content and luxury creative.; WPP explored a sale of Burson (afaqs Apr 2026); Athiva brand social and creative not assigned publicly.; WPP hired Goldman Sachs in Apr 2026 to explore a sale of Burson | N2: https://www.campaignindia.in/article/burson-wins-chalet-hotels-reputation-mandate/4xy9ew13ahvn7sn61tt41mbhx7 | O2: 2026-06 | P2: High | Q2: Burson | R2: Brands: travel, realty, auto, BFSI
A3: Burson India | B3: WPP | C3: PR | D3: Ducati India | E3: Ducati India | F3: Ducati (Audi AG) | G3: Automotive | H3: Luxury | I3: PR | J3: 2024-09 | K3: Active | L3: Ducati India appointed Burson as strategic communications partner for brand positioning and reputation in Sep 2024. | M3: WPP hired Goldman Sachs in Apr 2026 to explore a sale of Burson | N3: https://www.medianews4u.com/ducati-india-appoints-burson-as-strategic-communications-partner/ | O3: 2024-09 | P3: High | Q3: Burson Group India | R3: WPP
A4: Burson India | B4: WPP | C4: PR | D4: Birla Opus Paints | E4: Birla Opus Paints | F4: Grasim Industries (Aditya Birla Group) | G4: Other | H4: Premium | I4: PR | J4: 2024-07 | K4: Active | L4: Birla Opus appointed Burson for reputation management and brand communications in India in Jul 2024. | M4: WPP hired Goldman Sachs in Apr 2026 to explore a sale of Burson | N4: https://www.medianews4u.com/birla-opus-paints-appoints-burson-for-reputation-management-and-brand-communications-in-india/ | O4: 2024-07 | P4: High | Q4: Burson Group India | R4: WPP
A5: Burson India | B5: WPP | C5: PR | D5: Honda Cars India | E5: Honda Cars India | F5: Honda Motor Co | G5: Automotive | H5: Premium | I5: PR | J5: 2025-05 | K5: Active | L5: Burson appointed strategic communications partner for Honda Cars India providing integrated communications support. | M5: PR only; creative and social sit elsewhere.; WPP hired Goldman Sachs in Apr 2026 to explore a sale of Burson | N5: https://www.afaqs.com/news/newbizwins/honda-cars-india-appoints-burson-as-strategic-communications-partner-9064438 | O5: 2025-05 | P5: High | Q5: Burson | R5: Brands: travel, realty, auto, BFSI
A6: Burson India | B6: WPP | C6: PR | D6: Mirae Asset Sharekhan | E6: Mirae Asset Sharekhan | F6: Mirae Asset | G6: BFSI & wealth | H6: Premium | I6: PR | J6: 2025-11 | K6: Active | L6: Mirae Asset Sharekhan named Burson as its communications partner in Nov 2025. | M6: WPP hired Goldman Sachs in Apr 2026 to explore a sale of Burson | N6: https://www.medianews4u.com/mirae-asset-sharekhan-names-burson-as-communications-partner/ | O6: 2025-11 | P6: High | Q6: Burson Group India | R6: WPP
A7: Burson India | B7: WPP | C7: PR | D7: Eastman Auto & Power | E7: Eastman Auto & Power | F7: Eastman Auto & Power Ltd | G7: Other | H7: Mass | I7: PR | J7: 2024-12 | K7: Active | L7: Eastman Auto & Power partnered Burson to enhance brand presence in Dec 2024. | M7: WPP hired Goldman Sachs in Apr 2026 to explore a sale of Burson | N7: https://www.medianews4u.com/eastman-auto-power-partners-with-burson-to-enhance-brand-presence/ | O7: 2024-12 | P7: High | Q7: Burson Group India | R7: WPP
A8: Contract Advertising (VML) | B8: WPP | C8: Network creative | D8: BMW India | E8: BMW India | F8: BMW Group | G8: Automotive | H8: Luxury | I8: Integrated | J8: 2026-01 | K8: Won recently | L8: BMW India awarded integrated creative mandate (mainline plus digital) to VML's Contract Advertising after a competitive pitch, replacing Rediffusion. | M8: New incumbent, low near-term poachability; but social, content, experiential and dealer content can be carved out.; Account moved 2026-01 from Rediffusion; marketing director Vitesh Barar; WPP creative restructuring ongoing; Newly won in pitch; VML India creative head who oversaw Contract (Kalpesh Patankar) exited Aug 2026; Fresh pitch Jan 2026; MINI digital split out to SW Network; WPP network restructuring. | N8: https://www.storyboard18.com/agency-news/exclusive-bmw-india-appoints-vmls-contract-advertising-india-as-creative-agency-87842.htm | O8: 2026-01 | P8: High | Q8: Contract Advertising India (VML) | R8: Brands: travel, realty, auto, BFSI
A9: Contract Advertising (VML) | B9: WPP | C9: Network creative | D9: HSBC India | E9: HSBC India | F9: HSBC | G9: BFSI & wealth | H9: Premium | I9: Creative | J9: unknown | K9: Unclear | L9: Contract Advertising created HSBC India's 'My Account Starts Today' film with Virat Kohli in Jun 2023. | M9: No recent credit visible | N9: https://campaignbriefasia.com/2023/06/06/contract-advertising-creates-my-account-starts-today-for-hsbc-india-starring-virat-kohli/ | O9: 2023-06 | P9: Medium | Q9: Contract Advertising India (VML) | R9: WPP
A10: Contract Advertising (VML) | B10: WPP | C10: Network creative | D10: KISNA | E10: KISNA | F10: Hari Krishna Group | G10: Jewellery & watches | H10: Premium | I10: Creative | J10: 2022 | K10: Unclear | L10: Contract Advertising launched KISNA's brand re-stage campaign (Nov 2022); Aug 2026 Gen Z 9KT campaign has no agency credit. | M10: New CMO Prashant Awasthi (Sep 2025); new CFO and CTO 2026; Gen Z push; No recent credit visible | N10: https://www.medianews4u.com/contract-advertising-launches-brand-re-stage-campaign-for-kisna/ | O10: 2022-11 | P10: Medium | Q10: Contract Advertising | R10: Brands: jewellery, fashion, beauty, alcobev
A11: Contract Advertising (VML) | B11: WPP | C11: Network creative | D11: L&T Realty | E11: L&T Realty | F11: Larsen & Toubro | G11: Real estate | H11: Premium | I11: Creative | J11: unknown | K11: Unclear | L11: Contract Advertising made an L&T Realty film on trust and relationships in Dec 2021. | M11: No recent credit visible | N11: https://www.medianews4u.com/contract-advertisings-new-film-for-lt-realty-puts-the-spotlight-on-trust-and-relationships/ | O11: 2021-12 | P11: Medium | Q11: Contract Advertising India (VML) | R11: WPP
A12: Contract Advertising (VML) | B12: WPP | C12: Network creative | D12: Shoppers Stop | E12: Shoppers Stop | F12: Shoppers Stop Ltd | G12: Fashion & luxury retail | H12: Premium | I12: Creative | J12: 2019 | K12: Unclear | L12: Contract Advertising made Shoppers Stop women's campaigns in 2019 and May 2022. | M12: Long association, no recent credit visible | N12: https://campaignbriefasia.com/2022/05/10/contract-advertising-india-explores-the-changing-narrative-of-mothers-via-shoppers-stop-campaign/ | O12: 2022-05 | P12: Medium | Q12: Contract Advertising India (VML) | R12: WPP
A13: Contract Advertising (VML) | B13: WPP | C13: Network creative | D13: Haldiram's | E13: Haldiram's | F13: Haldiram's | G13: Premium F&B & QSR | H13: Mass | I13: Creative | J13: 2022-08 | K13: Unclear | L13: Contract Advertising won the Haldiram's mandate in Aug 2022. | N13: https://www.medianews4u.com/contract-advertising-wins-the-mandate-for-haldirams/ | O13: 2022-08 | P13: Medium | Q13: Contract Advertising India (VML) | R13: WPP
A14: Contract Advertising (VML) | B14: WPP | C14: Network creative | D14: Softovac | E14: Softovac | F14: LupinLife Consumer Healthcare | G14: Healthcare | H14: Mass | I14: Digital | J14: unknown | K14: Active | L14: Contract Advertising (a VML company) conceptualised the May 2026 digital first 'Kabz Ka Kabza' campaign with Varun Dhawan. | N14: https://www.medianews4u.com/varun-dhawan-headlines-softovacs-new-digital-campaign-kabz-ka-kabza-conceptualised-by-contract-advertising/ | O14: 2026-05 | P14: High | Q14: Contract Advertising India (VML) | R14: WPP
A15: Grey 82.5 (Ogilvy) | B15: WPP | C15: Network creative | D15: De Beers Forevermark | E15: De Beers Group (natural diamonds) | F15: De Beers Group | G15: Jewellery & watches | H15: Luxury | I15: Creative | J15: 2024-10 | K15: Active | L15: De Beers Group appointed 82.5 Communications for creative, retailer communications and category campaigns for natural diamonds in India. | M15: Split mandates: Forevermark creative sits with Dentsu Creative Isobar; unit now appears as Grey 82.5 (WPP consolidation).; Split mandate; 2026 De Beers India campaigns carry no agency credit; 82.5 Communications folded into Grey 82.5 in Jun 2026; team and brand transition | N15: https://www.storyboard18.com/brand-marketing/82-5-communications-wins-creative-mandate-for-de-beers-group-44868.htm | O15: 2024-10 | P15: High | Q15: 82.5 Communications | R15: Luxury, PR, events
A16: Grey 82.5 (Ogilvy) | B16: WPP | C16: Network creative | D16: Bacardi India | E16: Bacardi India (portfolio) | F16: Bacardi India | G16: Alcobev | H16: Premium | I16: Creative | J16: 2024-12 | K16: Active | L16: 82.5 Communications won Bacardi India's creative mandate for its brand portfolio after a competitive pitch (Dec 2024). | M16: New Director Marketing Goodies Narayanan (Dec 2025); Mahesh Kanchan now MD India and SEA (Jul 2026); Breezer Bold launch Sep 2026; Nearly two years in; WPP now brands the unit Grey 82.5 (restructuring). | N16: https://www.medianews4u.com/82-5-communications-wins-the-mandate-for-bacardi-indias-brands/ | O16: 2024-12 | P16: High | Q16: Grey 82.5 (formerly 82.5 Communications) | R16: Brands: jewellery, fashion, beauty, alcobev
A17: Grey 82.5 (Ogilvy) | B17: WPP | C17: Network creative | D17: Bacardi India | E17: Bacardi India brands | F17: Bacardi India | G17: Alcobev | H17: Premium | I17: Integrated | J17: 2024-12 | K17: Active | L17: 82.5 Communications won the mandate for Bacardi India's brands including upcoming launches in Dec 2024. | M17: New Bacardi India marketing director Goodies Narayanan (Dec 2025) and MD Mahesh Kanchan widened to India and SEA (Jul 2026); 82.5 Communications folded into Grey 82.5 in Jun 2026; team and brand transition | N17: https://www.medianews4u.com/82-5-communications-wins-the-mandate-for-bacardi-indias-brands/ | O17: 2024-12 | P17: High | Q17: 82.5 Communications (now Grey 82.5) | R17: WPP
A18: Grey 82.5 (Ogilvy) | B18: WPP | C18: Network creative | D18: Havells | E18: Havells | F18: Havells India | G18: Other | H18: Premium | I18: Creative | J18: 2018 | K18: Unclear | L18: Soho Square (2018) and then 82.5 Communications (Feb 2022) made Havells campaigns; no newer credit found. | M18: Long incumbency through Soho Square to 82.5 to Grey 82.5 rebrands | N18: https://campaignbriefasia.com/2022/02/09/havells-urges-their-customers-not-to-make-assumptions-based-on-peoples-appearance-via-new-82-5-communications-india-campaign/ | O18: 2022-02 | P18: Medium | Q18: 82.5 Communications (now Grey 82.5) | R18: WPP
A19: Grey 82.5 (Ogilvy) | B19: WPP | C19: Network creative | D19: Himalayan Natural Mineral Water | E19: Himalayan Natural Mineral Water | F19: Tata Consumer Products | G19: FMCG | H19: Premium | I19: Creative | J19: 2025-04 | K19: Active | L19: 82.5 won Himalayan's creative mandate in Apr 2025 and ran its Himalayan Day campaign in Sep 2025. | M19: 82.5 Communications folded into Grey 82.5 in Jun 2026; team and brand transition; Premium water, luxury hospitality adjacency | N19: https://www.medianews4u.com/82-5-communications-and-tcpl-bring-the-soul-of-the-himalayas-alive-with-himalayan-day-campaign/ | O19: 2025-09 | P19: High | Q19: 82.5 Communications (now Grey 82.5) | R19: WPP
A20: Grey 82.5 (Ogilvy) | B20: WPP | C20: Network creative | D20: Indian Craft Brewery | E20: Indian Craft Brewery | F20: Indian Craft Brewery | G20: Alcobev | H20: Premium | I20: Creative | J20: 2024-12 | K20: Unclear | L20: 82.5 Communications bagged the launch campaign mandate for Indian Craft Brewery in Dec 2024. | M20: Launch only project; ongoing brand work may be open | N20: https://www.medianews4u.com/82-5-communications-bags-the-launch-campaign-mandate-for-indian-craft-brewery/ | O20: 2024-12 | P20: High | Q20: 82.5 Communications (now Grey 82.5) | R20: WPP
A21: Grey 82.5 (Ogilvy) | B21: WPP | C21: Network creative | D21: JSW MG Motor India | E21: JSW MG Motor India | F21: JSW MG Motor India | G21: Automotive | H21: Premium | I21: Creative | J21: 2024-10 | K21: Unclear | L21: 82.5 Communications won a creative mandate for JSW MG's upcoming product campaign in Oct 2024; Cheil X made the Aug 2025 'EV Sahi Hai' campaign. | M21: Split mandate with Cheil X; new MD Anurag Mehrotra from Feb 2025; 82.5 Communications folded into Grey 82.5 in Jun 2026; team and brand transition | N21: https://www.medianews4u.com/82-5-communications-india-secures-the-creative-mandate-for-jsw-mg-motor-india/ | O21: 2024-10 | P21: High | Q21: 82.5 Communications (now Grey 82.5) | R21: WPP
A22: Grey 82.5 (Ogilvy) | B22: WPP | C22: Network creative | D22: Kajaria Ceramics | E22: Kajaria Ceramics | F22: Kajaria Ceramics Ltd | G22: Other | H22: Premium | I22: Creative | J22: 2023-08 | K22: Unclear | L22: 82.5 Communications announced a Kajaria win in Aug 2023. | M22: 82.5 Communications folded into Grey 82.5 in Jun 2026; team and brand transition | N22: https://www.medianews4u.com/82-5-communications-announces-kajaria-win/ | O22: 2023-08 | P22: Medium | Q22: 82.5 Communications (now Grey 82.5) | R22: WPP
A23: Grey 82.5 (Ogilvy) | B23: WPP | C23: Network creative | D23: Kalapuri | E23: Kalapuri | F23: Kalapuri | G23: Fashion & luxury retail | H23: Premium | I23: Experiential | J23: unknown | K23: Active | L23: 82.5 Mumbai's 'Blinkstop' for Kalapuri was a Cannes Lions 2026 Direct shortlist. | M23: Two WPP agencies credited on the same brand | N23: https://www.medianews4u.com/india-at-cannes-lions-2026-17-shortlists-and-counting-as-ogilvy-vml-lead-the-charge/ | O23: 2026-06 | P23: Medium | Q23: 82.5 Communications (Mumbai) | R23: WPP
A24: Grey 82.5 (Ogilvy) | B24: WPP | C24: Network digital | D24: MMTC-PAMP | E24: MMTC-PAMP | F24: MMTC-PAMP India | G24: Jewellery & watches | H24: Premium | I24: Digital | J24: unknown | K24: Unclear | L24: AutumnGrey made MMTC-PAMP's festive films in Oct 2022. | M24: Grey India merged into Grey 82.5 in Jun 2026 under 82.5 leadership; ex Grey India CCO Harsh Kapadia joined Code and Theory Jul 2026 | N24: https://www.medianews4u.com/mmtc-pamps-festive-films-by-autumngrey-capture-the-purity-of-emotions/ | O24: 2022-10 | P24: Medium | Q24: AutumnGrey (Grey India) | R24: WPP
A25: Grey 82.5 (Ogilvy) | B25: WPP | C25: Network digital | D25: Tanishq | E25: Tanishq | F25: Titan Company (Tata Group) | G25: Jewellery & watches | H25: Premium | I25: Creative | J25: unknown | K25: Active | L25: Autumn Grey conceptualised Tanishq's Women's Day 2025 film 'Her Choice'. | M25: Split mandate: Lowe Lintas makes Tanishq's main festive and diamond campaigns; Grey India merged into Grey 82.5 in Jun 2026 under 82.5 leadership; ex Grey India CCO Harsh Kapadia joined Code and Theory Jul 2026 | N25: https://www.afaqs.com/news/advertising/tanishq-challenges-empowerment-norms-in-womens-day-campaign-her-choice-8828061 | O25: 2025-03 | P25: High | Q25: AutumnGrey (Grey India) | R25: WPP
A26: Grey 82.5 (Ogilvy) | B26: WPP | C26: Network creative | D26: Tata Coffee Grand Cold Coffee | E26: Tata Coffee Grand Cold Coffee | F26: Tata Consumer Products | G26: FMCG | H26: Premium | I26: Creative | J26: 2025-04 | K26: Active | L26: 82.5 Communications won creative duties for Tata Coffee Grand Cold Coffee after a multi-agency pitch (Apr 2025). | M26: Recently pitched; 82.5 Communications folded into Grey 82.5 in Jun 2026; team and brand transition | N26: https://www.medianews4u.com/82-5-communications-secures-creative-mandate-for-tata-coffee-grand-cold-coffee-and-himalayan-natural-mineral-water/ | O26: 2025-04 | P26: High | Q26: Grey 82.5 (formerly 82.5 Communications) | R26: Brands: jewellery, fashion, beauty, alcobev
... A38: Mirum India (VML) | B38: WPP | C38: Network digital | D38: ibis (Accor India) | E38: ibis (Accor India) | F38: Accor | G38: Luxury hospitality & travel | H38: Mass | I38: Digital | J38: 2024-03 | K38: Active | L38: Mirum India, a VML company, won the digital mandate for ibis Hotels covering planning, media, production and campaigns. | M38: Two and a half years in; Accor's luxury brands in India are handled separately. | N38: https://www.socialsamosa.com/industry-updates/mirum-india-digital-mandate-ibis-hotels-4419184 | O38: 2024-03 | P38: High | Q38: Mirum India (VML) | R38: Brands: travel, realty, auto, BFSI
A39: Ogilvy India | B39: WPP | C39: Network creative | D39: Aqua Plumbings (Plumber Bathware, Aquini) | E39: Aqua Plumbings (Plumber Bathware, Aquini) | F39: Aqua Plumbings Pvt Ltd | G39: Other | H39: Luxury | I39: Creative | J39: 2025-06 | K39: Active | L39: Aqua Plumbings partnered Ogilvy Delhi in Jun 2025 to build its Plumber and ultra luxury Aquini bathware brands. | N39: https://www.medianews4u.com/aqua-plumbings-joins-hands-with-ogilvy-to-redefine-bathware-branding-in-india/ | O39: 2025-06 | P39: High | Q39: Ogilvy India (Ogilvy Delhi) | R39: WPP
A40: Ogilvy India | B40: WPP | C40: Network creative | D40: Asian Paints Emporio | E40: Asian Paints Emporio | F40: Asian Paints Ltd | G40: Other | H40: Luxury | I40: Creative | J40: unknown | K40: Active | L40: Ogilvy Mumbai made the Emporio luxury wood finish campaign starring Dino Morea, positioned on Italian craftsmanship. | M40: Luxury sub brand serviced by a mass team inside a long running Asian Paints relationship | N40: https://campaignbriefasia.com/2025/11/11/ogilvy-india-brings-italian-flair-to-asian-paints-emporios-latest-campaign-starring-dino-morea/ | O40: 2025-11 | P40: High | Q40: Ogilvy India | R40: WPP
A41: Ogilvy India | B41: WPP | C41: Network creative | D41: Adani Airports | E41: Adani Airports | F41: Adani Group | G41: Aviation | H41: Premium | I41: Creative | J41: unknown | K41: Active | L41: Ogilvy India made the Nov 2025 Adani Group film on human first service at its airports. | N41: https://campaignbriefasia.com/2025/11/19/adani-group-highlights-human-first-service-through-airports-via-new-ogilvy-india-film/ | O41: 2025-11 | P41: High | Q41: Ogilvy India | R41: WPP
A42: Ogilvy India | B42: WPP | C42: Network creative | D42: Allen Solly | E42: Allen Solly | F42: Aditya Birla Lifestyle Brands | G42: Fashion & luxury retail | H42: Premium | I42: Creative | J42: 2019 | K42: Active | L42: Ogilvy South conceptualised Allen Solly's 'Legs Now Turn Heads' film (Apr 2025), continuing Ogilvy's Allen Solly work since 2019. | M42: New AVP Marketing Raghuvar Seth (Apr 2026); Sania Mirza first womenswear ambassador (Sep 2025) | N42: https://www.medianews4u.com/allen-solly-elevates-mens-fashion-with-bottomwear-focused-legs-now-turn-heads-campaign/ | O42: 2025-04 | P42: High | Q42: Ogilvy South | R42: Brands: jewellery, fashion, beauty, alcobev
A43: Ogilvy India | B43: WPP | C43: Network creative | D43: Asian Paints | E43: Asian Paints | F43: Asian Paints Ltd | G43: Other | H43: Premium | I43: Integrated | J43: unknown | K43: Active | L43: Ogilvy India created Asian Paints' 'Rangon Ki Warranty' campaign in Apr 2026 plus Damp Proof and waterproofing work. | M43: Long incumbency; Ogilvy India in post Piyush Pandey era (he died Oct 2025), cut 30 to 40 jobs Sep 2025, now folded into WPP Creative India (Apr 2026) | N43: https://campaignbriefasia.com/2026/04/17/asian-paints-and-ogilvy-india-celebrate-colour-as-identity-in-new-rangon-ki-warranty-campaign/ | O43: 2026-04 | P43: High | Q43: Ogilvy India | R43: WPP
A44: Ogilvy India | B44: WPP | C44: Network creative | D44: Asian Paints Beautiful Homes | E44: Asian Paints Beautiful Homes | F44: Asian Paints Ltd | G44: Other | H44: Premium | I44: Creative | J44: unknown | K44: Active | L44: Ogilvy India showcased hassle free home painting in an Aug 2026 Beautiful Homes campaign. | N44: https://campaignbriefasia.com/2026/08/11/asian-paints-ogilvy-india-showcase-hassle-free-home-painting-with-beautiful-homes-campaign/ | O44: 2026-08 | P44: High | Q44: Ogilvy India | R44: WPP
